Workbook
Name IntervaloNomeado1: Os!$1:$1
Name IntervaloNomeado2: Os!$B$1:$AF$1

Sheet Os
A1: IdOs | B1: Contrato | C1: Obra | D1: Protocolo | E1: Produto | F1: Entrante | G1: Prev. Exec. | H1: Observacoes | I1: Conclusao | J1: Descricao | K1: Cidade | L1: ValorServico | M1: StatusOperacao | N1: RespCliente | O1: MedicaoConsolidada | P1: ValorPago | Q1: StatusMedicao | R1: StatusFinal | S1: ValorTercerizacao | T1: NPedidodeCompra | U1: Equipe | V1: NomeEquipe | W1: Lançamento | X1: CaboLancado? | Y1: InfraRealizada? | Z1: ProblemaEncontradoReparo | AA1: CausaRaiz(Reparo) | AB1: AcaoCorretiva(Reparo) | AC1: MaterialAplicado | AD1: Projeto | AE1: SituacaoAtual | AF1: Tempo | AG1: NumNF | AH1: MaterialAplicado? | AI1: Data AGRUP_Entrante | AJ1: Data AGRUP_Conclusão | AK1: Status Prazo | AL1: Ard | AM1: MotivoPerda | AN1: ResponsavelPerda | AO1: UF | AP1: POP | AQ1: Mes | AR1: Cenario | AS1: FacilidadesPlanejadas | AT1: CaixasPlanejadas | AU1: LançamentoPlanejado | AV1: TipoOs
A2: a1 | D2: 34907680 | F2: 45805 | G2: 45838 | I2: 45814 | L2: 10558.35 | M2: Concluído | Q2: NF Recebida | R2: Concluido | AF2: =IF(M2="Concluido",I2-F2,IF(M2="Cancelado",0,TODAY()-F2)) -> 197 | AO2: RN | AP2: NTL16 | AQ2: JUN-25 | AR2: C1 | AS2: 648 | AT2: 81 | AV2: Alivio Proativo
A3: a2 | D3: 35160533 | F3: 45818 | G3: 45838 | I3: 45828 | L3: 7885.35 | M3: Concluído | Q3: NF Recebida | R3: Concluido | AF3: =IF(M3="Concluido",I3-F3,IF(M3="Cancelado",0,TODAY()-F3)) -> 184 | AO3: RN | AP3: NTL17 | AQ3: JUN-25 | AR3: C1 | AS3: 504 | AT3: 63 | AV3: Alivio Proativo
A4: a3 | D4: 35213284 | F4: 45824 | G4: 45868 | I4: 45833.635 | L4: 8152.65 | M4: Concluído | Q4: NF Recebida | R4: Concluido | AF4: =IF(M4="Concluido",I4-F4,IF(M4="Cancelado",0,TODAY()-F4)) -> 178 | AO4: RN | AP4: NTL14 | AQ4: JUN-25 | AR4: C1 | AS4: 584 | AT4: 73 | AV4: Alivio Proativo
A5: a4 | D5: 35217090 | F5: 45824 | G5: 45868 | I5: 45829 | L5: 4276.8 | M5: Concluído | Q5: NF Recebida | R5: Concluido | AF5: =IF(M5="Concluido",I5-F5,IF(M5="Cancelado",0,TODAY()-F5)) -> 178 | AO5: RN | AP5: STO01 | AQ5: JUN-25 | AR5: C1 | AS5: 264 | AT5: 33 | AV5: Alivio Proativo
A6: a5 | D6: 35126349 | F6: 45818 | G6: 45838 | I6: 45821 | L6: 12563.1 | M6: Concluído | Q6: NF Recebida | R6: Concluido | AF6: =IF(M6="Concluido",I6-F6,IF(M6="Cancelado",0,TODAY()-F6)) -> 184 | AO6: RN | AP6: NTL15 | AQ6: JUN-25 | AR6: C1 | AS6: 800 | AT6: 100 | AV6: Alivio Proativo
A7: a6 | D7: 35232967 | F7: 45825 | G7: 45831 | I7: 45826 | L7: 514.8 | M7: Concluído | Q7: NF Recebida | R7: Concluido | AF7: =IF(M7="Concluido",I7-F7,IF(M7="Cancelado",0,TODAY()-F7)) -> 177 | AO7: CE | AP7: FLA05 | AQ7: JUN-25 | AR7: C3 | AS7: 8 | AT7: 1 | AV7: Alivio Proativo
A8: a7 | D8: 35240227 | F8: 45826 | G8: 45838 | I8: 45826 | L8: 514.8 | M8: Concluído | Q8: NF Recebida | R8: Concluido | AF8: =IF(M8="Concluido",I8-F8,IF(M8="Cancelado",0,TODAY()-F8)) -> 176 | AO8: RN | AP8: NTL06 | AQ8: JUN-25 | AR8: REATIVO | AS8: 8 | AT8: 1 | AV8: Alivio Reativo
A9: a8 | D9: 35237804 | F9: 45825 | G9: 45839 | H9: CABOS JÁ LANÇADOS, AGURADANDO LIBERAÇÃO PRA PODER FINALIZAR ATIVIDADE | M9: Cancelado | R9: Declinado Sem Acesso | AF9: =IF(M9="Concluido",I9-F9,IF(M9="Cancelado",0,TODAY()-F9)) -> 0 | AO9: PB | AP9: JPA00 | AQ9: JUN-25 | AR9: MDU | AS9: 8 | AT9: 1 | AV9: MDU
A10: a9 | D10: 35236516 | F10: 45825 | G10: 45838 | I10: 45833.596 | L10: 1564.2 | M10: Concluído | Q10: NF Recebida | R10: Concluido | AF10: =IF(M10="Concluido",I10-F10,IF(M10="Cancelado",0,TODAY()-F10)) -> 177 | AO10: PB | AP10: JPA00 | AQ10: JUN-25 | AR10: MDU | AS10: 8 | AT10: 1 | AV10: MDU
A11: a10 | D11: 35239625 | F11: 45826 | G11: 45839 | I11: 45835.453 | L11: 1940.4 | M11: Concluído | Q11: NF Recebida | R11: Concluido | AF11: =IF(M11="Concluido",I11-F11,IF(M11="Cancelado",0,TODAY()-F11)) -> 176 | AO11: PB | AP11: JPA00 | AQ11: JUN-25 | AR11: MDU | AS11: 16 | AT11: 2 | AV11: MDU
A12: a11 | D12: 35240907 | F12: 45826 | G12: 45832 | M12: Cancelado | R12: Declinado Sem Acesso | AF12: =IF(M12="Concluido",I12-F12,IF(M12="Cancelado",0,TODAY()-F12)) -> 0 | AO12: CE | AP12: FLA09 | AQ12: JUN-25 | AR12: REATIVO | AS12: 8 | AT12: 1 | AV12: Alivio Reativo
A13: a12 | D13: 35240874 | F13: 45826 | G13: 45838 | I13: 45833.377 | L13: 1544.4 | M13: Concluído | Q13: NF Recebida | R13: Concluido | AF13: =IF(M13="Concluido",I13-F13,IF(M13="Cancelado",0,TODAY()-F13)) -> 176 | AO13: CE | AP13: FLA12 | AQ13: JUN-25 | AR13: REATIVO | AS13: 24 | AT13: 3 | AV13: Alivio Reativo
A14: a13 | D14: 35232463 | F14: 45825 | G14: 45838 | M14: Cancelado | R14: Inviabilidade Técnica | AF14: =IF(M14="Concluido",I14-F14,IF(M14="Cancelado",0,TODAY()-F14)) -> 0 | AO14: CE | AP14: FLA22 | AQ14: JUN-25 | AR14: MDU | AS14: 64 | AT14: 8 | AV14: MDU
A15: a14 | D15: 35242081 | F15: 45826 | G15: 45838 | I15: 45826 | L15: 3496.4 | M15: Concluído | Q15: NF Recebida | R15: Concluido | AF15: =IF(M15="Concluido",I15-F15,IF(M15="Cancelado",0,TODAY()-F15)) -> 176 | AO15: CE | AP15: MCW02 | AQ15: JUN-25 | AR15: B2B | AS15: 8 | AT15: 1 | AV15: B2B
A16: a15 | D16: 35201709 | F16: 45824 | G16: 45841 | I16: 45831 | L16: 5712.09 | M16: Concluído | Q16: NF Recebida | R16: Concluido | AF16: =IF(M16="Concluido",I16-F16,IF(M16="Cancelado",0,TODAY()-F16)) -> 178 | AO16: CE | AP16: FLA16 | AQ16: JUN-25 | AR16: LPU | AS16: 0 | AT16: 0 | AV16: Const. de Redes
A17: a16 | D17: 35280769 | F17: 45831 | G17: 45868 | I17: 45839.349 | L17: 16038 | M17: Concluído | Q17: NF Recebida | R17: Concluido | AF17: =IF(M17="Concluido",I17-F17,IF(M17="Cancelado",0,TODAY()-F17)) -> 171 | AO17: CE | AP17: FLA20 | AQ17: JUN-25 | AR17: C1 | AS17: 1000 | AT17: 125 | AV17: Alivio Proativo
A18: a17 | D18: 35254508 | F18: 45828 | G18: 45840 | M18: Cancelado | R18: Inviabilidade Técnica | AF18: =IF(M18="Concluido",I18-F18,IF(M18="Cancelado",0,TODAY()-F18)) -> 0 | AO18: CE | AP18: FLA15 | AQ18: JUN-25 | AR18: MDU | AS18: 64 | AT18: 8 | AV18: MDU
A19: a18 | D19: 35256292 | F19: 45828 | G19: 45840 | M19: Cancelado | R19: Inviabilidade Técnica | AF19: =IF(M19="Concluido",I19-F19,IF(M19="Cancelado",0,TODAY()-F19)) -> 0 | AO19: CE | AP19: ESB01 | AQ19: JUN-25 | AR19: MDU | AS19: 40 | AT19: 5 | AV19: MDU
A20: a19 | D20: 35277733 | F20: 45828 | G20: 45835 | I20: 45833.371 | L20: 4849.98 | M20: Concluído | Q20: NF Recebida | R20: Concluido | AF20: =IF(M20="Concluido",I20-F20,IF(M20="Cancelado",0,TODAY()-F20)) -> 174 | AO20: PB | AP20: JPA00 | AQ20: JUN-25 | AR20: LPU | AS20: 0 | AT20: 0 | AV20: Alivio Proativo
A21: a20 | D21: 35278156 | F21: 45828 | G21: 45835 | H21: 2500m LANÇAMENTO | I21: 45835.709 | L21: 8275 | M21: Concluído | Q21: NF Recebida | R21: Concluido | AF21: =IF(M21="Concluido",I21-F21,IF(M21="Cancelado",0,TODAY()-F21)) -> 174 | AO21: RN | AP21: GOH01 | AQ21: JUN-25 | AR21: LPU | AS21: 0 | AT21: 0 | AV21: Alivio Proativo
A22: a21 | D22: 35281452 | F22: 45831 | G22: 45842 | M22: Cancelado | R22: Inviabilidade Técnica | AF22: =IF(M22="Concluido",I22-F22,IF(M22="Cancelado",0,TODAY()-F22)) -> 0 | AO22: RN | AP22: NTL17 | AQ22: JUN-25 | AR22: MDU | AS22: 16 | AT22: 2 | AV22: MDU
A23: a22 | D23: 35255930 | F23: 45828 | G23: 45840 | M23: Cancelado | R23: Inviabilidade Técnica | AF23: =IF(M23="Concluido",I23-F23,IF(M23="Cancelado",0,TODAY()-F23)) -> 0 | AO23: RN | AP23: NTL17 | AQ23: JUN-25 | AR23: MDU | AS23: 32 | AT23: 4 | AV23: MDU
A24: a23 | D24: 35255165 | F24: 45828 | G24: 45838 | I24: 45840.488 | L24: 7167.6 | M24: Concluído | Q24: NF Recebida | R24: Concluido | AF24: =IF(M24="Concluido",I24-F24,IF(M24="Cancelado",0,TODAY()-F24)) -> 174 | AO24: RN | AP24: NTL01 | AQ24: JUN-25 | AR24: C4 | AS24: 64 | AT24: 8 | AV24: Alivio Proativo
A25: a24 | D25: 35308809 | F25: 45832 | G25: 45845 | I25: 45834.632 | L25: 1029.6 | M25: Concluído | Q25: NF Recebida | R25: Concluido | AF25: =IF(M25="Concluido",I25-F25,IF(M25="Cancelado",0,TODAY()-F25)) -> 170 | AO25: RN | AP25: NTL09 | AQ25: JUN-25 | AR25: REATIVO | AS25: 16 | AT25: 2 | AV25: Alivio Reativo
A26: a25 | D26: 35079904 | F26: 45817 | G26: 45838 | I26: 45821 | L26: 14835.15 | M26: Concluído | Q26: NF Recebida | R26: Concluido | AF26: =IF(M26="Concluido",I26-F26,IF(M26="Cancelado",0,TODAY()-F26)) -> 185 | AO26: RN | AP26: NTL13 | AQ26: JUN-25 | AR26: C1 | AS26: 1000 | AT26: 125 | AV26: Alivio Proativo
A27: a26 | D27: 34911211 | F27: 45805 | G27: 45838 | I27: 45814 | L27: 10424.7 | M27: Concluído | Q27: NF Recebida | R27: Concluido | AF27: =IF(M27="Concluido",I27-F27,IF(M27="Cancelado",0,TODAY()-F27)) -> 197 | AO27: RN | AP27: NTL18 | AQ27: JUN-25 | AR27: C1 | AS27: 624 | AT27: 78 | AV27: Alivio Proativo
A28: a27 | D28: 34747591 | F28: 45796 | G28: 45807 | I28: 45814 | L28: 9444.6 | M28: Concluído | Q28: NF Recebida | R28: Concluido | AF28: =IF(M28="Concluido",I28-F28,IF(M28="Cancelado",0,TODAY()-F28)) -> 206 | AO28: CE | AP28: FLA08 | AQ28: JUN-25 | AR28: MDU | AS28: 120 | AT28: 15 | AV28: MDU
A29: a28 | D29: 34710933 | F29: 45792 | G29: 45805 | I29: 45812 | L29: 10216.8 | M29: Concluído | Q29: NF Recebida | R29: Concluido | AF29: =IF(M29="Concluido",I29-F29,IF(M29="Cancelado",0,TODAY()-F29)) -> 210 | AO29: CE | AP29: FLA09 | AQ29: JUN-25 | AR29: MDU | AS29: 192 | AT29: 24 | AV29: MDU
A30: a29 | D30: 35183696 | F30: 45819 | G30: 45832 | I30: 45821 | L30: 1940.4 | M30: Concluído | Q30: NF Recebida | R30: Concluido | AF30: =IF(M30="Concluido",I30-F30,IF(M30="Cancelado",0,TODAY()-F30)) -> 183 | AO30: CE | AP30: FLA14 | AQ30: JUN-25 | AR30: MDU | AS30: 16 | AT30: 2 | AV30: MDU
A31: a30 | D31: 34881184 | F31: 45805 | G31: 45817 | I31: 45819 | L31: 9365.4 | M31: Concluído | Q31: NF Recebida | R31: Concluido | AF31: =IF(M31="Concluido",I31-F31,IF(M31="Cancelado",0,TODAY()-F31)) -> 197 | AO31: CE | AP31: FLA12 | AQ31: JUN-25 | AR31: MDU | AS31: 160 | AT31: 20 | AV31: MDU
A32: a31 | D32: 35009048 | F32: 45810 | G32: 45821 | I32: 45814 | L32: 1940.4 | M32: Concluído | Q32: NF Recebida | R32: Concluido | AF32: =IF(M32="Concluido",I32-F32,IF(M32="Cancelado",0,TODAY()-F32)) -> 192 | AO32: CE | AP32: FLA32 | AQ32: JUN-25 | AR32: MDU | AS32: 16 | AT32: 2 | AV32: MDU
A33: a32 | D33: 34871192 | F33: 45805 | G33: 45817 | I33: 45819 | L33: 3069 | M33: Concluído | Q33: NF Recebida | R33: Concluido | AF33: =IF(M33="Concluido",I33-F33,IF(M33="Cancelado",0,TODAY()-F33)) -> 197 | AO33: CE | AP33: FLA09 | AQ33: JUN-25 | AR33: MDU | AS33: 40 | AT33: 5 | AV33: MDU
A34: a33 | D34: 34997884 | F34: 45810 | G34: 45814 | I34: 45811 | L34: 514.8 | M34: Concluído | Q34: NF Recebida | R34: Concluido | AF34: =IF(M34="Concluido",I34-F34,IF(M34="Cancelado",0,TODAY()-F34)) -> 192 | AO34: CE | AP34: FLA19 | AQ34: JUN-25 | AR34: REATIVO | AS34: 8 | AT34: 1 | AV34: Alivio Reativo
A35: a34 | D35: 35216936 | F35: 45824 | G35: 45868 | I35: 45825 | L35: 1069.2 | M35: Concluído | Q35: NF Recebida | R35: Concluido | AF35: =IF(M35="Concluido",I35-F35,IF(M35="Cancelado",0,TODAY()-F35)) -> 178 | AO35: CE | AP35: FLA21 | AQ35: JUN-25 | AR35: C1 | AS35: 88 | AT35: 11 | AV35: Alivio Proativo
... A43: a42 | D43: 35234503 | F43: 45825 | G43: 45831 | I43: 45826 | L43: 900.9 | M43: Concluído | Q43: NF Recebida | R43: Concluido | AF43: =IF(M43="Concluido",I43-F43,IF(M43="Cancelado",0,TODAY()-F43)) -> 177 | AO43: CE | AP43: FLA27 | AQ43: JUN-25 | AR43: C1 | AS43: 16 | AT43: 1 | AV43: Alivio Proativo
A44: a43 | D44: 35126884 | F44: 45818 | G44: 45824 | I44: 45824 | L44: 15976.51 | M44: Concluído | Q44: NF Recebida | R44: Concluido | AF44: =IF(M44="Concluido",I44-F44,IF(M44="Cancelado",0,TODAY()-F44)) -> 184 | AO44: CE | AQ44: JUN-25 | AR44: LPU | AS44: 1 | AT44: 1 | AV44: B2B
A45: 9dba3ce2 | D45: 35372414 | F45: 45833 | G45: 45840 | I45: 45835.658 | L45: 346.5 | M45: Concluído | Q45: NF Recebida | R45: Concluido | AF45: =IF(M45="Concluido",I45-F45,IF(M45="Cancelado",0,TODAY()-F45)) -> 169 | AO45: CE | AP45: FLA05 | AQ45: JUN-25 | AR45: C2 | AS45: 8 | AT45: 1 | AV45: Alivio Reativo
A46: a44 | D46: 35336923 | F46: 45833 | G46: 45844 | H46: Semana 01/JUL-25 | I46: 45849.699 | L46: 16572.6 | M46: Concluído | Q46: NF Recebida | R46: Concluido | AF46: =IF(M46="Concluido",I46-F46,IF(M46="Cancelado",0,TODAY()-F46)) -> 169 | AO46: RN | AP46: NTL21 | AQ46: JUL-25 | AR46: C1 | AS46: 1000 | AT46: 125 | AV46: Alivio Proativo
A47: a45 | D47: 35338033 | F47: 45833 | G47: 45844 | H47: Semana 01/JUL-25 | I47: 45846.493 | L47: 9890.1 | M47: Concluído | Q47: NF Recebida | R47: Concluido | AF47: =IF(M47="Concluido",I47-F47,IF(M47="Cancelado",0,TODAY()-F47)) -> 169 | AO47: RN | AP47: CGM01 | AQ47: JUL-25 | AR47: C1 | AS47: 600 | AT47: 75 | AV47: Alivio Proativo
A48: 756a629d | D48: 35332631 | F48: 45832 | G48: 45846 | H48: AD1 250,00 | I48: 45834.7 | L48: 943 | M48: Concluído | Q48: NF Recebida | R48: Concluido | AF48: =IF(M48="Concluido",I48-F48,IF(M48="Cancelado",0,TODAY()-F48)) -> 170 | AO48: CE | AP48: ESB01 | AQ48: JUN-25 | AR48: C2 | AS48: 16 | AT48: 2 | AV48: Alivio Reativo
A49: 810e3f35 | D49: 35374681 | F49: 45834 | G49: 45844 | H49: Semana 01/JUL-25 | I49: 45851.7 | L49: 2004.75 | M49: Concluído | Q49: NF Recebida | R49: Concluido | AF49: =IF(M49="Concluido",I49-F49,IF(M49="Cancelado",0,TODAY()-F49)) -> 168 | AO49: RN | AP49: TUL01 | AQ49: JUL-25 | AR49: C1 | AS49: 224 | AT49: 28 | AV49: Alivio Proativo
A50: 976578db | D50: 35409825 | F50: 45835 | G50: 45845 | H50: ROTAS DE CABO RECUSADA PELO CLIENTE, JÁ LANÇAMOS E RETIRAMOS 2KM DE CABO NESSE CLIENTE - OS CANCELADA, VAI TER QUE SER FEITA PELA PRIMEIRA ROTA. VÃO GERAR UMA NOVA OS | M50: Cancelado | R50: Inviabilidade Técnica | AF50: =TODAY()-F50 -> 167 | AO50: CE | AP50: MCW01 | AQ50: JUN-25 | AR50: B2B | AS50: 1 | AT50: 1 | AV50: Alivio Proativo
A51: a8fe2c75 | D51: 35408310 | F51: 45835 | G51: 45840 | M51: Cancelado | R51: Inviabilidade Técnica | AF51: =TODAY()-F51 -> 167 | AO51: CE | AP51: FLA30 | AQ51: JUN-25 | AR51: MDU | AS51: 16 | AT51: 2 | AV51: MDU
A52: a75153de | D52: 35407969 | F52: 45835 | G52: 45840 | M52: Cancelado | R52: Declinado Sem Acesso | AF52: =TODAY()-F52 -> 167 | AO52: PB | AP52: JPA00 | AQ52: JUN-25 | AR52: MDU | AS52: 40 | AT52: 5 | AV52: MDU
A53: 0c2e3a4e | D53: 35408604 | F53: 45835 | G53: 45841 | I53: 45842.803 | L53: 346.5 | M53: Concluído | Q53: NF Recebida | R53: Concluido | AF53: =TODAY()-F53 -> 167 | AO53: RN | AP53: NTL09 | AQ53: JUL-25 | AR53: C2 | AS53: 8 | AT53: 1 | AV53: Alivio Reativo
A54: 7e7b6587 | D54: 35409296 | F54: 45835 | G54: 45848 | H54: OS FOI PRA OUTRA EMPREITEIRA | M54: Cancelado | R54: Inviabilidade Técnica | AF54: =TODAY()-F54 -> 167 | AO54: RN | AP54: NTL06 | AQ54: JUN-25 | AR54: MDU | AS54: 208 | AT54: 13 | AV54: MDU
A55: 5af0c8a0 | D55: 35407141 | F55: 45835 | G55: 45851 | H55: Semana 02/JUL-25 | I55: 45854.787 | L55: 8419.95 | M55: Concluído | Q55: NF Recebida | R55: Concluido | AF55: =TODAY()-F55 -> 167 | AO55: RN | AP55: NTL19 | AQ55: JUL-25 | AR55: C1 | AS55: 504 | AT55: 63 | AV55: Alivio Proativo
A56: 8776c434 | D56: 35417028 | F56: 45838 | G56: 45842 | I56: 45842.673 | L56: 346.5 | M56: Concluído | Q56: NF Recebida | R56: Concluido | AF56: =TODAY()-F56 -> 164 | AO56: CE | AP56: FLA13 | AQ56: JUL-25 | AR56: C2 | AS56: 8 | AT56: 1 | AV56: Alivio Reativo
A57: e16c654b | D57: 34415737 | F57: 45838 | G57: 45842 | I57: 45840.58 | L57: 346.5 | M57: Concluído | Q57: NF Recebida | R57: Concluido | AF57: =TODAY()-F57 -> 164 | AO57: CE | AP57: FLA05 | AQ57: JUL-25 | AR57: C2 | AS57: 8 | AT57: 1 | AV57: Alivio Reativo
A58: f16ed38c | D58: 35421227 | F58: 45838 | G58: 45842 | H58: FIBRA SEM SINAL, USO DIGITAL SINALIZOU QUE EQUIPE EXTERNA IRIA ATIVAR PON | M58: Cancelado | R58: Inviabilidade Técnica | AF58: =TODAY()-F58 -> 164 | AO58: CE | AP58: FLA20 | AQ58: JUN-25 | AR58: C2 | AS58: 8 | AT58: 1 | AV58: Alivio Reativo
A59: d3c992ed | D59: 35338365 | F59: 45834 | G59: 45846 | H59: SÍNDICO NÃO AUTORIZOU ATIVIDADE | M59: Cancelado | R59: Declinado Sem Acesso | AF59: =TODAY()-F59 -> 168 | AO59: CE | AP59: FLA10 | AQ59: JUN-25 | AR59: REATIVO | AS59: 16 | AT59: 2 | AV59: Alivio Reativo
A60: e6f46529 | D60: 35417991 | F60: 45838 | G60: 45845 | H60: CONDOMÍNIO SEM TUBULAÇÃO PRA RECEBER OS CABOS, ATENDIMENTO ACONTECE DE FORMA AÉREA. SERÁ NECESSÁRIO CONSTRUIR TUBULAÇÃO E CAIXA SUBTERRÂNEA 30X30 | M60: Cancelado | R60: Inviabilidade Técnica | AF60: =TODAY()-F60 -> 164 | AO60: CE | AP60: FLA30 | AQ60: JUN-25 | AR60: MDU | AS60: 16 | AT60: 2 | AV60: MDU
A61: a46 | D61: 35561930 | F61: 45847 | G61: 45858 | H61: Semana 03/ JUL-25 | I61: 45869.4 | L61: 12516.1 | M61: Concluído | Q61: NF Recebida | R61: Concluido | AF61: =TODAY()-F61 -> 155 | AO61: CE | AP61: FLA28 | AQ61: JUL-25 | AR61: C4 | AS61: 192 | AT61: 12 | AV61: Alivio Proativo
A62: a47 | D62: 35422645 | F62: 45838 | G62: 45858 | H62: FOI PASSADO PARA OUTRA EMPRESA | L62: 8177.4 | M62: Cancelado | R62: Inviabilidade Técnica | AF62: =TODAY()-F62 -> 164 | AO62: CE | AP62: FLA28 | AQ62: JUN-25 | AR62: C5 | AS62: 128 | AT62: 8 | AV62: Alivio Proativo
A63: a48 | D63: 35421914 | F63: 45838 | G63: 45851 | H63: Semana 02/JUL-25 | I63: 45853.414 | L63: 4410.45 | M63: Concluído | Q63: NF Recebida | R63: Concluido | AF63: =TODAY()-F63 -> 164 | AO63: RN | AP63: NTL00 | AQ63: JUL-25 | AR63: C1 | AS63: 304 | AT63: 38 | AV63: Alivio Proativo
A64: 4ccb893e | D64: 35476089 | F64: 45839 | G64: 45845 | I64: 45839.355 | L64: 133.65 | M64: Concluído | Q64: NF Recebida | R64: Concluido | AF64: =TODAY()-F64 -> 163 | AO64: CE | AP64: FLA20 | AQ64: JUL-25 | AR64: C1 | AS64: 8 | AT64: 1 | AV64: Alivio Reativo
A65: 58263240 | D65: 35476820 | F65: 45839 | G65: 45852 | I65: 45852.765 | L65: 3346.2 | M65: Concluído | Q65: NF Recebida | R65: Concluido | AF65: =TODAY()-F65 -> 163 | AO65: PB | AP65: JPA00 | AQ65: JUL-25 | AR65: MDU | AS65: 48 | AT65: 6 | AV65: MDU
A66: 616f3d56 | D66: 35469521 | F66: 45839 | G66: 45849 | M66: Cancelado | R66: Declinado Sem Acesso | AF66: =TODAY()-F66 -> 163 | AO66: PB | AP66: JPA00 | AQ66: JUL-25 | AR66: MDU | AS66: 64 | AT66: 8 | AV66: MDU
A67: b334a1cc | D67: 35481054 | F67: 45839 | G67: 45849 | M67: Cancelado | R67: Inviabilidade Técnica | AF67: =TODAY()-F67 -> 163 | AO67: CE | AP67: FLA04 | AQ67: JUL-25 | AR67: REATIVO | AS67: 8 | AT67: 1 | AV67: Alivio Reativo
A68: 9be487de | D68: 35476508 | F68: 45839 | G68: 45819 | I68: 45840.736 | L68: 514.8 | M68: Concluído | Q68: NF Recebida | R68: Concluido | AF68: =TODAY()-F68 -> 163 | AO68: PB | AP68: JPA00 | AQ68: JUL-25 | AR68: C3 | AS68: 8 | AT68: 1 | AV68: Alivio Reativo
A69: cb52e4df | D69: 35495903 | F69: 45840 | G69: 45846 | I69: 45845.553 | L69: 346.5 | M69: Concluído | Q69: NF Recebida | R69: Concluido | AF69: =TODAY()-F69 -> 162 | AO69: CE | AP69: FLA05 | AQ69: JUL-25 | AR69: C2 | AS69: 8 | AT69: 1 | AV69: Alivio Reativo
A70: 90f54e20 | D70: 35491090 | F70: 45839 | G70: 45858 | H70: Semana 03/JUL-25 | I70: 45860.726 | L70: 22651.2 | M70: Concluído | Q70: NF Recebida | R70: Concluido | AF70: =TODAY()-F70 -> 163 | AO70: RN | AP70: GOH01 | AQ70: JUL-25 | AR70: C1/C4 | AS70: 536 | AT70: 49 | AV70: Alivio Proativo
A71: 5ebb119c | D71: 35495244 | F71: 45840 | G71: 45846 | I71: 45842.567 | L71: 346.5 | M71: Concluído | Q71: NF Recebida | R71: Concluido | AF71: =TODAY()-F71 -> 162 | AO71: RN | AP71: NTL07 | AQ71: JUL-25 | AR71: C2 | AS71: 8 | AT71: 1 | AV71: Alivio Reativo
A72: 8f21cd38 | D72: 35490157 | F72: 45840 | G72: 45846 | M72: Cancelado | R72: Declinado Sem Acesso | AF72: =TODAY()-F72 -> 162 | AO72: RN | AP72: NTL03 | AQ72: JUL-25 | AR72: MDU | AS72: 8 | AT72: 1 | AV72: Alivio Reativo
A73: e8e146e0 | D73: 35498282 | F73: 45840 | G73: 45850.666 | I73: 45842.771 | L73: 1839.75 | M73: Concluído | Q73: NF Recebida | R73: Concluido | AF73: =TODAY()-F73 -> 162 | AO73: CE | AP73: GIGA+ PENTECOSTE | AQ73: JUL-25 | AR73: B2B | AS73: 1 | AT73: 1 | AV73: Const. de Redes
A74: f85fcb40 | D74: 35513368 | F74: 45841 | G74: 45854 | I74: 45848.716 | L74: 1564.2 | M74: Concluído | Q74: NF Recebida | R74: Concluido | AF74: =TODAY()-F74 -> 161 | AO74: CE | AP74: FLA21 | AQ74: JUL-25 | AR74: MDU | AS74: 8 | AT74: 1 | AV74: MDU
A75: 2e0eda74 | D75: 35534862 | F75: 45842 | G75: 45852 | H75: OS DE LANÇAMENTO E INSTALAR CEO | I75: 45848.731 | L75: 768.75 | M75: Concluído | Q75: NF Recebida | R75: Concluido | AF75: =TODAY()-F75 -> 160 | AO75: RN | AP75: GOH01 | AQ75: JUL-25 | AR75: LPU | AS75: 0 | AT75: 0 | AV75: Alivio Proativo
A76: 61a8ee1f | D76: 35521695 | F76: 45845 | G76: 45855.397 | I76: 45855.578 | L76: 1675.45 | M76: Concluído | Q76: NF Recebida | R76: Concluido | AF76: =TODAY()-F76 -> 157 | AO76: CE | AP76: FLA14 | AQ76: JUL-25 | AR76: B2B | AS76: 1 | AT76: 1 | AV76: B2B
A77: 76c0ebd6 | D77: 35560061 | F77: 45845 | H77: PASSADO PRA OUTRA EMPREITEIRA | M77: Cancelado | R77: Inviabilidade Técnica | AF77: =TODAY()-F77 -> 157 | AO77: RN | AP77: NTL00 | AQ77: JUL-25 | AR77: B2B | AS77: 8 | AT77: 1 | AV77: Alivio Proativo
A78: 07d111dd | D78: 35560138 | F78: 45845 | G78: 45869.398 | H78: SEM AUTORIZAÇÃO DE EXECUÇÃO | L78: 1324 | M78: Cancelado | R78: Declinado Sem Acesso | AF78: =TODAY()-F78 -> 157 | AO78: CE | AP78: FLA19 | AQ78: JUL-25 | AR78: B2B | AS78: 1 | AT78: 1 | AV78: B2B
A79: ab56153f | D79: 35569423 | F79: 45846 | G79: 45868 | I79: 45856.758 | L79: 1737.45 | M79: Concluído | Q79: NF Recebida | R79: Concluido | AF79: =TODAY()-F79 -> 156 | AO79: RN | AP79: NTL18 | AQ79: JUL-25 | AR79: C1 | AS79: 104 | AT79: 13 | AV79: Alivio Proativo
A80: 89b8bb43 | D80: 35569198 | F80: 45846 | G80: 45868 | I80: 45861.72 | L80: 1202.85 | M80: Concluído | Q80: NF Recebida | R80: Concluido | AF80: =TODAY()-F80 -> 156 | AO80: RN | AP80: NTL12 | AQ80: JUL-25 | AR80: C1 | AS80: 72 | AT80: 9 | AV80: Alivio Proativo
A81: 6d3f2ff5 | D81: 35570554 | F81: 45846 | G81: 45868.4 | H81: O VALAOR DO LANÇAMENTO ESTÁ DOBRADO, POIS NESSA OS LANÇAMOS O CABO PELA ROTA SOLICITADA PELO PROJETO E O CLIENTE NÃO ACEITOU A ROTA LANÇADA. FOI RETIRADO O CABO, E LANÇADO NOVAMENTE POR OUTRA ROTA DE ACEITE DO CLEINTE. | I81: 45848.588 | L81: 9688.62 | M81: Concluído | Q81: NF Recebida | R81: Concluido | AF81: =TODAY()-F81 -> 156 | AO81: CE | AP81: MCW01 | AQ81: JUL-25 | AR81: B2B | AS81: 1 | AT81: 1 | AV81: Alivio Proativo
A82: 227ff623 | D82: 35588496 | F82: 45846 | G82: 45868 | I82: 45860.557 | L82: 1603.8 | M82: Concluído | Q82: NF Recebida | R82: Concluido | AF82: =TODAY()-F82 -> 156 | AO82: RN | AP82: NTL21 | AQ82: JUL-25 | AR82: C1 | AS82: 104 | AT82: 13 | AV82: Alivio Proativo
A83: a5b877cb | D83: 35568331 | F83: 45847 | G83: 45859 | H83: Herysson liberou 21/07, fazer lançamento com cabo de 24FO | I83: 45861.785 | L83: 3316.5 | M83: Concluído | Q83: NF Recebida | R83: Concluido | AF83: =TODAY()-F83 -> 155 | AO83: CE | AP83: FLA08 | AQ83: JUL-25 | AR83: REATIVO | AS83: 32 | AT83: 4 | AV83: Alivio Reativo
A84: 27bc5131 | D84: 35622073 | F84: 45847 | G84: 45868 | I84: 45852.773 | L84: 1069.2 | M84: Concluído | Q84: NF Recebida | R84: Concluido | AF84: =TODAY()-F84 -> 155 | AO84: CE | AP84: FLA20 | AQ84: JUL-25 | AR84: C1 | AS84: 72 | AT84: 9 | AV84: Alivio Proativo
A85: ac728c22 | D85: 35528847 | F85: 45847 | G85: 45849 | I85: 45848.718 | L85: 346.5 | M85: Concluído | Q85: NF Recebida | R85: Concluido | AF85: =TODAY()-F85 -> 155 | AO85: CE | AP85: FLA12 | AQ85: JUL-25 | AR85: C2 | AS85: 8 | AT85: 1 | AV85: Alivio Reativo
A86: ce1d6c7c | D86: 35597034 | F86: 45847 | G86: 45868 | I86: 45861.577 | L86: 133.65 | M86: Concluído | Q86: NF Recebida | R86: Concluido | AF86: =TODAY()-F86 -> 155 | AO86: RN | AP86: NTL06 | AQ86: JUL-25 | AR86: C1 | AS86: 8 | AT86: 1 | AV86: Alivio Proativo
A87: b76c136a | D87: 35592522 | F87: 45847 | G87: 45853 | I87: 45849.543 | L87: 346.5 | M87: Concluído | Q87: NF Recebida | R87: Concluido | AF87: =TODAY()-F87 -> 155 | AO87: CE | AP87: FLA12 | AQ87: JUL-25 | AR87: C2 | AS87: 8 | AT87: 1 | AV87: Alivio Reativo
A88: 0b787be0 | D88: 35596539 | F88: 45847 | G88: 45868 | I88: 45860.723 | L88: 267.3 | M88: Concluído | Q88: NF Recebida | R88: Concluido | AF88: =TODAY()-F88 -> 155 | AO88: RN | AP88: NTL20 | AQ88: JUL-25 | AR88: C1 | AS88: 16 | AT88: 2 | AV88: Alivio Proativo
A89: 70e0a29a | D89: 35595558 | F89: 45847 | G89: 45868 | I89: 45855.575 | L89: 935.55 | M89: Concluído | Q89: NF Recebida | R89: Concluido | AF89: =TODAY()-F89 -> 155 | AO89: RN | AP89: NTL19 | AQ89: JUL-25 | AR89: C1 | AS89: 56 | AT89: 7 | AV89: Alivio Proativo
A90: 6986d96d | D90: 35598409 | F90: 45847 | G90: 45853 | I90: 45849.673 | L90: 514.8 | M90: Concluído | Q90: NF Recebida | R90: Concluido | AF90: =TODAY()-F90 -> 155 | AO90: CE | AP90: FLA21 | AQ90: JUL-25 | AR90: REATIVO | AS90: 8 | AT90: 1 | AV90: Alivio Reativo
A91: 3b9ec969 | D91: 35597558 | F91: 45847 | G91: 45860 | I91: 45853.728 | L91: 514.8 | M91: Concluído | Q91: NF Recebida | R91: Concluido | AF91: =TODAY()-F91 -> 155 | AO91: CE | AP91: FLA03 | AQ91: JUL-25 | AR91: REATIVO | AS91: 8 | AT91: 1 | AV91: Alivio Reativo
A92: 34439b95 | D92: 35621663 | F92: 45849 | G92: 45868 | H92: OS APENAS DE LANÇAMENTO | I92: 45849.694 | L92: 827.5 | M92: Concluído | Q92: NF Recebida | R92: Concluido | AF92: =TODAY()-F92 -> 153 | AO92: CE | AP92: TA20738 / TA20737 | AQ92: JUL-25 | AR92: LPU | AV92: Alivio Proativo
A93: d348b773 | D93: 35617031 | F93: 45849 | G93: 45855 | I93: 45853.72 | L93: 514.8 | M93: Concluído | Q93: NF Recebida | R93: Concluido | AF93: =TODAY()-F93 -> 153 | AO93: CE | AP93: FLA30 | AQ93: JUL-25 | AR93: C3 | AS93: 16 | AT93: 1 | AV93: Alivio Reativo
A94: d52315e3 | D94: 35628792 | F94: 45849 | G94: 45852 | I94: 45849.681 | L94: 514.8 | M94: Concluído | Q94: NF Recebida | R94: Concluido | AF94: =TODAY()-F94 -> 153 | AO94: CE | AP94: FLA21 | AQ94: JUL-25 | AR94: REATIVO | AS94: 8 | AT94: 1 | AV94: Alivio Reativo
A95: 0af87b05 | D95: 35606450 | F95: 45849 | G95: 45868 | I95: 45854.416 | L95: 900.9 | M95: Concluído | Q95: NF Recebida | R95: Concluido | AF95: =TODAY()-F95 -> 153 | AO95: CE | AP95: FLA07 | AQ95: JUL-25 | AR95: C4 | AS95: 8 | AT95: 1 | AV95: Alivio Reativo
A96: 4f060efa | D96: 35628052 | F96: 45852 | G96: 45863 | H96: Alinhado parte interna amanha com o cliente 12 as 13hrs | I96: 45859.756 | L96: 514.8 | M96: Concluído | Q96: NF Recebida | R96: Concluido | AF96: =TODAY()-F96 -> 150 | AO96: CE | AP96: FLA09 | AQ96: JUL-25 | AR96: REATIVO | AS96: 8 | AT96: 1 | AV96: Alivio Reativo
A97: 0bda303f | D97: 35648544 | F97: 45853 | G97: 45868 | I97: 45856.664 | L97: 1491.16 | M97: Concluído | Q97: NF Recebida | R97: Concluido | AF97: =TODAY()-F97 -> 149 | AO97: CE | AP97: FLA29 | AQ97: JUL-25 | AR97: B2B | AS97: 1 | AT97: 1 | AV97: B2B
A98: 03b3213f | D98: 35664048 | F98: 45854 | G98: 45865 | H98: Semana 04/ JUL-25 | I98: 45871.743 | L98: 6209.8 | M98: Concluído | Q98: NF Recebida | R98: Concluido | AF98: =TODAY()-F98 -> 148 | AO98: CE | AP98: FLA04 | AQ98: JUL-25 | AR98: C2/C4 | AS98: 136 | AT98: 17 | AV98: Alivio Proativo
A99: 9b3e5b86 | D99: 35671830 | F99: 45854 | G99: 45861 | I99: 45862.722 | L99: 900.9 | M99: Concluído | Q99: NF Recebida | R99: Concluido | AF99: =TODAY()-F99 -> 148 | AO99: CE | AP99: FLA32 | AQ99: JUL-25 | AR99: C4 | AS99: 16 | AT99: 1 | AV99: Alivio Reativo
A100: 242e10d0 | D100: 35676342 | F100: 45856 | G100: 45868 | H100: SEM ACORDO PRA CABEAMENTO, CÉLIO FEZ VISTORIA | M100: Cancelado | Q100: Não Medido | R100: Inviabilidade Técnica | AF100: =TODAY()-F100 -> 146 | AO100: CE | AP100: FLA13 | AQ100: JUL-25 | AR100: MDU | AS100: 64 | AT100: 8 | AV100: MDU
A101: 000d66d3 | D101: 35685867 | F101: 45856 | G101: 45868 | H101: INSTALAÇÃO DE UM SMAP E SUBSTITUIÇÃO DE OUTRO SMAP | I101: 45857.347 | L101: 1029.6 | M101: Concluído | Q101: NF Recebida | R101: Concluido | AF101: =TODAY()-F101 -> 146 | AO101: CE | AP101: FLA08 | AQ101: JUL-25 | AR101: REATIVO | AS101: 8 | AT101: 1 | AV101: Alivio Reativo
A102: b745fdea | D102: 35687265 | F102: 45855 | G102: 45856 | H102: OS DE FUSÃO - 07 FUSÕES E BAIXADO 04 CAIXAS | I102: 45856.648 | L102: 600.52 | M102: Concluído | Q102: NF Recebida | R102: Concluido | AF102: =TODAY()-F102 -> 147 | AO102: CE | AP102: FLA17 | AQ102: JUL-25 | AR102: LPU | AV102: Const. de Redes
A103: 18adb71f | D103: 35688732 | F103: 45859 | G103: 45869 | I103: 45880.741 | L103: 2489.17 | M103: Concluído | Q103: NF Recebida | R103: Concluido | AF103: =TODAY()-F103 -> 143 | AO103: CE | AP103: FLA30 | AQ103: AGO-25 | AR103: LPU | AV103: Const. de Redes
A104: c4c2886b | D104: 35677910 | F104: 45859 | G104: 45869 | H104: Desistencia do Cliente | M104: Cancelado | Q104: Não Medido | R104: Declinado Sem Acesso | AF104: =TODAY()-F104 -> 143 | AO104: PB | AP104: JPA00 | AQ104: JUL-25 | AR104: MDU | AS104: 16 | AT104: 2 | AV104: MDU
A105: 82d1bc28 | D105: 35680915 | F105: 45859 | G105: 45869 | H105: Um dos Blocos ainda está em contrução. Entrega será de 5 SMAPs | I105: 45869.593 | L105: 3069 | M105: Concluído | Q105: NF Recebida | R105: Concluido | AF105: =TODAY()-F105 -> 143 | AO105: PB | AP105: JPA00 | AQ105: JUL-25 | AR105: MDU | AS105: 80 | AT105: 10 | AV105: MDU
A106: 96f74be1 | D106: 35688433 | F106: 45859 | G106: 45870 | H106: CONDOMÍNIO COM OBSTRUÇÃO. SERÁ FEITO OBRA CIVIL DE 266m DE TUBULAÇÃO NOVA. ESTRUTURA CONCLUÍDA, CONSTRUIDO 266m DE CANALIZAÇÃO. ORÇAMENTO DA CANALIZAÇÃO R$ 22.982,40. CONCLUÍDO DEPOIS DE ISNTABILIDADE DA REDE SER CORRIGIDA, SINAL FICAVA VARIANDO NO POWER MITER. | I106: 45884.383 | L106: 34832.7 | M106: Concluído | Q106: NF Recebida | R106: Concluido | AF106: =TODAY()-F106 -> 143 | AO106: PB | AP106: JPA00 | AQ106: AGO-25 | AR106: MDU | AS106: 80 | AT106: 10 | AV106: MDU
A107: 36c9867a | D107: 35716080 | F107: 45859 | G107: 45866 | H107: FEITO FUSÃO DE 2 CX DE MANUTENÇÃO NO TRECHO E FEITO NAS CTOS | I107: 45866.359 | L107: 846.5 | M107: Concluído | Q107: NF Recebida | R107: Concluido | AF107: =TODAY()-F107 -> 143 | AO107: CE | AP107: FLA17 | AQ107: JUL-25 | AR107: C3 | AS107: 8 | AT107: 1 | AV107: Alivio Reativo
...

Sheet CaixaAlares
A1: IdCaixa | B1: Projeto | C1: Pop | D1: Cidade | E1: UF | F1: Chassi | G1: Placa | H1: OLT | I1: Cto | J1: Cenario | K1: Bairro | L1: Endereco | M1: Lat | N1: Long | O1: OS | P1: Status | Q1: Potência | R1: Valor | S1: Equipe | T1: OBS | U1: Data | V1: Lançado12FO | W1: LançadoDrop | X1: NomeEquipe | Y1: ArquivoOrigem
A2: a1 | C2: FLA09 | D2: FORTALEZA | E2: CE | F2: CH04 | G2: PL03 | H2: OLT08 | I2: FLA09-2361 | J2: C1 | K2: Aldeota | L2: R. Barão de Aracati, 747 - Aldeota | M2: -3.7281569 | N2: -38.510175 | O2: a32 | P2: OK | R2: 1564.2 | S2: 60db2b1b | T2: apta | U2: 45820 | X2: ALEF/ CAIKY (85998135803)
A3: a2 | C3: FLA09 | D3: FORTALEZA | E3: CE | F3: CH04 | G3: PL03 | H3: OLT08 | I3: FLA09-2362 | J3: A1 | K3: Aldeota | L3: R. Barão de Aracati, 747 - Aldeota | M3: -3.7281569 | N3: -38.510175 | O3: a32 | P3: OK | R3: 376.2 | S3: 60db2b1b | T3: apta | U3: 45820 | X3: ALEF/ CAIKY (85998135803)
A4: a3 | C4: FLA09 | D4: FORTALEZA | E4: CE | F4: CH04 | G4: PL03 | H4: OLT08 | I4: FLA09-2363 | J4: A1 | K4: Aldeota | L4: R. Barão de Aracati, 747 - Aldeota | M4: -3.7281569 | N4: -38.510175 | O4: a32 | P4: OK | R4: 376.2 | S4: 60db2b1b | T4: apta | U4: 45820 | X4: ALEF/ CAIKY (85998135803)
A5: a4 | C5: FLA09 | D5: FORTALEZA | E5: CE | F5: CH04 | G5: PL03 | H5: OLT08 | I5: FLA09-2364 | J5: A1 | K5: Aldeota | L5: R. Barão de Aracati, 747 - Aldeota | M5: -3.7281569 | N5: -38.510175 | O5: a32 | P5: OK | R5: 376.2 | S5: 60db2b1b | T5: apta | U5: 45820 | X5: ALEF/ CAIKY (85998135803)
A6: a5 | C6: FLA09 | D6: FORTALEZA | E6: CE | F6: CH04 | G6: PL03 | H6: OLT08 | I6: FLA09-2365 | J6: A1 | K6: Aldeota | L6: R. Barão de Aracati, 747 - Aldeota | M6: -3.7281569 | N6: -38.510175 | O6: a32 | P6: OK | R6: 376.2 | S6: 60db2b1b | T6: apta | U6: 45820 | X6: ALEF/ CAIKY (85998135803)
A7: a6 | C7: FLA12 | D7: FORTALEZA | E7: CE | F7: CH02-NOK | G7: PL08 | H7: OLT16 | I7: FLA12-2813 | J7: C1 | K7: Pres. Kennedy | L7: Av. Cearenses, 54 - Pres. Kennedy, Fortaleza - CE | M7: -3.7316557 | N7: -38.566913 | O7: a30 | P7: OK | R7: 1564.2 | S7: 53ef62a7 | T7: apta | U7: 45819 | X7: JOSIMAR/ DANIEL (85992869866)
A8: a7 | C8: FLA12 | D8: FORTALEZA | E8: CE | F8: CH02-NOK | G8: PL08 | H8: OLT16 | I8: FLA12-2814 | J8: A1 | K8: Pres. Kennedy | L8: Av. Cearenses, 54 - Pres. Kennedy, Fortaleza - CE | M8: -3.7316557 | N8: -38.566913 | O8: a30 | P8: OK | R8: 376.2 | S8: 53ef62a7 | T8: apta | U8: 45819 | X8: JOSIMAR/ DANIEL (85992869866)
A9: a8 | C9: FLA12 | D9: FORTALEZA | E9: CE | F9: CH02-NOK | G9: PL08 | H9: OLT16 | I9: FLA12-2815 | J9: A1 | K9: Pres. Kennedy | L9: Av. Cearenses, 54 - Pres. Kennedy, Fortaleza - CE | M9: -3.7316557 | N9: -38.566913 | O9: a30 | P9: OK | R9: 376.2 | S9: 53ef62a7 | T9: apta | U9: 45819 | X9: JOSIMAR/ DANIEL (85992869866)
A10: a9 | C10: FLA12 | D10: FORTALEZA | E10: CE | F10: CH02-NOK | G10: PL08 | H10: OLT16 | I10: FLA12-2816 | J10: A1 | K10: Pres. Kennedy | L10: Av. Cearenses, 54 - Pres. Kennedy, Fortaleza - CE | M10: -3.7316557 | N10: -38.566913 | O10: a30 | P10: OK | R10: 376.2 | S10: 53ef62a7 | T10: apta | U10: 45819 | X10: JOSIMAR/ DANIEL (85992869866)
A11: a10 | C11: FLA12 | D11: FORTALEZA | E11: CE | F11: CH01-NOK | G11: PL08 | H11: OLT03 | I11: FLA12-2849 | J11: A1 | K11: Pres. Kennedy | L11: Av. Cearenses, 54 - Pres. Kennedy, Fortaleza - CE | M11: -3.7316557 | N11: -38.566913 | O11: a30 | P11: OK | R11: 376.2 | S11: 53ef62a7 | T11: apta | U11: 45819 | X11: JOSIMAR/ DANIEL (85992869866)
A12: a11 | C12: FLA12 | D12: FORTALEZA | E12: CE | F12: CH01-NOK | G12: PL08 | H12: OLT03 | I12: FLA12-2850 | J12: A1 | K12: Pres. Kennedy | L12: Av. Cearenses, 54 - Pres. Kennedy, Fortaleza - CE | M12: -3.7316557 | N12: -38.566913 | O12: a30 | P12: OK | R12: 376.2 | S12: 60db2b1b | T12: apta | U12: 45819 | X12: ALEF/ CAIKY (85998135803)
A13: a12 | C13: FLA12 | D13: FORTALEZA | E13: CE | F13: CH01-NOK | G13: PL08 | H13: OLT03 | I13: FLA12-2851 | J13: A1 | K13: Pres. Kennedy | L13: Av. Cearenses, 54 - Pres. Kennedy, Fortaleza - CE | M13: -3.7316557 | N13: -38.566913 | O13: a30 | P13: OK | R13: 376.2 | S13: 60db2b1b | T13: apta | U13: 45819 | X13: ALEF/ CAIKY (85998135803)
... A41: a40 | C41: FLA08 | D41: FORTALEZA | E41: CE | F41: CH01-NOK | G41: PL03 | H41: OLT 07 | I41: FLA08-623 | J41: A1 | K41: Passaré | L41: R. João Granjeiro, 95 - Passaré Fortaleza - CE, 60862-341 | M41: -3.8137417 | N41: -38.531467 | O41: a27 | P41: OK | R41: 376.2 | S41: 53ef62a7 | T41: apta | U41: 45817 | X41: JOSIMAR/ DANIEL (85992869866)
A42: a41 | C42: NTL-17 | D42: NATAL | E42: RN | F42: CH01 | G42: PL08 | H42: OLT 16 | I42: NTL17-1021 | J42: C1 | K42: Lagoa Nova | L42: R. Cel. Auris Coelho, 454-522 - Lagoa Nova, Natal - RN, 59075-050 | M42: -5.825253 | N42: -35.204833 | O42: a2 | P42: OK | Q42: -18.69 | R42: 133.65 | S42: 05dea2e6 | T42: apta | U42: 45827 | X42: PAULO ROBERTO (84996063007)
A43: a42 | C43: NTL17 | D43: NATAL | E43: RN | F43: CH02 | G43: PL01 | H43: OLT 04 | I43: NTL17-1049 | J43: C1 | K43: Lagoa Nova | L43: R. Prof. Antônio Campos, 536-654 - Lagoa Nova, Natal - RN, 59056-090 | M43: -5.8219789 | N43: -35.206354 | O43: a2 | P43: OK | Q43: -19.38 | R43: 133.65 | S43: 05dea2e6 | T43: apta | U43: 45827 | X43: PAULO ROBERTO (84996063007)
A44: a43 | C44: NTL17 | D44: NATAL | E44: RN | F44: CH02 | G44: PL02 | H44: OLT 04 | I44: NTL17-1177 | J44: C1 | K44: Nova Descoberta | L44: R. da Saudade, 1127-1053 - Nova Descoberta, Natal - RN, 59056-400 | M44: -5.8223338 | N44: -35.201845 | O44: a2 | P44: OK | Q44: -18.77 | R44: 133.65 | S44: 05dea2e6 | T44: apta | U44: 45827 | X44: PAULO ROBERTO (84996063007)
A45: a44 | C45: NTL17 | D45: NATAL | E45: RN | F45: CH02 | G45: PL02 | H45: OLT 05 | I45: NTL17-1186 | J45: C1 | K45: Lagoa Nova | L45: Av. Xavier da Silveira - Lagoa Nova, Natal - RN, 59056-530 | M45: -5.8255598 | N45: -35.203485 | O45: a2 | P45: OK | Q45: -18.57 | R45: 133.65 | S45: 5aac2867 | T45: apta | U45: 45825 | X45: EVANILDO/ DELANO (85991198015)
A46: a45 | C46: NTL17 | D46: NATAL | E46: RN | F46: CH02 | G46: PL02 | H46: OLT 09 | I46: NTL17-1218 | J46: C1 | K46: Nova Descoberta | L46: R. Dinarte Mariz Neto, 190 - Nova Descoberta, Natal - RN, 59075-360 | M46: -5.824746 | N46: -35.200292 | O46: a2 | P46: - | Q46: Sem Sinal | R46: 0 | S46: 05dea2e6 | T46: n apta | U46: 45827 | X46: PAULO ROBERTO (84996063007)
A47: a46 | C47: NTL17 | D47: NATAL | E47: RN | F47: CH02 | G47: PL02 | H47: OLT 09 | I47: NTL17-1219 | J47: C1 | K47: Nova Descoberta | L47: R. Dinarte Mariz Neto, 250 - Nova Descoberta, Natal - RN, 59075-360 | M47: -5.8250528 | N47: -35.199769 | O47: a2 | P47: OK | Q47: -18.16 | R47: 133.65 | S47: 05dea2e6 | T47: apta | U47: 45827 | X47: PAULO ROBERTO (84996063007)
A48: a47 | C48: NTL17 | D48: NATAL | E48: RN | F48: CH02 | G48: PL02 | H48: OLT 09 | I48: NTL17-1221 | J48: C1 | K48: Nova Descoberta | L48: R. Dinarte Mariz Neto, 407-341 - Nova Descoberta, Natal - RN, 59075-360 | M48: -5.8254664 | N48: -35.19898 | O48: a2 | P48: OK | Q48: -18.62 | R48: 133.65 | S48: 05dea2e6 | T48: apta | U48: 45827 | X48: PAULO ROBERTO (84996063007)
A49: a48 | C49: NTL17 | D49: NATAL | E49: RN | F49: CH02 | G49: PL02 | H49: OLT 11 | I49: NTL17-1240 | J49: C1 | K49: Lagoa Nova | L49: R. Cel. Auris Coelho, 868 - Lagoa Nova, Natal - RN, 59075-050 | M49: -5.8262669 | N49: -35.201807 | O49: a2 | P49: OK | Q49: -18.17 | R49: 133.65 | S49: 5aac2867 | T49: apta | U49: 45827 | X49: EVANILDO/ DELANO (85991198015)
A50: a49 | C50: NTL17 | D50: NATAL | E50: RN | F50: CH02 | G50: PL02 | H50: OLT 12 | I50: NTL17-1248 | J50: C1 | K50: Nova Descoberta | L50: R. Kerginaldo Cavalcante, 347 - Nova Descoberta, Natal - RN, 59075-240 | M50: -5.8259894 | N50: -35.202977 | O50: a2 | P50: OK | Q50: -18.08 | R50: 133.65 | S50: 5aac2867 | T50: apta | U50: 45825 | X50: EVANILDO/ DELANO (85991198015)
A51: a50 | C51: NTL17 | D51: NATAL | E51: RN | F51: CH02 | G51: PL02 | H51: OLT 14 | I51: NTL17-1258 | J51: C1 | K51: Lagoa Nova | L51: R. Kerginaldo Cavalcante, 462 - Nova Descoberta, Natal - RN, 59075-240 | M51: -5.8268753 | N51: -35.203333 | O51: a2 | P51: OK | Q51: -18.79 | R51: 133.65 | S51: 5aac2867 | T51: apta | U51: 45827 | X51: EVANILDO/ DELANO (85991198015)
A52: a51 | C52: NTL17 | D52: NATAL | E52: RN | F52: CH02 | G52: PL02 | H52: OLT 15 | I52: NTL17-1267 | J52: C1 | K52: Lagoa Nova | L52: R. Cel. Auris Coelho, 900-986 - Lagoa Nova, Natal - RN, 59075-050 | M52: -5.8265258 | N52: -35.201048 | O52: a2 | P52: OK | Q52: -18.37 | R52: 133.65 | S52: 5aac2867 | T52: apta | U52: 45827 | X52: EVANILDO/ DELANO (85991198015)
A53: a52 | C53: NTL17 | D53: NATAL | E53: RN | F53: CH02 | G53: PL02 | H53: OLT 15 | I53: NTL17-1268 | J53: C1 | K53: Lagoa Nova | L53: R. Cel. Auris Coelho, 900-986 - Lagoa Nova, Natal - RN, 59075-050 | M53: -5.8264351 | N53: -35.201306 | O53: a2 | P53: OK | Q53: -17.89 | R53: 133.65 | S53: 5aac2867 | T53: apta | U53: 45827 | X53: EVANILDO/ DELANO (85991198015)
A54: a53 | C54: NTL17 | D54: NATAL | E54: RN | F54: CH02 | G54: PL02 | H54: OLT 15 | I54: NTL17-1270 | J54: C1 | K54: Lagoa Nova | L54: R. Cel. Norton Chaves, 51-57 - Lagoa Nova, Natal - RN, 59075-200 | M54: -5.8284243 | N54: -35.203193 | O54: a2 | P54: OK | Q54: -17.78 | R54: 133.65 | S54: 5aac2867 | T54: apta | U54: 45825 | X54: EVANILDO/ DELANO (85991198015)
A55: a54 | C55: NTL17 | D55: NATAL | E55: RN | F55: CH02 | G55: PL02 | H55: OLT 16 | I55: NTL17-1276 | J55: C1 | K55: Lagoa Nova | L55: R. Dinarte Mariz Neto - Nova Descoberta, Natal - RN, 59075-360 Nova Descoberta | M55: -5.824802 | N55: -35.200005 | O55: a2 | P55: OK | Q55: -18.36 | R55: 133.65 | S55: 05dea2e6 | T55: apta | U55: 45827 | X55: PAULO ROBERTO (84996063007)
A56: a55 | C56: NTL17 | D56: NATAL | E56: RN | F56: CH02 | G56: PL03 | H56: OLT 01 | I56: NTL17-1287 | J56: C1 | K56: Lagoa Nova | L56: R. Cel. Auris Coelho, 1031-963 - Lagoa Nova, Natal - RN, 59075-050 | M56: -5.8267312 | N56: -35.20041 | O56: a2 | P56: OK | Q56: -17.44 | R56: 133.65 | S56: 5aac2867 | T56: apta | U56: 45827 | X56: EVANILDO/ DELANO (85991198015)
A57: a56 | C57: NTL17 | D57: NATAL | E57: RN | F57: CH02 | G57: PL03 | H57: OLT 02 | I57: NTL17-1295 | J57: C1 | L57: R. Laércio Fernandes, 277-197 - Nova Descoberta, Natal - RN, 59075-230 | M57: -5.8257333 | N57: -35.201697 | O57: a2 | P57: OK | Q57: -18.28 | R57: 133.65 | S57: 5aac2867 | T57: apta | U57: 45827 | X57: EVANILDO/ DELANO (85991198015)
A58: a57 | C58: NTL17 | D58: NATAL | E58: RN | F58: CH02 | G58: PL03 | H58: OLT 04 | I58: NTL17-1305 | J58: C1 | L58: R. Padre Raimundo Brasil, 644-856 - Nova Descoberta, Natal - RN, 59075-100 | M58: -5.8257626 | N58: -35.199691 | O58: a2 | P58: OK | Q58: -18.39 | R58: 133.65 | S58: 5aac2867 | T58: apta | U58: 45827 | X58: EVANILDO/ DELANO (85991198015)
A59: a58 | C59: NTL17 | D59: NATAL | E59: RN | F59: CH02 | G59: PL03 | H59: OLT 04 | I59: NTL17-1310 | J59: C1 | K59: Nova Descoberta | L59: R. Padre Raimundo Brasil, 724 - Nova Descoberta, Natal - RN, 59075-100 | M59: -5.825325 | N59: -35.200549 | O59: a2 | P59: OK | Q59: -18.27 | R59: 133.65 | S59: 5aac2867 | T59: apta | U59: 45827 | X59: EVANILDO/ DELANO (85991198015)
A60: a59 | C60: NTL17 | D60: NATAL | E60: RN | F60: CH02 | G60: PL03 | H60: OLT 05 | I60: NTL17-1316 | J60: C1 | L60: R. Padre Raimundo Brasil, 435 - Nova Descoberta, Natal - RN, 59075-100 | M60: -5.8244338 | N60: -35.20211 | O60: a2 | P60: OK | Q60: -19.77 | R60: 133.65 | S60: 21 | T60: apta | U60: 45827 | X60: LEONARDO FERREIRA / PCF4G19 - (85985946718)
A61: a60 | C61: NTL17 | D61: NATAL | E61: RN | F61: CH02 | G61: PL03 | H61: OLT 11 | I61: NTL17-1367 | J61: C1 | L61: R. Padre Raimundo Brasil, 911 - Nova Descoberta, Natal - RN, 59075-100 | M61: -5.8266565 | N61: -35.19806 | O61: a2 | P61: OK | Q61: -18.22 | R61: 133.65 | S61: 21 | T61: apta | U61: 45827 | X61: LEONARDO FERREIRA / PCF4G19 - (85985946718)
A62: a61 | C62: NTL17 | D62: NATAL | E62: RN | F62: CH02 | G62: PL03 | H62: OLT 13 | I62: NTL17-1377 | J62: C1 | K62: Nova Descoberta | L62: Av. Amintas Barros, 512-558 - Nova Descoberta, Natal - RN, 59075-420 | M62: -5.8263924 | N62: -35.194616 | O62: a2 | P62: OK | Q62: -19.16 | R62: 133.65 | S62: 21 | T62: apta | U62: 45827 | X62: LEONARDO FERREIRA / PCF4G19 - (85985946718)
A63: a62 | C63: NTL17 | D63: NATAL | E63: RN | F63: CH02 | G63: PL03 | H63: OLT 13 | I63: NTL17-1378 | J63: C1 | K63: Nova Descoberta Nova Descoberta Nova Descoberta Nova Descoberta Nova Descoberta | L63: R. Themístocles Duarte, 513 - Nova Descoberta, Natal - RN, 59075-420 | M63: -5.8258987 | N63: -35.194914 | O63: a2 | P63: OK | Q63: -18.62 | R63: 133.65 | S63: 21 | T63: apta | U63: 45827 | X63: LEONARDO FERREIRA / PCF4G19 - (85985946718)
A64: a63 | C64: NTL17 | D64: NATAL | E64: RN | F64: CH02 | G64: PL03 | H64: OLT 14 | I64: NTL17-1382 | J64: C1 | K64: Lagoa Nova | L64: Av. Amintas Barros, 4998 - Lagoa Nova, Natal - RN, 59075-250 | M64: -5.8246926 | N64: -35.198063 | O64: a2 | P64: OK | Q64: -20.55 | R64: 133.65 | S64: 21 | T64: apta | U64: 45827 | X64: LEONARDO FERREIRA / PCF4G19 - (85985946718)
A65: a64 | C65: NTL17 | D65: NATAL | E65: RN | F65: CH02 | G65: PL03 | H65: OLT 14 | I65: NTL17-1383 | J65: C1 | K65: Nova Descoberta | L65: R. Nelson Matos, 1868-1886 - Nova Descoberta, Natal - RN, 59075-380 | M65: -5.8242844 | N65: -35.198229 | O65: a2 | P65: OK | Q65: -19.52 | R65: 133.65 | S65: 21 | T65: apta | U65: 45827 | X65: LEONARDO FERREIRA / PCF4G19 - (85985946718)
A66: a65 | C66: NTL17 | D66: NATAL | E66: RN | F66: CH02 | G66: PL04 | H66: OLT 02 | I66: NTL17-1424 | J66: C1 | K66: Lagoa Nova | L66: Av. Sen. Salgado Filho - Lagoa Nova, Natal - RN, 59064-741 | M66: -5.8270408 | N66: -35.209985 | O66: a2 | P66: OK | Q66: -20.72 | R66: 133.65 | S66: 21 | T66: apta | U66: 45825 | X66: LEONARDO FERREIRA / PCF4G19 - (85985946718)
A67: a66 | C67: NTL17 | D67: NATAL | E67: RN | F67: CH02 | G67: PL04 | H67: OLT 04 | I67: NTL17-1439 | J67: C1 | K67: Lagoa Nova | L67: R. do Xisto, 2-106 - Lagoa Nova, Natal - RN, 59076-110 | M67: -5.8292555 | N67: -35.208443 | O67: a2 | P67: OK | Q67: -18.63 | R67: 133.65 | S67: 21 | T67: apta | U67: 45825 | X67: LEONARDO FERREIRA / PCF4G19 - (85985946718)
A68: a67 | C68: NTL17 | D68: NATAL | E68: RN | F68: CH02 | G68: PL04 | H68: OLT 04 | I68: NTL17-1440 | J68: C1 | K68: Lagoa Nova | L68: R. do Xisto, 2-106 - Lagoa Nova, Natal - RN, 59076-110 | M68: -5.828946 | N68: -35.208336 | O68: a2 | P68: OK | Q68: -18.65 | R68: 133.65 | S68: 21 | T68: apta | U68: 45825 | X68: LEONARDO FERREIRA / PCF4G19 - (85985946718)
A69: a68 | C69: NTL17 | D69: NATAL | E69: RN | F69: CH02 | G69: PL04 | H69: OLT 05 | I69: NTL17-1443 | J69: C1 | K69: Candelaria | L69: Av. Sen. Salgado Filho, 13 - Candelária, Natal - RN, 59064-741 | M69: -5.8278786 | N69: -35.210329 | O69: a2 | P69: OK | Q69: -19.53 | R69: 133.65 | S69: 21 | T69: apta | U69: 45825 | X69: LEONARDO FERREIRA / PCF4G19 - (85985946718)
A70: a69 | C70: NTL17 | D70: NATAL | E70: RN | F70: CH02 | G70: PL04 | H70: OLT 05 | I70: NTL17-1446 | J70: C1 | K70: Lagoa Nova | L70: Rua do Tório, 474-486 - Lagoa Nova, Natal - RN, 59076-500 | M70: -5.8299199 | N70: -35.206697 | O70: a2 | P70: OK | Q70: -19.5 | R70: 133.65 | S70: 21 | T70: apta | U70: 45825 | X70: LEONARDO FERREIRA / PCF4G19 - (85985946718)
A71: a70 | C71: NTL17 | D71: NATAL | E71: RN | F71: CH02 | G71: PL04 | H71: OLT 05 | I71: NTL17-1448 | J71: C1 | K71: Lagoa Nova | L71: R. do Calcário, 57-9 - Lagoa Nova, Natal - RN, 59076-240 | M71: -5.829525 | N71: -35.206077 | O71: a2 | P71: OK | Q71: -19.64 | R71: 133.65 | S71: 21 | T71: apta | U71: 45825 | X71: LEONARDO FERREIRA / PCF4G19 - (85985946718)
A72: a71 | C72: NTL17 | D72: NATAL | E72: RN | F72: CH02 | G72: PL04 | H72: OLT 09 | I72: NTL17-1476 | J72: C1 | K72: Lagoa Nova | L72: R. Ágata, 38 - Lagoa Nova, Natal - RN, 59076-350 | M72: -5.8304696 | N72: -35.202928 | O72: a2 | P72: OK | Q72: -19.4 | R72: 133.65 | S72: 21 | T72: apta | U72: 45827 | X72: LEONARDO FERREIRA / PCF4G19 - (85985946718)
A73: a72 | C73: NTL17 | D73: NATAL | E73: RN | F73: CH02 | G73: PL04 | H73: OLT 10 | I73: NTL17-1481 | J73: C1 | K73: Lagoa Nova | L73: R. da Ametista, 2388 - Lagoa Nova, Natal - RN, 59076-300 | M73: -5.8289353 | N73: -35.203835 | O73: a2 | P73: OK | Q73: -20.23 | R73: 133.65 | S73: 21 | T73: apta | U73: 45827 | X73: LEONARDO FERREIRA / PCF4G19 - (85985946718)
... A78: a77 | C78: NTL17 | D78: NATAL | E78: RN | F78: CH01 | G78: PL04 | H78: OLT 16 | I78: NTL17-506 | J78: C1 | K78: Lagoa Nova | L78: R. São Cristóvão, 14-5 - Lagoa Nova, Natal - RN, 59056-295 | M78: -5.8165994 | N78: -35.20173 | O78: a2 | P78: OK | Q78: -19.01 | R78: 133.65 | S78: 05dea2e6 | T78: apta | U78: 45822 | X78: PAULO ROBERTO (84996063007)
A79: a78 | C79: NTL17 | D79: NATAL | E79: RN | F79: CH01 | G79: PL05 | H79: OLT 01 | I79: NTL17-513 | J79: C1 | K79: Lagoa Nova | L79: R. Planaltina, 2-84 - Lagoa Nova, Natal - RN, 59056-160 | M79: -5.8149570197528 | N79: -35.200736 | O79: a2 | P79: OK | Q79: -18.18 | R79: 133.65 | S79: 05dea2e6 | T79: apta | U79: 45822 | X79: PAULO ROBERTO (84996063007)
A80: a79 | C80: NTL17 | D80: NATAL | E80: RN | F80: CH01 | G80: PL05 | H80: OLT 01 | I80: NTL17-519 | J80: C1 | K80: Lagoa Nova | L80: R. Amaro Mesquita, 43a - Lagoa Nova, Natal - RN, 59056-270 | M80: -5.8152259 | N80: -35.201123 | O80: a2 | P80: OK | Q80: -18.53 | R80: 133.65 | S80: 05dea2e6 | T80: apta | U80: 45822 | X80: PAULO ROBERTO (84996063007)
A81: a80 | C81: NTL17 | D81: NATAL | E81: RN | F81: CH01 | G81: PL05 | H81: OLT 01 | I81: NTL17-520 | J81: C1 | K81: Lagoa Nova | L81: R. Amaro Mesquita, 766 - Lagoa Nova, Natal - RN, 59056-270 | M81: -5.8155267 | N81: -35.200477 | O81: a2 | P81: OK | Q81: -19.53 | R81: 133.65 | S81: 05dea2e6 | T81: apta | U81: 45822 | X81: PAULO ROBERTO (84996063007)
A82: a81 | C82: NTL17 | D82: NATAL | E82: RN | F82: CH01 | G82: PL05 | H82: OLT 02 | I82: NTL17-525 | J82: C1 | K82: Lagoa Nova | L82: Av. Antônio Basílio, 3930-3974 - Lagoa Nova, Natal - RN, 59056-385 | M82: -5.816997 | N82: -35.201553 | O82: a2 | P82: OK | Q82: -19.98 | R82: 133.65 | S82: 05dea2e6 | T82: apta | U82: 45822 | X82: PAULO ROBERTO (84996063007)
A83: a82 | C83: NTL17 | D83: NATAL | E83: RN | F83: CH01 | G83: PL05 | H83: OLT 02 | I83: NTL17-526 | J83: C1 | K83: Lagoa Nova | L83: Av. Antônio Basílio, 3724-3792 - Lagoa Nova, Natal - RN, 59052-000 | M83: -5.8165114 | N83: -35.202816 | O83: a2 | P83: - | Q83: Formigas | R83: 0 | S83: 05dea2e6 | T83: n apta | U83: 45824 | X83: PAULO ROBERTO (84996063007)
A84: a83 | C84: NTL17 | D84: NATAL | E84: RN | F84: CH01 | G84: PL05 | H84: OLT 03 | I84: NTL17-531 | J84: C1 | L84: R. da Torre, 530 - Nova Descoberta, Natal - RN, 59056-370 | M84: -5.8165567 | N84: -35.199428 | O84: a2 | P84: OK | Q84: -18.8 | R84: 133.65 | S84: 05dea2e6 | T84: apta | U84: 45824 | X84: PAULO ROBERTO (84996063007)
A85: a84 | C85: NTL17 | D85: NATAL | E85: RN | F85: CH01 | G85: PL05 | H85: OLT 06 | I85: NTL17-558 | J85: C1 | L85: R. Velho Modesto, 182 - Nova Descoberta, Natal - RN, 59056-390 | M85: -5.8171878 | N85: -35.19846 | O85: a2 | P85: OK | Q85: -19.72 | R85: 133.65 | S85: 05dea2e6 | T85: apta | U85: 45824 | X85: PAULO ROBERTO (84996063007)
A86: a85 | C86: NTL17 | D86: NATAL | E86: RN | F86: CH01 | G86: PL05 | H86: OLT 07 | I86: NTL17-564 | J86: C1 | K86: Nova Descoberta Nova Descoberta Nova Descoberta | L86: Av. Brg. Gomes Ribeiro, 4918 - Nova Descoberta, Natal - RN, 59056-520 | M86: -5.816434 | N86: -35.197679 | O86: a2 | P86: OK | Q86: -19.04 | R86: 133.65 | S86: 05dea2e6 | T86: apta | U86: 45824 | X86: PAULO ROBERTO (84996063007)
A87: a86 | C87: NTL17 | D87: NATAL | E87: RN | F87: CH01 | G87: PL05 | H87: OLT 07 | I87: NTL17-566 | J87: C1 | K87: Tirol | L87: R. Dr. Vicente Farache, 470-532 - Tirol, Natal - RN, 59015-370 | M87: -5.8158149 | N87: -35.198409 | O87: a2 | P87: OK | Q87: -19.32 | R87: 133.65 | S87: 05dea2e6 | T87: apta | U87: 45824 | X87: PAULO ROBERTO (84996063007)
A88: a87 | C88: NTL17 | D88: NATAL | E88: RN | F88: CH01 | G88: PL05 | H88: OLT 07 | I88: NTL17-567 | J88: C1 | K88: Tirol | L88: R. Dr. Vicente Farache, 470-532 - Tirol, Natal - RN, 59015-370 | M88: -5.8165007 | N88: -35.198666 | O88: a2 | P88: - | Q88: Formigas | R88: 0 | S88: 05dea2e6 | T88: n apta | U88: 45824 | X88: PAULO ROBERTO (84996063007)
A89: a88 | C89: NTL17 | D89: NATAL | E89: RN | F89: CH01 | G89: PL05 | H89: OLT 07 | I89: NTL17-568 | J89: C1 | K89: Nova Descoberta | L89: R. Velho Modesto, 131-25 - Nova Descoberta, Natal - RN, 59056-390 | M89: -5.8167302 | N89: -35.198028 | O89: a2 | P89: OK | Q89: -19.27 | R89: 133.65 | S89: 05dea2e6 | T89: apta | U89: 45824 | X89: PAULO ROBERTO (84996063007)
A90: a89 | C90: NTL17 | D90: NATAL | E90: RN | F90: CH01 | G90: PL05 | H90: OLT 11 | I90: NTL17-597 | J90: C1 | K90: Tirol | L90: Rua Dr. João Dutra, 1911 - Tirol, Natal - RN, 59015-400 | M90: -5.8133053 | N90: -35.19723 | O90: a2 | P90: OK | Q90: -19.12 | R90: 133.65 | S90: 05dea2e6 | T90: apta | U90: 45825 | X90: PAULO ROBERTO (84996063007)
A91: a90 | C91: NTL17 | D91: NATAL | E91: RN | F91: CH01 | G91: PL05 | H91: OLT 15 | I91: NTL17-627 | J91: C1 | K91: Lagoa Nova | L91: Av. Nevaldo Rocha, 4164A - Lagoa Nova, Natal - RN, 59015-450 | M91: -5.8135121 | N91: -35.203228 | O91: a2 | P91: OK | Q91: -18.19 | R91: 133.65 | S91: 05dea2e6 | T91: apta | U91: 45825 | X91: PAULO ROBERTO (84996063007)
A92: a91 | C92: NTL17 | D92: NATAL | E92: RN | F92: CH01 | G92: PL05 | H92: OLT 15 | I92: NTL17-628 | J92: C1 | K92: Lagoa Nova | L92: Av. Nevaldo Rocha, 4156-4290 - Lagoa Nova, Natal - RN, 59054-590 | M92: -5.8137282 | N92: -35.202671 | O92: a2 | P92: OK | Q92: -19.71 | R92: 133.65 | S92: 05dea2e6 | T92: apta | U92: 45825 | X92: PAULO ROBERTO (84996063007)
A93: a92 | C93: NTL17 | D93: NATAL | E93: RN | F93: CH01 | G93: PL05 | H93: OLT 16 | I93: NTL17-637 | J93: C1 | K93: Lagoa Nova | L93: R. Amaro Mesquita, 20 - Lagoa Nova, Natal - RN, 59056-270 | M93: -5.8139764 | N93: -35.203953 | O93: a2 | P93: OK | Q93: -18.38 | R93: 133.65 | S93: 05dea2e6 | T93: apta | U93: 45825 | X93: PAULO ROBERTO (84996063007)
A94: a93 | C94: NTL17 | D94: NATAL | E94: RN | F94: CH01 | G94: PL05 | H94: OLT 16 | I94: NTL17-638 | J94: C1 | K94: Lagoa Nova | L94: R. Amaro Mesquita, 20 - Lagoa Nova, Natal - RN, 59056-270 | M94: -5.8137015 | N94: -35.204578 | O94: a2 | P94: OK | Q94: -18.2 | R94: 133.65 | S94: 05dea2e6 | T94: apta | U94: 45825 | X94: PAULO ROBERTO (84996063007)
A95: a94 | C95: NTL17 | D95: NATAL | E95: RN | F95: CH01 | G95: PL06 | H95: OLT 03 | I95: NTL17-657 | J95: C1 | K95: Lagoa Nova | L95: Av. Rui Barbosa, 2660-2696 - Lagoa Nova, Natal - RN, 59129-390 | M95: -5.8153946 | N95: -35.202975 | O95: a2 | P95: OK | Q95: -19.91 | R95: 133.65 | S95: 05dea2e6 | T95: apta | U95: 45825 | X95: PAULO ROBERTO (84996063007)
A96: a95 | C96: NTL17 | D96: NATAL | E96: RN | F96: CH01 | G96: PL06 | H96: OLT 03 | I96: NTL17-663 | J96: C1 | K96: Lagoa Nova | L96: Av. Rui Barbosa, 5 - Lagoa Nova, Natal - RN, 59129-390 | M96: -5.8159737 | N96: -35.203175 | O96: a2 | P96: OK | Q96: -19.38 | R96: 133.65 | S96: 05dea2e6 | T96: apta | U96: 45825 | X96: PAULO ROBERTO (84996063007)
A97: a96 | C97: NTL17 | D97: NATAL | E97: RN | F97: CH01 | G97: PL06 | H97: OLT 10 | I97: NTL17-715 | J97: C1 | K97: Lagoa Nova | L97: Rua Coronel Luiz Júlio - Lagoa Nova, Natal - RN, 59056-240 | M97: -5.8181044 | N97: -35.205469 | O97: a2 | P97: OK | Q97: -19.08 | R97: 133.65 | S97: 05dea2e6 | T97: apta | U97: 45825 | X97: PAULO ROBERTO (84996063007)
A98: a97 | C98: NTL17 | D98: NATAL | E98: RN | F98: CH01 | G98: PL07 | H98: OLT 03 | I98: NTL17-785 | J98: C1 | K98: Lagoa Nova | L98: Rua Felipe Cortez, 10-102 - Lagoa Nova, Natal - RN, 59064-630 | M98: -5.8203672 | N98: -35.203722 | O98: a2 | P98: OK | Q98: -19.55 | R98: 133.65 | S98: 05dea2e6 | T98: apta | U98: 45825 | X98: PAULO ROBERTO (84996063007)
A99: a98 | C99: NTL17 | D99: NATAL | E99: RN | F99: CH01 | G99: PL07 | H99: OLT 03 | I99: NTL17-786 | J99: C1 | K99: Lagoa Nova | L99: R. Des. Sinval Moreira Dias, 1668 - Lagoa Nova, Natal - RN, 59056-310 | M99: -5.8203939 | N99: -35.20417 | O99: a2 | P99: - | Q99: Formigas | R99: 0 | S99: 05dea2e6 | T99: n apta | U99: 45825 | X99: PAULO ROBERTO (84996063007)
A100: a99 | C100: NTL17 | D100: NATAL | E100: RN | F100: CH01 | G100: PL07 | H100: OLT 09 | I100: NTL17-833 | J100: C1 | K100: Nova Descoberta | L100: R. Potiguaranas, 546-652 - Nova Descoberta, Natal - RN, 59056-610 | M100: -5.8215146 | N100: -35.196797 | O100: a2 | P100: OK | Q100: -19.64 | R100: 133.65 | S100: 05dea2e6 | T100: apta | U100: 45825 | X100: PAULO ROBERTO (84996063007)
A101: a100 | C101: NTL17 | D101: NATAL | E101: RN | F101: CH01 | G101: PL07 | H101: OLT 09 | I101: NTL17-835 | J101: C1 | K101: Nova Descoberta | L101: Rua Clementino de Faria, 2159-2111 - Nova Descoberta, Natal - RN, 59056-485 | M101: -5.8209115 | N101: -35.197982 | O101: a2 | P101: OK | Q101: -19.95 | R101: 133.65 | S101: 05dea2e6 | T101: apta | U101: 45825 | X101: PAULO ROBERTO (84996063007)
A102: a101 | C102: NTL17 | D102: NATAL | E102: RN | F102: CH01 | G102: PL07 | H102: OLT 15 | I102: NTL17-885 | J102: C1 | K102: Lagoa Nova | L102: Rua Marise Bastier, 531-425 - Lagoa Nova, Natal - RN, 59075-070 | M102: -5.8208528 | N102: -35.206933 | O102: a2 | P102: OK | Q102: -19.22 | R102: 133.65 | S102: 05dea2e6 | T102: apta | U102: 45828 | X102: PAULO ROBERTO (84996063007)
A103: a102 | C103: NTL17 | D103: NATAL | E103: RN | F103: CH01 | G103: PL08 | H103: OLT 04 | I103: NTL17-926 | J103: C1 | K103: Lagoa Nova | L103: Rua Marise Bastier, 37 - Lagoa Nova, Natal - RN, 59056-070 | M103: -5.82168 | N103: -35.207231 | O103: a2 | P103: OK | Q103: -18.99 | R103: 133.65 | S103: 05dea2e6 | T103: apta | U103: 45825 | X103: PAULO ROBERTO (84996063007)
A104: a103 | C104: NTL17 | D104: NATAL | E104: RN | F104: CH01 | G104: PL08 | H104: OLT 07 | I104: NTL17-947 | J104: C1 | K104: Lagoa Nova | L104: R. Prof. Antônio Campos, 2303-2207 - Lagoa Nova, Natal - RN, 59075-000 | M104: -5.8214772 | N104: -35.206144 | O104: a2 | P104: OK | Q104: -19.37 | R104: 133.65 | S104: 05dea2e6 | T104: apta | U104: 45827 | X104: PAULO ROBERTO (84996063007)
A105: a104 | C105: NTL14 | D105: PARNAMIRIM | E105: RN | F105: CH01 | G105: PL01 | H105: OLT01 | I105: NTL14-002 | J105: C1 | K105: Vida Nova | L105: Rua Auta de Souza, Vida Nova, Parnamirim | M105: -5.900493281272854 | N105: -35.2727747120955 | O105: a3 | P105: OK | Q105: -18.63 | R105: 133.65 | S105: 21 | T105: apta | U105: 45831 | X105: LEONARDO FERREIRA / PCF4G19 - (85985946718)
A106: a105 | C106: NTL14 | D106: PARNAMIRIM | E106: RN | F106: CH01 | G106: PL01 | H106: OLT01 | I106: NTL14-004 | J106: C1 | K106: Parque Jockei Clube | L106: Rua Auta de Souza, Parque Jockei Clube, Parnamirim | M106: -5.9024306 | N106: -35.270673 | O106: a3 | P106: OK | Q106: -18.35 | R106: 133.65 | S106: 05dea2e6 | T106: apta | U106: 45831 | X106: PAULO ROBERTO (84996063007)
A107: a106 | C107: NTL14 | D107: PARNAMIRIM | E107: RN | F107: CH01 | G107: PL01 | H107: OLT01 | I107: NTL14-007 | J107: C1 | K107: Vida Nova | L107: Rua Auta de Souza, Vida Nova, Parnamirim | M107: -5.9034522 | N107: -35.269524 | O107: a3 | P107: OK | Q107: -19.17 | R107: 133.65 | S107: 05dea2e6 | T107: apta | U107: 45832 | X107: PAULO ROBERTO (84996063007)
A108: a107 | C108: NTL14 | D108: PARNAMIRIM | E108: RN | F108: CH01 | G108: PL01 | H108: OLT02 | I108: NTL14-013 | J108: C1 | K108: Vida Nova | L108: Rua Arabaiana, Vida Nova, Parnamirim | M108: -5.901528138457993 | N108: -35.27084601470768 | O108: a3 | P108: OK | Q108: -18.03 | R108: 133.65 | S108: 05dea2e6 | T108: apta | U108: 45831 | X108: PAULO ROBERTO (84996063007)
A109: a108 | C109: NTL14 | D109: PARNAMIRIM | E109: RN | F109: CH01 | G109: PL01 | H109: OLT03 | I109: NTL14-022 | J109: C1 | K109: Parque Jockei Clube | L109: Rua Xareu Do, Parque Jockei Clube, Parnamirim | M109: -5.898723 | N109: -35.272028 | O109: a3 | P109: OK | Q109: -18.9 | R109: 133.65 | S109: 05dea2e6 | T109: apta | U109: 45831 | X109: PAULO ROBERTO (84996063007)
A110: a109 | C110: NTL14 | D110: PARNAMIRIM | E110: RN | F110: CH01 | G110: PL01 | H110: OLT04 | I110: NTL14-027 | J110: C1 | K110: Vida Nova | L110: Rua Oceano Pacífico, Vida Nova, Parnamirim | M110: -5.89945443139211 | N110: -35.27050471676621 | O110: a3 | P110: OK | Q110: -18.72 | R110: 133.65 | S110: 05dea2e6 | T110: apta | U110: 45831 | X110: PAULO ROBERTO (84996063007)
A111: a110 | C111: NTL14 | D111: PARNAMIRIM | E111: RN | F111: CH01 | G111: PL01 | H111: OLT04 | I111: NTL14-030 | J111: C1 | K111: Parque Jockei Clube | L111: Rua Oceano Atlântico, Parque Jockei Clube, Parnamirim | M111: -5.9010474 | N111: -35.269477 | O111: a3 | P111: OK | Q111: -19.49 | R111: 133.65 | S111: 21 | T111: apta | U111: 45831 | X111: LEONARDO FERREIRA / PCF4G19 - (85985946718)
A112: a111 | C112: NTL14 | D112: PARNAMIRIM | E112: RN | F112: CH01 | G112: PL01 | H112: OLT04 | I112: NTL14-031 | J112: C1 | K112: Parque Jockei Clube | L112: Rua Oceano Índico, Parque Jockei Clube, Parnamirim | M112: -5.898054 | N112: -35.271428 | O112: a3 | P112: OK | Q112: -18.46 | R112: 133.65 | S112: 05dea2e6 | T112: apta | U112: 45831 | X112: PAULO ROBERTO (84996063007)
A113: a112 | C113: NTL14 | D113: PARNAMIRIM | E113: RN | F113: CH01 | G113: PL01 | H113: OLT08 | I113: NTL14-062 | J113: C1 | K113: Vida Nova | L113: Rua Garoupa, Vida Nova, Parnamirim | M113: -5.901719572486617 | N113: -35.27005943448866 | O113: a3 | P113: OK | Q113: -17.58 | R113: 133.65 | S113: 05dea2e6 | T113: apta | U113: 45832 | X113: PAULO ROBERTO (84996063007)
A114: a113 | C114: NTL14 | D114: PARNAMIRIM | E114: RN | F114: CH01 | G114: PL01 | H114: OLT09 | I114: NTL14-068 | J114: C1 | K114: una, 83, Parnamirim - RN, 59147-51 | L114: Rua Sauna, Parnamirim | M114: -5.9025269 | N114: -35.268505 | O114: a3 | P114: OK | Q114: -18.98 | R114: 133.65 | S114: 21 | T114: apta | U114: 45831 | X114: LEONARDO FERREIRA / PCF4G19 - (85985946718)
A115: a114 | C115: NTL14 | D115: PARNAMIRIM | E115: RN | F115: CH01 | G115: PL01 | H115: OLT09 | I115: NTL14-070 | J115: C1 | K115: Vida Nova | L115: Rua Melusa, Vida Nova, Parnamirim | M115: -5.9013789 | N115: -35.270085 | O115: a3 | P115: OK | Q115: -17.97 | R115: 133.65 | S115: 21 | T115: apta | U115: 45831 | X115: LEONARDO FERREIRA / PCF4G19 - (85985946718)
A116: a115 | C116: NTL14 | D116: PARNAMIRIM | E116: RN | F116: CH01 | G116: PL01 | H116: OLT09 | I116: NTL14-071 | J116: C1 | K116: Parque Jockei Clube | L116: Rua Mar Vermelho, Parque Jockei Clube, Parnamirim | M116: -5.900462278873334 | N116: -35.27077826268893 | O116: a3 | P116: OK | Q116: -17.87 | R116: 133.65 | S116: 21 | T116: apta | U116: 45831 | X116: LEONARDO FERREIRA / PCF4G19 - (85985946718)
A117: a116 | C117: NTL14 | D117: PARNAMIRIM | E117: RN | F117: CH01 | G117: PL01 | H117: OLT09 | I117: NTL14-072 | J117: C1 | K117: Vida Nova | L117: Rua Mar Vermelho, Vida Nova, Parnamirim | M117: -5.900921177431879 | N117: -35.270268641254034 | O117: a3 | P117: OK | Q117: -18.91 | R117: 133.65 | S117: 21 | T117: apta | U117: 45831 | X117: LEONARDO FERREIRA / PCF4G19 - (85985946718)
A118: a117 | C118: NTL14 | D118: PARNAMIRIM | E118: RN | F118: CH01 | G118: PL01 | H118: OLT10 | I118: NTL14-074 | J118: C1 | K118: Parque Jockei Clube | L118: Rua Oceano Atlântico, Parque Jockei Clube, Parnamirim | M118: -5.9014512 | N118: -35.269027 | O118: a3 | P118: OK | Q118: -17.98 | R118: 133.65 | S118: 21 | T118: apta | U118: 45831 | X118: LEONARDO FERREIRA / PCF4G19 - (85985946718)
A119: a118 | C119: NTL14 | D119: PARNAMIRIM | E119: RN | F119: CH01 | G119: PL01 | H119: OLT12 | I119: NTL14-095 | J119: C1 | K119: Parque Jockei Clube | L119: Rua Rio Senna, Parque Jockei Clube, Parnamirim | M119: -5.8935228 | N119: -35.276387 | O119: a3 | P119: - | Q119: Condomínio | R119: 133.65 | S119: Leonardo | T119: n apta | X119: Leonardo
A120: a119 | C120: NTL14 | D120: PARNAMIRIM | E120: RN | F120: CH01 | G120: PL01 | H120: OLT12 | I120: NTL14-096 | J120: C1 | K120: Parque Jockei Clube | L120: Rua Rio Senna, Parque Jockei Clube, Parnamirim | M120: -5.893287970771505 | N120: -35.27665033936501 | O120: a3 | P120: - | Q120: Condomínio | R120: 133.65 | S120: Leonardo | T120: n apta | X120: Leonardo
A121: a120 | C121: NTL14 | D121: PARNAMIRIM | E121: RN | F121: CH01 | G121: PL01 | H121: OLT16 | I121: NTL14-128 | J121: C1 | K121: Vida Nova | L121: Rua Mar da Galiléia, Vida Nova, Parnamirim | M121: -5.897616 | N121: -35.271584 | O121: a3 | P121: OK | Q121: -19.41 | R121: 133.65 | S121: 21 | T121: apta | U121: 45831 | X121: LEONARDO FERREIRA / PCF4G19 - (85985946718)
A122: a121 | C122: NTL14 | D122: PARNAMIRIM | E122: RN | F122: CH01 | G122: PL02 | H122: OLT02 | I122: NTL14-144 | J122: C1 | K122: Monte Castelo | L122: Rua Tilápia, Monte Castelo, Parnamirim | M122: -5.9025342 | N122: -35.267623 | O122: a3 | P122: OK | Q122: -18.38 | R122: 133.65 | S122: 21 | T122: apta | U122: 45831 | X122: LEONARDO FERREIRA / PCF4G19 - (85985946718)
A123: a122 | C123: NTL14 | D123: PARNAMIRIM | E123: RN | F123: CH01 | G123: PL02 | H123: OLT03 | I123: NTL14-145 | J123: C1 | K123: Nova Esperança | L123: Avenida Paulo Afonso, Nova Esperança, Parnamirim | M123: -5.9030296 | N123: -35.267768 | O123: a3 | P123: OK | Q123: -18.03 | R123: 133.65 | S123: 21 | T123: apta | U123: 45831 | X123: LEONARDO FERREIRA / PCF4G19 - (85985946718)
A124: a123 | C124: NTL14 | D124: PARNAMIRIM | E124: RN | F124: CH01 | G124: PL02 | H124: OLT05 | I124: NTL14-166 | J124: C1 | K124: Parque Jockei Clube | L124: Rua Padre Thiago Theisen, Parque Jockei Clube, Parnamirim | M124: -5.8937041837858635 | N124: -35.264360457658775 | O124: a3 | P124: - | Q124: Condomínio | R124: 133.65 | S124: Leonardo | T124: n apta | U124: 45832 | X124: Leonardo
A125: a124 | C125: NTL14 | D125: PARNAMIRIM | E125: RN | F125: CH01 | G125: PL02 | H125: OLT06 | I125: NTL14-169 | J125: C1 | K125: Parque de Exposicoes | L125: Rua Mario Lago, Parque de Exposicoes, Parnamirim | M125: -5.894926807710451 | N125: -35.264396667480476 | O125: a3 | P125: - | Q125: Condomínio | R125: 133.65 | S125: Leonardo | T125: n apta | U125: 45832 | X125: Leonardo
A126: a125 | C126: NTL14 | D126: PARNAMIRIM | E126: RN | F126: CH01 | G126: PL02 | H126: OLT06 | I126: NTL14-174 | J126: C1 | K126: Parque Jockei Clube | L126: Rua Padre Thiago Theisen, Parque Jockei Clube, Parnamirim | M126: -5.894096384225308 | N126: -35.2644369006157 | O126: a3 | P126: - | Q126: Condomínio | R126: 133.65 | S126: Leonardo | T126: n apta | U126: 45832 | X126: Leonardo
A127: a126 | C127: NTL14 | D127: PARNAMIRIM | E127: RN | F127: CH01 | G127: PL02 | H127: OLT07 | I127: NTL14-178 | J127: C1 | K127: Parque de Exposicoes | L127: Rua Chico Buarque De Holanda, Parque de Exposicoes, Parnamirim | M127: -5.895659180162469 | N127: -35.26475340127946 | O127: a3 | P127: - | Q127: Condomínio | R127: 133.65 | S127: Leonardo | T127: n apta | U127: 45832 | X127: Leonardo
A128: a127 | C128: NTL14 | D128: PARNAMIRIM | E128: RN | F128: CH01 | G128: PL02 | H128: OLT07 | I128: NTL14-179 | J128: C1 | K128: Santos Reis | L128: Rua Sem Denominacao, Santos Reis, Parnamirim | M128: -5.896072723378657 | N128: -35.2647614479065 | O128: a3 | P128: - | Q128: Condomínio | R128: 133.65 | S128: Leonardo | T128: n apta | U128: 45832 | X128: Leonardo
A129: a128 | C129: NTL14 | D129: PARNAMIRIM | E129: RN | F129: CH01 | G129: PL02 | H129: OLT08 | I129: NTL14-186 | J129: C1 | K129: Parque de Exposicoes | L129: Rua Doutor Jose Americo, Parque de Exposicoes, Parnamirim | M129: -5.897224639712079 | N129: -35.26506386697292 | O129: a3 | P129: - | Q129: Condomínio | R129: 133.65 | S129: Leonardo | T129: n apta | U129: 45832 | X129: Leonardo
A130: a129 | C130: NTL14 | D130: PARNAMIRIM | E130: RN | F130: CH01 | G130: PL02 | H130: OLT10 | I130: NTL14-206 | J130: C1 | K130: Monte Castelo | L130: Rua Francisco Ferreira Neves, Monte Castelo, Parnamirim | M130: -5.9053097 | N130: -35.263225 | O130: a3 | P130: OK | Q130: -19.27 | R130: 133.65 | S130: 21 | T130: apta | U130: 45831 | X130: LEONARDO FERREIRA / PCF4G19 - (85985946718)
A131: a130 | C131: NTL14 | D131: PARNAMIRIM | E131: RN | F131: CH01 | G131: PL02 | H131: OLT10 | I131: NTL14-207 | J131: C1 | K131: Monte Castelo | L131: Rua Ozeas Pereira Dos Santos, Monte Castelo, Parnamirim | M131: -5.9048273 | N131: -35.263463 | O131: a3 | P131: OK | Q131: -19.41 | R131: 133.65 | S131: 21 | T131: apta | U131: 45831 | X131: LEONARDO FERREIRA / PCF4G19 - (85985946718)
...

Sheet ImportaCaixa
A1: IdImporta | B1: Data | C1: Arquivo | D1: NomeArquivo
A2: fd09a874 | B2: 45836.976 | C2: ImportaCaixa_Files_/fd09a874.Arquivo.022603.xlsx | D2: Import_280625

Sheet LancaAlares
A1: IdLancamento | B1: Os | C1: De | D1: Para | E1: Previsao | F1: Cenario | G1: Valor | H1: Cabo | I1: Status | J1: Lancado | K1: CenarioReal | L1: ValorReal | M1: DifLanc | N1: OrcadoAtual | O1: Data | P1: Obs | Q1: Equipe | R1: ArquivoOrigem
A2: a1 | B2: a23 | C2: CEOSP2- 04 PA71 | D2: CEOSP4-22-PA71 | E2: 199 | F2: C4 | G2: 900.9 | H2: 12FO | I2: OK | J2: 231 | K2: C4 | L2: 900.9 | M2: 32 | N2: 900.9 | O2: 45835 | Q2: 21
A3: a2 | B3: a23 | C3: NTL01-303/NTL01-932 | D3: NTL01-933 | E3: 89 | F3: C3 | G3: 514.8 | H3: 12FO | I3: OK | J3: 127 | K3: C4 | L3: 900.9 | M3: 38 | N3: 900.9 | O3: 45835 | Q3: 21
A4: a3 | B4: a23 | C4: NTL01-933 | D4: NTL01-934 | E4: 168 | F4: C4 | G4: 900.9 | H4: 12FO | I4: OK | J4: 188 | K4: C4 | L4: 900.9 | M4: 20 | N4: 900.9 | O4: 45835 | Q4: 21
A5: a4 | B5: a23 | C5: CEOSP4-15-PA71 | D5: NTL01-1017 | E5: 127 | F5: C4 | G5: 900.9 | H5: 12FO | I5: OK | J5: 156 | K5: C4 | L5: 900.9 | M5: 29 | N5: 900.9 | O5: 45835 | Q5: 21
A6: a5 | B6: a23 | C6: NTL01-1017 | D6: NTL01-1018 | E6: 188 | F6: C4 | G6: 900.9 | H6: 12FO | I6: OK | J6: 206 | K6: C4 | L6: 900.9 | M6: 18 | N6: 900.9 | O6: 45835 | Q6: 21
A7: a6 | B7: a23 | C7: CEOSP4-14-PA71 | D7: NTL01-1021 | E7: 102 | F7: C4 | G7: 900.9 | H7: 12FO | I7: OK | J7: 139 | K7: C4 | L7: 900.9 | M7: 37 | N7: 900.9 | O7: 45835 | Q7: 21
A8: a7 | B8: a23 | C8: NTL01-1021 | D8: NTL01-1022 | E8: 129 | F8: C4 | G8: 900.9 | H8: 12FO | I8: OK | J8: 164 | K8: C4 | L8: 900.9 | M8: 35 | N8: 900.9 | O8: 45835 | Q8: 21
A9: a8 | B9: a23 | C9: NTL01-1022 | D9: NTL01-1023 | E9: 69 | F9: C3 | G9: 514.8 | H9: 12FO | I9: OK | J9: 89 | K9: C3 | L9: 514.8 | M9: 20 | N9: 514.8 | O9: 45835 | Q9: 21
A10: a9 | B10: a14 | C10: CEOSP-11(MAFG05) | D10: MCW02-2328 | E10: 1200 | F10: LPU | G10: 3972 | H10: 12FO | I10: OK | J10: 1011 | K10: LPU | L10: 3346.41 | M10: 189 | N10: 3346.41 | O10: 45826 | Q10: 6
A11: a10 | B11: a15 | C11: CEODEV-TRONCO-F-29 | D11: CTO-GALPAO-NOVO | E11: 1700 | F11: LPU | G11: 5627 | H11: 12FO | I11: OK | J11: 1691 | K11: LPU | L11: 5597.21 | M11: 9 | N11: 5597.21 | O11: 45831 | Q11: 6
A12: a11 | B12: a43 | C12: POPGIGA+PENTECOSTE | D12: CTOAT-2-PENTECOSTE | E12: 3750 | F12: LPU | G12: 12412.5 | H12: 12FO | I12: OK | J12: 4708 | K12: LPU | L12: 15583.48 | M12: -958 | N12: 15583.48 | O12: 45824 | Q12: 6
A16: ab74c7c8 | B16: 90f54e20 | C16: GOH01-0542/GOH01-0543 | D16: GOH01-0990 | E16: 115 | F16: C4 | G16: 900.9 | H16: 12FO | I16: OK | J16: 115 | K16: C4 | L16: 900.9 | M16: 0 | N16: 900.9 | O16: 45853 | Q16: 0611f994 | R16: LancGOH01-05.07
A17: 5cda6f28 | B17: 90f54e20 | C17: GOH01-0990 | D17: GOH01-0991 | E17: 257 | F17: C4 | G17: 900.9 | H17: 12FO | I17: OK | J17: 252 | K17: C4 | L17: 900.9 | M17: -5 | N17: 900.9 | O17: 45853 | Q17: 0611f994 | R17: LancGOH01-05.07
A18: 17f74e62 | B18: 90f54e20 | C18: GOH01-0991 | D18: GOH01-0992 | E18: 268 | F18: C4 | G18: 900.9 | H18: 12FO | I18: OK | J18: 263 | K18: C4 | L18: 900.9 | M18: -5 | N18: 900.9 | O18: 45853 | Q18: 0611f994 | R18: LancGOH01-05.07
A19: 4b42a7c2 | B19: 90f54e20 | C19: GOH01-0548/GOH01-0986 | D19: GOH01-0989 | E19: 105 | F19: C4 | G19: 900.9 | H19: 12FO | I19: OK | J19: 143 | K19: C4 | L19: 900.9 | M19: 38 | N19: 900.9 | O19: 45853 | Q19: 0611f994 | R19: LancGOH01-05.07
A20: 15b3d85b | B20: 90f54e20 | C20: GOH01-0595 | D20: GOH01-1011 | E20: 183 | F20: C4 | G20: 900.9 | H20: 12FO | I20: OK | J20: 185 | K20: C4 | L20: 900.9 | M20: 2 | N20: 900.9 | O20: 45853 | Q20: 0611f994 | R20: LancGOH01-05.07
A21: 7af20421 | B21: 90f54e20 | C21: GOH01-1011 | D21: GOH01-1012 | E21: 293 | F21: C4 | G21: 900.9 | H21: 12FO | I21: OK | J21: 303 | K21: C5 | L21: 1386 | M21: 10 | N21: 1386 | O21: 45853 | Q21: 0611f994 | R21: LancGOH01-05.07
A22: 10cb0941 | B22: 90f54e20 | C22: GOH01-0590 | D22: GOH01-1009 | E22: 162 | F22: C4 | G22: 900.9 | H22: 12FO | I22: OK | J22: 161 | K22: C4 | L22: 900.9 | M22: -1 | N22: 900.9 | O22: 45853 | Q22: 0611f994 | R22: LancGOH01-05.07
A23: 54e3c6ba | B23: 90f54e20 | C23: GOH01-1009 | D23: GOH01-1010 | E23: 106 | F23: C4 | G23: 900.9 | H23: 12FO | I23: OK | J23: 104 | K23: C4 | L23: 900.9 | M23: -2 | N23: 900.9 | O23: 45853 | Q23: 0611f994 | R23: LancGOH01-05.07
A24: 267043c9 | B24: 90f54e20 | C24: CAIXA-GO-03 - 1/4 | D24: GOH01-0941 | E24: 244 | F24: C4 | G24: 900.9 | H24: 12FO | I24: OK | J24: 329 | K24: C5 | L24: 1386 | M24: 85 | N24: 1386 | O24: 45853 | Q24: 0611f994 | R24: LancGOH01-05.07
A25: a339481e | B25: 90f54e20 | C25: GOH01-0941 | D25: GOH01-0942 | E25: 183 | F25: C4 | G25: 900.9 | H25: 12FO | I25: OK | J25: 447 | K25: C5 | L25: 1386 | M25: 264 | N25: 1386 | O25: 45853 | Q25: 0611f994 | R25: LancGOH01-05.07
A26: b3a9cfbf | B26: 90f54e20 | C26: CAIXA-GO-19 - 1/4 | D26: GOH01-1018 | E26: 374 | F26: C5 | G26: 1386 | H26: 12FO | I26: OK | J26: 385 | K26: C5 | L26: 1386 | M26: 11 | N26: 1386 | O26: 45853 | Q26: 0611f994 | R26: LancGOH01-05.07
A27: be68223f | B27: 90f54e20 | C27: GOH01-1018 | D27: GOH01-1019 | E27: 216 | F27: C4 | G27: 900.9 | H27: 12FO | I27: OK | J27: 254 | K27: C4 | L27: 900.9 | M27: 38 | N27: 900.9 | O27: 45853 | Q27: 0611f994 | R27: LancGOH01-05.07
... A33: e1b8a41a | B33: 90f54e20 | C33: GOH01-0895 | D33: GOH01-0896 | E33: 248 | F33: C4 | G33: 900.9 | H33: 12FO | I33: OK | J33: 245 | K33: C4 | L33: 900.9 | M33: -3 | N33: 900.9 | O33: 45853 | Q33: 0611f994 | R33: LancGOH01-05.07
A34: 18e8a46f | B34: a47 | C34: 332-4 | D34: FLA28-0121 | E34: 185 | F34: C4 | G34: 9009 | H34: 12FO | R34: import_35422645
A35: 9a1c8d70 | B35: a47 | C35: FLA28-0121 | D35: FLA28-0122 | E35: 366 | F35: C5 | G35: 1386 | H35: 12FO | R35: import_35422645
A36: bd077e9c | B36: a47 | C36: FLA28-0122 | D36: FLA28-0123 | E36: 219 | F36: C4 | G36: 9009 | H36: 12FO | R36: import_35422645
A37: 92cd9c5a | B37: a47 | C37: FLA28-0123 | D37: FLA28-0124 | E37: 295 | F37: C4 | G37: 9009 | H37: 12FO | R37: import_35422645
A38: 7cb05231 | B38: a47 | C38: FLA28-0124 | D38: FLA28-0125 | E38: 268 | F38: C4 | G38: 9009 | H38: 12FO | R38: import_35422645
A39: 1b61e6c1 | B39: a47 | C39: FLA28-0125 | D39: FLA28-0126 | E39: 305 | F39: C5 | G39: 1386 | H39: 12FO | R39: import_35422645
A40: 70efb7b5 | B40: a47 | C40: FLA28-0126 | D40: FLA28-0127 | E40: 262 | F40: C4 | G40: 9009 | H40: 12FO | R40: import_35422645
A41: f9626d7a | B41: a47 | C41: FLA28-0127 | D41: FLA28-0128 | E41: 235 | F41: C4 | G41: 9009 | H41: 12FO | R41: import_35422645
A42: 13b0a5ad | B42: a46 | C42: 332-1 - (CE33166) | D42: FLA28-0107 | E42: 147 | F42: C4 | G42: 9009 | H42: 12FO | I42: OK | J42: 152 | K42: C4 | L42: 900.9 | M42: 5 | N42: 900.9 | O42: 45866 | Q42: 6 | R42: import_35332151
A43: d6261b81 | B43: a46 | C43: FLA28-0107 | D43: FLA28-0108 | E43: 152 | F43: C4 | G43: 9009 | H43: 12FO | I43: OK | J43: 158 | K43: C4 | L43: 900.9 | M43: 6 | N43: 900.9 | O43: 45866 | Q43: 6 | R43: import_35332151
A44: 9ac8b3b1 | B44: a46 | C44: FLA28-0108 | D44: FLA28-0109 | E44: 165 | F44: C4 | G44: 9009 | H44: 12FO | I44: OK | J44: 172 | K44: C4 | L44: 900.9 | M44: 7 | N44: 900.9 | O44: 45866 | Q44: 6 | R44: import_35332151
A45: 712cb12e | B45: a46 | C45: FLA28-0109 | D45: FLA28-0110 | E45: 167 | F45: C4 | G45: 9009 | H45: 12FO | I45: OK | J45: 170 | K45: C4 | L45: 900.9 | M45: 3 | N45: 900.9 | O45: 45866 | Q45: 6 | R45: import_35332151
A46: f4945ec9 | B46: a46 | C46: FLA28-0110 | D46: FLA28-0111 | E46: 153 | F46: C4 | G46: 9009 | H46: 12FO | I46: OK | J46: 160 | K46: C4 | L46: 900.9 | M46: 7 | N46: 900.9 | O46: 45866 | Q46: 6 | R46: import_35332151
A47: a8785fa8 | B47: a46 | C47: FLA28-0111 | D47: FLA28-0112 | E47: 235 | F47: C4 | G47: 9009 | H47: 12FO | I47: OK | J47: 236 | K47: C4 | L47: 900.9 | M47: 1 | N47: 900.9 | O47: 45866 | Q47: 6 | R47: import_35332151
A48: 1e9373b0 | B48: a46 | C48: FLA28-0113 | D48: FLA28-0115 | E48: 265 | F48: C4 | G48: 9009 | H48: 12FO | I48: OK | J48: 260 | K48: C4 | L48: 900.9 | M48: -5 | N48: 900.9 | O48: 45866 | Q48: 6 | R48: import_35332151
A49: a61e617b | B49: a46 | C49: FLA28-0115 | D49: FLA28-0116 | E49: 247 | F49: C4 | G49: 9009 | H49: 12FO | I49: OK | J49: 246 | K49: C4 | L49: 900.9 | M49: -1 | N49: 900.9 | O49: 45867 | Q49: 6 | R49: import_35332151
A50: adb1c718 | B50: a46 | C50: FLA28-0116 | D50: FLA28-0117 | E50: 289 | F50: C4 | G50: 9009 | H50: 12FO | I50: OK | J50: 315 | K50: C5 | L50: 1386 | M50: 26 | N50: 1386 | O50: 45867 | Q50: 6 | R50: import_35332151
A51: 4643ff25 | B51: a46 | C51: FLA28-0117 | D51: FLA28-0118 | E51: 266 | F51: C4 | G51: 9009 | H51: 12FO | I51: OK | J51: 355 | K51: C5 | L51: 1386 | M51: 89 | N51: 1386 | O51: 45867 | Q51: 6 | R51: import_35332151
A52: 8b9dabaa | B52: a46 | C52: FLA28-0118 | D52: FLA28-0119 | E52: 296 | F52: C4 | G52: 9009 | H52: 12FO | I52: OK | J52: 310 | K52: C5 | L52: 1386 | M52: 14 | N52: 1386 | O52: 45867 | Q52: 6 | R52: import_35332151
A53: d67877d5 | B53: a46 | C53: FLA28-0119 | D53: FLA28-0120 | E53: 266 | F53: C4 | G53: 9009 | H53: 12FO | I53: OK | J53: 240 | K53: C4 | L53: 900.9 | M53: -26 | N53: 900.9 | O53: 45867 | Q53: 6 | R53: import_35332151
A54: 8e84bd47 | B54: 6d3f2ff5 | C54: MCW01-343 | D54: CEO - REDE INTEGRADA - (ENGT-19659) | E54: 1700 | F54: LPU | G54: 5627 | H54: 24 FO | I54: OK | J54: 1418 | K54: LPU | L54: 4693.58 | M54: 282 | N54: 4693.58 | O54: 45848 | Q54: d975757f
A55: fa1ec7b2 | B55: 34439b95 | C55: TA20738 | D55: TA20737 | E55: 160 | F55: LPU | G55: 529.6 | H55: 12FO | I55: OK | J55: 250 | K55: LPU | L55: 827.5 | M55: 90 | N55: 827.5 | O55: 45853 | Q55: d975757f
A56: a854eb60 | B56: 03b3213f | C56: CEOSP-11 | D56: FLA04-150 | E56: 142 | F56: C4 | G56: 900.9 | H56: 12FO | I56: OK | J56: 188 | K56: C4 | L56: 900.9 | M56: 46 | N56: 900.9 | O56: 45867 | Q56: d975757f
A57: 86bfd350 | B57: 03b3213f | C57: FLA04-150 | D57: FLA04-151 | E57: 129 | F57: C4 | G57: 900.9 | H57: 12FO | I57: OK | J57: 176 | K57: C4 | L57: 900.9 | M57: 47 | N57: 900.9 | O57: 45867 | Q57: d975757f
A59: 4cc18f55 | B59: 96f74be1 | C59: CEOSP2- 55 | D59: CEOSP4- 454 | E59: 335 | F59: C5 | G59: 1386 | H59: 12FO | I59: OK | J59: 454 | K59: C5 | L59: 1386 | M59: 119 | N59: 1386 | O59: 45876 | Q59: 0611f994 | R59: import_lanc_21072025
A60: 540e443e | B60: 96f74be1 | C60: CEOSP4- 454 | D60: JPA00-8657 | E60: 162 | F60: C4 | G60: 900.9 | H60: 12FO | I60: OK | J60: 330 | K60: C4 | L60: 900.9 | M60: 168 | N60: 900.9 | O60: 45876 | Q60: 0611f994 | R60: import_lanc_21072025
A61: 06f19aa5 | B61: 96f74be1 | C61: JPA00-8657 | D61: JPA00-8658 | E61: 249 | F61: C4 | G61: 900.9 | H61: 12FO | I61: OK | J61: 288 | K61: C4 | L61: 900.9 | M61: 39 | N61: 900.9 | O61: 45876 | Q61: 0611f994 | R61: import_lanc_21072025
A62: c25cfed5 | B62: 96f74be1 | C62: JPA00-8658 | D62: JPA00-8659 | E62: 258 | F62: C4 | G62: 900.9 | H62: 12FO | I62: OK | J62: 365 | K62: C5 | L62: 1386 | M62: 107 | N62: 1386 | O62: 45876 | Q62: 0611f994 | R62: import_lanc_21072025
A63: c9a84453 | B63: 96f74be1 | C63: JPA00-8659 | D63: JPA00-8660 | E63: 266 | F63: C4 | G63: 900.9 | H63: 12FO | I63: OK | J63: 405 | K63: C5 | L63: 1386 | M63: 139 | N63: 1386 | O63: 45876 | Q63: 0611f994 | R63: import_lanc_21072025
A64: e9091d8d | B64: 96f74be1 | C64: CEOSP4- 454 | D64: JPA00-8661 | E64: 505 | F64: C5 | G64: 1386 | H64: 12FO | I64: OK | J64: 609 | K64: C5 | L64: 1386 | M64: 104 | N64: 1386 | O64: 45876 | Q64: 0611f994 | R64: import_lanc_21072025
A65: 4be04c51 | B65: 96f74be1 | C65: JPA00-8661 | D65: JPA00-8662 | E65: 248 | F65: C4 | G65: 900.9 | H65: 12FO | I65: OK | J65: 284 | K65: C4 | L65: 900.9 | M65: 36 | N65: 900.9 | O65: 45876 | Q65: 0611f994 | R65: import_lanc_21072025
A66: 4d51d876 | B66: 96f74be1 | C66: JPA00-8662 | D66: JPA00-8663 | E66: 121 | F66: C4 | G66: 900.9 | H66: 12FO | I66: OK | J66: 150 | K66: C4 | L66: 900.9 | M66: 29 | N66: 900.9 | O66: 45876 | Q66: 0611f994 | R66: import_lanc_21072025
A67: 9f771f0a | B67: 96f74be1 | C67: JPA00-8663 | D67: JPA00-8664 | E67: 222 | F67: C4 | G67: 900.9 | H67: 12FO | I67: OK | J67: 302 | K67: C4 | L67: 900.9 | M67: 80 | N67: 900.9 | O67: 45876 | Q67: 0611f994 | R67: import_lanc_21072025
A68: bc4a0e1b | B68: 96f74be1 | C68: JPA00-8664 | D68: JPA00-8665 | E68: 131 | F68: C4 | G68: 900.9 | H68: 12FO | I68: OK | J68: 156 | K68: C4 | L68: 900.9 | M68: 25 | N68: 900.9 | O68: 45876 | Q68: 0611f994 | R68: import_lanc_21072025
A69: 350d6ac0 | B69: 96f74be1 | C69: JPA00-8665 | D69: JPA00-8666 | E69: 216 | F69: C4 | G69: 900.9 | H69: 12FO | I69: OK | J69: 317 | K69: C4 | L69: 900.9 | M69: 101 | N69: 900.9 | O69: 45876 | Q69: 0611f994 | R69: import_lanc_21072025
A70: 2de3c80e | B70: b44ce929 | C70: CEOSEC-06 | D70: CEOSP2-10 NA100 | E70: 547 | F70: C5 | G70: 1386 | H70: 12FO | I70: OK | J70: 602 | K70: C5 | L70: 1386 | M70: 55 | N70: 1386 | O70: 45882 | Q70: 0611f994 | R70: import_lanc_04082025
... A79: 6e72476f | B79: b44ce929 | C79: NTL18-1823 | D79: NTL18-1824 | E79: 122 | F79: C4 | G79: 900.9 | H79: 12FO | I79: OK | J79: 135 | K79: C4 | L79: 900.9 | M79: 13 | N79: 900.9 | O79: 45882 | Q79: 0611f994 | R79: import_lanc_04082025
A80: abf66b73 | B80: 4c68ae55 | C80: CAIXA-GO-20-1/4 | D80: GOH01-0997 | E80: 61 | F80: C3 | G80: 490 | H80: 12FO | I80: OK | J80: 105 | K80: C4 | L80: 757.98 | M80: 44 | N80: 757.98 | O80: 45794 | Q80: 21
A81: 8b2cf931 | B81: 4c68ae55 | C81: GOH01-0997 | D81: GOH01-1000 | E81: 179 | F81: C4 | G81: 757.98 | H81: 12FO | I81: OK | J81: 190 | K81: C4 | L81: 757.98 | M81: 11 | N81: 757.98 | O81: 45794 | Q81: 21
A82: a9de53ff | B82: 4c68ae55 | C82: GOH01-0976 | D82: GOH01-0998 | E82: 120 | F82: C4 | G82: 757.98 | H82: 12FO | I82: OK | J82: 130 | K82: C4 | L82: 757.98 | M82: 10 | N82: 757.98 | O82: 45794 | Q82: 21
A83: 12eb357d | B83: 4c68ae55 | C83: GOH01-0998 | D83: GOH01-0999 | E83: 166 | F83: C4 | G83: 757.98 | H83: 12FO | I83: OK | J83: 175 | K83: C4 | L83: 757.98 | M83: 9 | N83: 757.98 | O83: 45794 | Q83: 21
A84: 0b29d9bc | B84: a60479a8 | C84: NTL09-4853 | D84: NTL09-4852 | E84: 154 | F84: C4 | G84: 757 | H84: 12FO | I84: OK | J84: 275 | K84: C4 | L84: 757.98 | M84: 121 | N84: 757.98 | O84: 45768 | R84: Os_MAIO_RNPB_LANCA
A85: 4fe217cd | B85: a60479a8 | C85: NTL09-4852 | D85: NTL09-4851 | E85: 103 | F85: C4 | G85: 757 | H85: 12FO | I85: OK | J85: 145 | K85: C4 | L85: 757.98 | M85: 42 | N85: 757.98 | O85: 45768 | R85: Os_MAIO_RNPB_LANCA
A86: 4c149b5f | B86: a60479a8 | C86: NTL09-4851 | D86: NTL09-4850 | E86: 202 | F86: C4 | G86: 757 | H86: 12FO | I86: OK | J86: 270 | K86: C4 | L86: 757.98 | M86: 68 | N86: 757.98 | O86: 45768 | R86: Os_MAIO_RNPB_LANCA
A87: 5621f6cd | B87: a60479a8 | C87: NTL09-4850 | D87: NTL09-4849 | E87: 175 | F87: C4 | G87: 757 | H87: 12FO | I87: OK | J87: 200 | K87: C4 | L87: 757.98 | M87: 25 | N87: 757.98 | O87: 45768 | R87: Os_MAIO_RNPB_LANCA
A88: 8d4a2cf2 | B88: a60479a8 | C88: NTL09-4849 | D88: CEOSP8-08 | E88: 410 | F88: C5 | G88: 950 | H88: 12FO | I88: OK | J88: 500 | K88: C5 | L88: 950 | M88: 90 | N88: 950 | O88: 45768 | R88: Os_MAIO_RNPB_LANCA
A89: 6743d377 | B89: a60479a8 | C89: CEOSP8-08 | D89: NTL09-4854 | E89: 214 | F89: C4 | G89: 757 | H89: 12FO | I89: OK | J89: 200 | K89: C4 | L89: 757.98 | M89: -14 | N89: 757.98 | O89: 45768 | R89: Os_MAIO_RNPB_LANCA
A90: 5dcfc776 | B90: a60479a8 | C90: NTL09-4854 | D90: NTL09-4855 | E90: 114 | F90: C4 | G90: 757 | H90: 12FO | I90: OK | J90: 200 | K90: C4 | L90: 757.98 | M90: 86 | N90: 757.98 | O90: 45772 | R90: Os_MAIO_RNPB_LANCA
A91: b6e6ce79 | B91: a60479a8 | C91: NTL09-4855 | D91: NTL09-4856 | E91: 169 | F91: C4 | G91: 757 | H91: 12FO | I91: OK | J91: 240 | K91: C4 | L91: 757.98 | M91: 71 | N91: 757.98 | O91: 45772 | R91: Os_MAIO_RNPB_LANCA
A92: 13cc11e7 | B92: a60479a8 | C92: NTL09-4856 | D92: NTL09-4857 | E92: 88.3 | F92: C3 | G92: 490 | H92: 12FO | I92: OK | J92: 120 | K92: C4 | L92: 757.98 | M92: 31.7 | N92: 757.98 | O92: 45772 | R92: Os_MAIO_RNPB_LANCA
A93: ce3b9a9e | B93: a60479a8 | C93: CEOSP8-08 | D93: CEOSP2-04 | E93: 369 | F93: C5 | G93: 950 | H93: 24FO | I93: OK | J93: 510 | K93: C5 | L93: 950 | M93: 141 | N93: 950 | O93: 45761 | R93: Os_MAIO_RNPB_LANCA
A94: 2cac0b05 | B94: a60479a8 | C94: CEOSP8-08 | D94: NTL09-4858 | E94: 176 | F94: C4 | G94: 757 | H94: 12FO | I94: OK | J94: 200 | K94: C4 | L94: 757.98 | M94: 24 | N94: 757.98 | O94: 45769 | R94: Os_MAIO_RNPB_LANCA
A95: a145c125 | B95: a60479a8 | C95: NTL09-4858 | D95: NTL09-4859 | E95: 141 | F95: C4 | G95: 757 | H95: 12FO | I95: OK | J95: 250 | K95: C4 | L95: 757.98 | M95: 109 | N95: 757.98 | O95: 45769 | R95: Os_MAIO_RNPB_LANCA
... A233: 58685d4f | B233: bdb5204e | C233: CEOSP4-03 JP01 | D233: JPA00-3265/JPA00-3266 | E233: 74 | F233: C2/C3 | G233: 810 | H233: 12FO | I233: OK | J233: 98 | K233: C3 | L233: 490 | M233: 24 | N233: 490 | O233: 45793 | R233: Os_MAIO_RNPB_LANCA
A234: 3bb3614a | B234: bdb5204e | C234: JPA00-165/JPA00-1537 | D234: JPA00-3277 | E234: 180 | F234: C4 | G234: 757 | H234: 12FO | I234: OK | J234: 199 | K234: C4 | L234: 757.98 | M234: 199 | N234: 757.98 | O234: 45794 | P234: NÃO ESTAVA EM PROJETO, FOI SOLICITADO INSTALAÇÃO E LANÇAMENTO | R234: Os_MAIO_RNPB_LANCA
A235: 972545d2 | B235: 3731fad5 | C235: SGM01-1673 | D235: CEOSP4-05 | E235: 103 | F235: C4 | G235: 757 | H235: 12FO | I235: OK | J235: 175 | K235: C4 | L235: 757 | M235: 72 | N235: 757.98 | R235: Os_ABRIL_LANCA_RN
A236: 8d32f8cf | B236: 3731fad5 | C236: SGM01-1785 | D236: CEOSP4-06 SGA10 | E236: 230.65 | F236: C4 | G236: 757 | H236: 12FO | I236: OK | J236: 288 | K236: C4 | L236: 757 | M236: 57.35 | N236: 757.98 | R236: Os_ABRIL_LANCA_RN
A237: ffa614ce | B237: 3731fad5 | C237: SGM01-1777 | D237: CEOSP4-06 SGA10 | E237: 157.63 | F237: C4 | G237: 757 | H237: 12FO | I237: OK | J237: 251 | K237: C4 | L237: 757 | M237: 93.37 | N237: 757.98 | R237: Os_ABRIL_LANCA_RN
A238: 62d2dd85 | B238: 3731fad5 | C238: SGM01-1681 | D238: CEOSP8-01 | E238: 129 | F238: C4 | G238: 757 | H238: 12FO | I238: OK | J238: 180 | K238: C4 | L238: 757 | M238: 51 | N238: 757.98 | R238: Os_ABRIL_LANCA_RN
A239: 11b3e630 | B239: 3731fad5 | C239: SGM01-1819 | D239: CEOSP8-02 | E239: 767 | F239: C5 | G239: 950 | H239: 12FO | I239: OK | J239: 950 | K239: C5 | L239: 950 | M239: 183 | N239: 950 | R239: Os_ABRIL_LANCA_RN
A240: 4d7d2cee | B240: 3731fad5 | C240: NTL04-1160 | D240: SGM01-1631 | E240: 272 | F240: C4 | G240: 757 | H240: 12FO | I240: OK | J240: 300 | K240: C4 | L240: 757 | M240: 28 | N240: 757.98 | R240: Os_ABRIL_LANCA_RN
A241: 684bc801 | B241: 3731fad5 | C241: SGM01-1631 | D241: SGM01-1632 | E241: 42.2 | F241: C3 | G241: 490 | H241: 12FO | I241: OK | J241: 110 | K241: C4 | L241: 757 | M241: 67.8 | N241: 757.98 | R241: Os_ABRIL_LANCA_RN
A242: 7158c976 | B242: 3731fad5 | C242: SGM01-1674 | D242: SGM01-1673 | E242: 58.8 | F242: C3 | G242: 490 | H242: 12FO | I242: OK | J242: 100 | K242: C3 | L242: 490 | M242: 41.2 | N242: 490 | R242: Os_ABRIL_LANCA_RN
A243: bcbafe3a | B243: 3731fad5 | C243: Reserva | D243: CEOSP1-06 SGA10 | E243: 500 | F243: C5 | G243: 950 | H243: 24FO | I243: OK | J243: 500 | K243: C5 | L243: 950 | M243: 0 | N243: 950 | R243: Os_ABRIL_LANCA_RN
A244: 7c38cba8 | B244: 3731fad5 | C244: Reserva | D244: CEOSP1-06 SGA10 | E244: 170 | F244: C4 | G244: 757 | H244: 24FO | I244: OK | J244: 500 | K244: C4 | L244: 757 | M244: 330 | N244: 757.98 | R244: Os_ABRIL_LANCA_RN
A245: 8d0e96d7 | B245: 3731fad5 | C245: SGM01-1675 | D245: SGM01-1674 | E245: 67.9 | F245: C3 | G245: 490 | H245: 12FO | I245: OK | J245: 135 | K245: C4 | L245: 757 | M245: 67.1 | N245: 757.98 | R245: Os_ABRIL_LANCA_RN
A246: 6e5fabf8 | B246: 3731fad5 | C246: SGM01-1676 | D246: SGM01-1675 | E246: 82.5 | F246: C3 | G246: 490 | H246: 12FO | I246: OK | J246: 150 | K246: C4 | L246: 757 | M246: 67.5 | N246: 757.98 | R246: Os_ABRIL_LANCA_RN
... A414: a0e28c6c | B414: 3731fad5 | C414: SGM01-1855 | D414: SGM01-1856 | E414: 268.81 | F414: C4 | G414: 757 | H414: 12FO | I414: OK | J414: 276 | K414: C4 | L414: 757 | M414: 7.19 | N414: 757.98 | R414: Os_ABRIL_LANCA_RN
A415: 77bd8018 | B415: 7ce090f8 | C415: CEOAT-02 | D415: NTL02-261 | E415: 670 | F415: C5 | G415: 1386 | H415: 12FO | I415: OK | J415: 662 | K415: C5 | L415: 1386 | M415: -8 | N415: 1386 | O415: 45897 | Q415: 0611f994 | R415: import_lanc_25082025
A416: f9fde636 | B416: 7ce090f8 | C416: NTL02-261 | D416: NTL02-262 | E416: 333 | F416: C5 | G416: 1386 | H416: 12FO | I416: OK | J416: 343 | K416: C5 | L416: 1386 | M416: 10 | N416: 1386 | O416: 45897 | Q416: 0611f994 | R416: import_lanc_25082025
A417: 44b11665 | B417: 7ce090f8 | C417: NTL02-262 | D417: NTL02-263 | E417: 489 | F417: C5 | G417: 1386 | H417: 12FO | I417: OK | J417: 485 | K417: C5 | L417: 1386 | M417: -4 | N417: 1386 | O417: 45897 | Q417: 0611f994 | R417: import_lanc_25082025
A418: 7bef4a80 | B418: 7ce090f8 | C418: NTL02-263 | D418: NTL02-264 | E418: 280 | F418: C4 | G418: 900.9 | H418: 12FO | I418: OK | J418: 312 | K418: C5 | L418: 1386 | M418: 32 | N418: 1386 | O418: 45897 | Q418: 0611f994 | R418: import_lanc_25082025
A419: 6acba430 | B419: 8ff21d28 | C419: CEOSP4- 361 | D419: JPA00-3289 | E419: 224 | F419: C4 | G419: 900.9 | H419: 12FO | I419: OK | J419: 245 | K419: C4 | L419: 900.9 | M419: 21 | N419: 900.9 | O419: 45897 | Q419: 60db2b1b | R419: import_lanc_26082025
A420: 7269d28e | B420: 8ff21d28 | C420: JPA00-3289 | D420: JPA00-3290 | E420: 150 | F420: C4 | G420: 900.9 | H420: 12FO | I420: OOK | J420: 179 | K420: C4 | L420: 900.9 | M420: 29 | N420: 900.9 | O420: 45897 | Q420: 60db2b1b | R420: import_lanc_26082025
A421: a279c73a | B421: 8ff21d28 | C421: JPA00-3290 | D421: JPA00-3291 | E421: 165 | F421: C4 | G421: 900.9 | H421: 12FO | I421: OK | J421: 198 | K421: C4 | L421: 900.9 | M421: 33 | N421: 900.9 | O421: 45897 | Q421: 60db2b1b | R421: import_lanc_26082025
...

Sheet Din_OS

Sheet Tabela
A1: DT Padrão | B1: Data | C1: Dia da Semana | D1: Entrante | E1: No Prazo | F1: Fora do Prazo | G1: % Prazo | H1: Cabo aplicado | J1: Acumulado | M1: Simulador | N1: Em aberto
A2: =C2 -> 45658 | B2: =IF(C2="","",(TEXT(C2,"DD")&"/"&TEXT(C2,"MM")&"/"&TEXT(C2,"yy"))) -> 01/01/yy | C2: 45658 | D2: =COUNTIF(Os!$AI:$AI,$B2)+3 -> 3 | E2: =COUNTIFS(Os!$AJ:$AJ,$B2,Os!$AK:$AK,"No Prazo",Os!$M:$M,"Concluído") -> 0 | F2: =COUNTIFS(Os!$AJ:$AJ,$B2,Os!$AK:$AK,"Fora do Prazo") -> 0 | G2: =IFERROR(E2/SUM(E2:F2),"-") -> - | J2: Entrante | K2: =SUM(D2:D32) -> 3 | M2: =R13/4 -> 0 | N2: =K2-SUM(K3:K4) -> 3
A3: =A2+1 -> 45659 | B3: =IF(C3="","",(TEXT(C3,"DD")&"/"&TEXT(C3,"MM")&"/"&TEXT(C3,"yy"))) -> 02/01/yy | C3: =C2+1 -> 45659 | D3: =COUNTIF(Os!$AI:$AI,$B3) -> 0 | E3: =COUNTIFS(Os!$AJ:$AJ,$B3,Os!$AK:$AK,"No Prazo",Os!$M:$M,"Concluído") -> 0 | F3: =COUNTIFS(Os!$AJ:$AJ,$B3,Os!$AK:$AK,"Fora do Prazo") -> 0 | G3: =IFERROR(E3/SUM(E3:F3),"-") -> - | J3: No Prazo | K3: =SUM(E2:E32) -> 0
A4: =A3+1 -> 45660 | B4: =IF(C4="","",(TEXT(C4,"DD")&"/"&TEXT(C4,"MM")&"/"&TEXT(C4,"yy"))) -> 03/01/yy | C4: =C3+1 -> 45660 | D4: =COUNTIF(Os!$AI:$AI,$B4) -> 0 | E4: =COUNTIFS(Os!$AJ:$AJ,$B4,Os!$AK:$AK,"No Prazo",Os!$M:$M,"Concluído") -> 0 | F4: =COUNTIFS(Os!$AJ:$AJ,$B4,Os!$AK:$AK,"Fora do Prazo") -> 0 | G4: =IFERROR(E4/SUM(E4:F4),"-") -> - | J4: Fora do Prazo | K4: =SUM(F2:F32) -> 0
A5: =A4+1 -> 45661 | B5: =IF(C5="","",(TEXT(C5,"DD")&"/"&TEXT(C5,"MM")&"/"&TEXT(C5,"yy"))) -> 04/01/yy | C5: =C4+1 -> 45661 | D5: =COUNTIF(Os!$AI:$AI,$B5) -> 0 | E5: =COUNTIFS(Os!$AJ:$AJ,$B5,Os!$AK:$AK,"No Prazo",Os!$M:$M,"Concluído") -> 0 | F5: =COUNTIFS(Os!$AJ:$AJ,$B5,Os!$AK:$AK,"Fora do Prazo") -> 0 | G5: =IFERROR(E5/SUM(E5:F5),"-") -> - | J5: % Prazo | K5: =K3/SUM(K3:K4) -> #DIV/0!
A6: =A5+1 -> 45662 | B6: =IF(C6="","",(TEXT(C6,"DD")&"/"&TEXT(C6,"MM")&"/"&TEXT(C6,"yy"))) -> 05/01/yy | C6: =C5+1 -> 45662 | D6: =COUNTIF(Os!$AI:$AI,$B6) -> 0 | E6: =COUNTIFS(Os!$AJ:$AJ,$B6,Os!$AK:$AK,"No Prazo",Os!$M:$M,"Concluído") -> 0 | F6: =COUNTIFS(Os!$AJ:$AJ,$B6,Os!$AK:$AK,"Fora do Prazo") -> 0 | G6: =IFERROR(E6/SUM(E6:F6),"-") -> -
A7: =A6+1 -> 45663 | B7: =IF(C7="","",(TEXT(C7,"DD")&"/"&TEXT(C7,"MM")&"/"&TEXT(C7,"yy"))) -> 06/01/yy | C7: =C6+1 -> 45663 | D7: =COUNTIF(Os!$AI:$AI,$B7) -> 0 | E7: =COUNTIFS(Os!$AJ:$AJ,$B7,Os!$AK:$AK,"No Prazo",Os!$M:$M,"Concluído") -> 0 | F7: =COUNTIFS(Os!$AJ:$AJ,$B7,Os!$AK:$AK,"Fora do Prazo") -> 0 | G7: =IFERROR(E7/SUM(E7:F7),"-") -> - | Q7: Entrante
A8: =A7+1 -> 45664 | B8: =IF(C8="","",(TEXT(C8,"DD")&"/"&TEXT(C8,"MM")&"/"&TEXT(C8,"yy"))) -> 07/01/yy | C8: =C7+1 -> 45664 | D8: =COUNTIF(Os!$AI:$AI,$B8) -> 0 | E8: =COUNTIFS(Os!$AJ:$AJ,$B8,Os!$AK:$AK,"No Prazo",Os!$M:$M,"Concluído") -> 0 | F8: =COUNTIFS(Os!$AJ:$AJ,$B8,Os!$AK:$AK,"Fora do Prazo") -> 0 | G8: =IFERROR(E8/SUM(E8:F8),"-") -> - | Q8: No Prazo | R8: =4*R9 -> 0
A9: =A8+1 -> 45665 | B9: =IF(C9="","",(TEXT(C9,"DD")&"/"&TEXT(C9,"MM")&"/"&TEXT(C9,"yy"))) -> 08/01/yy | C9: =C8+1 -> 45665 | D9: =COUNTIF(Os!$AI:$AI,$B9) -> 0 | E9: =COUNTIFS(Os!$AJ:$AJ,$B9,Os!$AK:$AK,"No Prazo",Os!$M:$M,"Concluído") -> 0 | F9: =COUNTIFS(Os!$AJ:$AJ,$B9,Os!$AK:$AK,"Fora do Prazo") -> 0 | G9: =IFERROR(E9/SUM(E9:F9),"-") -> - | Q9: Fora do Prazo | R9: =K4 -> 0
A10: =A9+1 -> 45666 | B10: =IF(C10="","",(TEXT(C10,"DD")&"/"&TEXT(C10,"MM")&"/"&TEXT(C10,"yy"))) -> 09/01/yy | C10: =C9+1 -> 45666 | D10: =COUNTIF(Os!$AI:$AI,$B10) -> 0 | E10: =COUNTIFS(Os!$AJ:$AJ,$B10,Os!$AK:$AK,"No Prazo",Os!$M:$M,"Concluído") -> 0 | F10: =COUNTIFS(Os!$AJ:$AJ,$B10,Os!$AK:$AK,"Fora do Prazo") -> 0 | G10: =IFERROR(E10/SUM(E10:F10),"-") -> - | Q10: % Prazo | R10: =R8/SUM(R8:R9) -> #DIV/0!
A11: =A10+1 -> 45667 | B11: =IF(C11="","",(TEXT(C11,"DD")&"/"&TEXT(C11,"MM")&"/"&TEXT(C11,"yy"))) -> 10/01/yy | C11: =C10+1 -> 45667 | D11: =COUNTIF(Os!$AI:$AI,$B11) -> 0 | E11: =COUNTIFS(Os!$AJ:$AJ,$B11,Os!$AK:$AK,"No Prazo",Os!$M:$M,"Concluído") -> 0 | F11: =COUNTIFS(Os!$AJ:$AJ,$B11,Os!$AK:$AK,"Fora do Prazo") -> 0 | G11: =IFERROR(E11/SUM(E11:F11),"-") -> -
A12: =A11+1 -> 45668 | B12: =IF(C12="","",(TEXT(C12,"DD")&"/"&TEXT(C12,"MM")&"/"&TEXT(C12,"yy"))) -> 11/01/yy | C12: =C11+1 -> 45668 | D12: =COUNTIF(Os!$AI:$AI,$B12) -> 0 | E12: =COUNTIFS(Os!$AJ:$AJ,$B12,Os!$AK:$AK,"No Prazo",Os!$M:$M,"Concluído") -> 0 | F12: =COUNTIFS(Os!$AJ:$AJ,$B12,Os!$AK:$AK,"Fora do Prazo") -> 0 | G12: =IFERROR(E12/SUM(E12:F12),"-") -> - | Q12: Reparos que preciso fazer para está NO PRAZO
A13: =A12+1 -> 45669 | B13: =IF(C13="","",(TEXT(C13,"DD")&"/"&TEXT(C13,"MM")&"/"&TEXT(C13,"yy"))) -> 12/01/yy | C13: =C12+1 -> 45669 | D13: =COUNTIF(Os!$AI:$AI,$B13) -> 0 | E13: =COUNTIFS(Os!$AJ:$AJ,$B13,Os!$AK:$AK,"No Prazo",Os!$M:$M,"Concluído") -> 0 | F13: =COUNTIFS(Os!$AJ:$AJ,$B13,Os!$AK:$AK,"Fora do Prazo") -> 0 | G13: =IFERROR(E13/SUM(E13:F13),"-") -> - | R13: =R8-K3 -> 0
A14: =A13+1 -> 45670 | B14: =IF(C14="","",(TEXT(C14,"DD")&"/"&TEXT(C14,"MM")&"/"&TEXT(C14,"yy"))) -> 13/01/yy | C14: =C13+1 -> 45670 | D14: =COUNTIF(Os!$AI:$AI,$B14) -> 0 | E14: =COUNTIFS(Os!$AJ:$AJ,$B14,Os!$AK:$AK,"No Prazo",Os!$M:$M,"Concluído") -> 0 | F14: =COUNTIFS(Os!$AJ:$AJ,$B14,Os!$AK:$AK,"Fora do Prazo") -> 0 | G14: =IFERROR(E14/SUM(E14:F14),"-") -> -
A15: =A14+1 -> 45671 | B15: =IF(C15="","",(TEXT(C15,"DD")&"/"&TEXT(C15,"MM")&"/"&TEXT(C15,"yy"))) -> 14/01/yy | C15: =C14+1 -> 45671 | D15: =COUNTIF(Os!$AI:$AI,$B15) -> 0 | E15: =COUNTIFS(Os!$AJ:$AJ,$B15,Os!$AK:$AK,"No Prazo",Os!$M:$M,"Concluído") -> 0 | F15: =COUNTIFS(Os!$AJ:$AJ,$B15,Os!$AK:$AK,"Fora do Prazo") -> 0 | G15: =IFERROR(E15/SUM(E15:F15),"-") -> -
A16: =A15+1 -> 45672 | B16: =IF(C16="","",(TEXT(C16,"DD")&"/"&TEXT(C16,"MM")&"/"&TEXT(C16,"yy"))) -> 15/01/yy | C16: =C15+1 -> 45672 | D16: =COUNTIF(Os!$AI:$AI,$B16) -> 0 | E16: =COUNTIFS(Os!$AJ:$AJ,$B16,Os!$AK:$AK,"No Prazo",Os!$M:$M,"Concluído") -> 0 | F16: =COUNTIFS(Os!$AJ:$AJ,$B16,Os!$AK:$AK,"Fora do Prazo") -> 0 | G16: =IFERROR(E16/SUM(E16:F16),"-") -> - | K16: * Qtde por tecnico
A17: =A16+1 -> 45673 | B17: =IF(C17="","",(TEXT(C17,"DD")&"/"&TEXT(C17,"MM")&"/"&TEXT(C17,"yy"))) -> 16/01/yy | C17: =C16+1 -> 45673 | D17: =COUNTIF(Os!$AI:$AI,$B17) -> 0 | E17: =COUNTIFS(Os!$AJ:$AJ,$B17,Os!$AK:$AK,"No Prazo",Os!$M:$M,"Concluído") -> 0 | F17: =COUNTIFS(Os!$AJ:$AJ,$B17,Os!$AK:$AK,"Fora do Prazo") -> 0 | G17: =IFERROR(E17/SUM(E17:F17),"-") -> - | K17: * Do concluido - qto teve cabo apliacado
A18: =A17+1 -> 45674 | B18: =IF(C18="","",(TEXT(C18,"DD")&"/"&TEXT(C18,"MM")&"/"&TEXT(C18,"yy"))) -> 17/01/yy | C18: =C17+1 -> 45674 | D18: =COUNTIF(Os!$AI:$AI,$B18) -> 0 | E18: =COUNTIFS(Os!$AJ:$AJ,$B18,Os!$AK:$AK,"No Prazo",Os!$M:$M,"Concluído") -> 0 | F18: =COUNTIFS(Os!$AJ:$AJ,$B18,Os!$AK:$AK,"Fora do Prazo") -> 0 | G18: =IFERROR(E18/SUM(E18:F18),"-") -> - | K18: * Qtos reparos pode perder para ainda ficar na meta - com virgula
A19: =A18+1 -> 45675 | B19: =IF(C19="","",(TEXT(C19,"DD")&"/"&TEXT(C19,"MM")&"/"&TEXT(C19,"yy"))) -> 18/01/yy | C19: =C18+1 -> 45675 | D19: =COUNTIF(Os!$AI:$AI,$B19) -> 0 | E19: =COUNTIFS(Os!$AJ:$AJ,$B19,Os!$AK:$AK,"No Prazo",Os!$M:$M,"Concluído") -> 0 | F19: =COUNTIFS(Os!$AJ:$AJ,$B19,Os!$AK:$AK,"Fora do Prazo") -> 0 | G19: =IFERROR(E19/SUM(E19:F19),"-") -> - | K19: * Pareto com os responsaveis pela causa
A20: =A19+1 -> 45676 | B20: =IF(C20="","",(TEXT(C20,"DD")&"/"&TEXT(C20,"MM")&"/"&TEXT(C20,"yy"))) -> 19/01/yy | C20: =C19+1 -> 45676 | D20: =COUNTIF(Os!$AI:$AI,$B20) -> 0 | E20: =COUNTIFS(Os!$AJ:$AJ,$B20,Os!$AK:$AK,"No Prazo",Os!$M:$M,"Concluído") -> 0 | F20: =COUNTIFS(Os!$AJ:$AJ,$B20,Os!$AK:$AK,"Fora do Prazo") -> 0 | G20: =IFERROR(E20/SUM(E20:F20),"-") -> - | K20: * SImular resultado expurgando causas diferentes sem acesso cliente, sem acesso ARd
A21: =A20+1 -> 45677 | B21: =IF(C21="","",(TEXT(C21,"DD")&"/"&TEXT(C21,"MM")&"/"&TEXT(C21,"yy"))) -> 20/01/yy | C21: =C20+1 -> 45677 | D21: =COUNTIF(Os!$AI:$AI,$B21) -> 0 | E21: =COUNTIFS(Os!$AJ:$AJ,$B21,Os!$AK:$AK,"No Prazo",Os!$M:$M,"Concluído") -> 0 | F21: =COUNTIFS(Os!$AJ:$AJ,$B21,Os!$AK:$AK,"Fora do Prazo") -> 0 | G21: =IFERROR(E21/SUM(E21:F21),"-") -> -
A22: =A21+1 -> 45678 | B22: =IF(C22="","",(TEXT(C22,"DD")&"/"&TEXT(C22,"MM")&"/"&TEXT(C22,"yy"))) -> 21/01/yy | C22: =C21+1 -> 45678 | D22: =COUNTIF(Os!$AI:$AI,$B22) -> 0 | E22: =COUNTIFS(Os!$AJ:$AJ,$B22,Os!$AK:$AK,"No Prazo",Os!$M:$M,"Concluído") -> 0 | F22: =COUNTIFS(Os!$AJ:$AJ,$B22,Os!$AK:$AK,"Fora do Prazo") -> 0 | G22: =IFERROR(E22/SUM(E22:F22),"-") -> -
A23: =A22+1 -> 45679 | B23: =IF(C23="","",(TEXT(C23,"DD")&"/"&TEXT(C23,"MM")&"/"&TEXT(C23,"yy"))) -> 22/01/yy | C23: =C22+1 -> 45679 | D23: =COUNTIF(Os!$AI:$AI,$B23) -> 0 | E23: =COUNTIFS(Os!$AJ:$AJ,$B23,Os!$AK:$AK,"No Prazo",Os!$M:$M,"Concluído") -> 0 | F23: =COUNTIFS(Os!$AJ:$AJ,$B23,Os!$AK:$AK,"Fora do Prazo") -> 0 | G23: =IFERROR(E23/SUM(E23:F23),"-") -> -
A24: =A23+1 -> 45680 | B24: =IF(C24="","",(TEXT(C24,"DD")&"/"&TEXT(C24,"MM")&"/"&TEXT(C24,"yy"))) -> 23/01/yy | C24: =C23+1 -> 45680 | D24: =COUNTIF(Os!$AI:$AI,$B24) -> 0 | E24: =COUNTIFS(Os!$AJ:$AJ,$B24,Os!$AK:$AK,"No Prazo",Os!$M:$M,"Concluído") -> 0 | F24: =COUNTIFS(Os!$AJ:$AJ,$B24,Os!$AK:$AK,"Fora do Prazo") -> 0 | G24: =IFERROR(E24/SUM(E24:F24),"-") -> -
A25: =A24+1 -> 45681 | B25: =IF(C25="","",(TEXT(C25,"DD")&"/"&TEXT(C25,"MM")&"/"&TEXT(C25,"yy"))) -> 24/01/yy | C25: =C24+1 -> 45681 | D25: =COUNTIF(Os!$AI:$AI,$B25) -> 0 | E25: =COUNTIFS(Os!$AJ:$AJ,$B25,Os!$AK:$AK,"No Prazo",Os!$M:$M,"Concluído") -> 0 | F25: =COUNTIFS(Os!$AJ:$AJ,$B25,Os!$AK:$AK,"Fora do Prazo") -> 0 | G25: =IFERROR(E25/SUM(E25:F25),"-") -> -
A26: =A25+1 -> 45682 | B26: =IF(C26="","",(TEXT(C26,"DD")&"/"&TEXT(C26,"MM")&"/"&TEXT(C26,"yy"))) -> 25/01/yy | C26: =C25+1 -> 45682 | D26: =COUNTIF(Os!$AI:$AI,$B26) -> 0 | E26: =COUNTIFS(Os!$AJ:$AJ,$B26,Os!$AK:$AK,"No Prazo",Os!$M:$M,"Concluído") -> 0 | F26: =COUNTIFS(Os!$AJ:$AJ,$B26,Os!$AK:$AK,"Fora do Prazo") -> 0 | G26: =IFERROR(E26/SUM(E26:F26),"-") -> -
A27: =A26+1 -> 45683 | B27: =IF(C27="","",(TEXT(C27,"DD")&"/"&TEXT(C27,"MM")&"/"&TEXT(C27,"yy"))) -> 26/01/yy | C27: =C26+1 -> 45683 | D27: =COUNTIF(Os!$AI:$AI,$B27) -> 0 | E27: =COUNTIFS(Os!$AJ:$AJ,$B27,Os!$AK:$AK,"No Prazo",Os!$M:$M,"Concluído") -> 0 | F27: =COUNTIFS(Os!$AJ:$AJ,$B27,Os!$AK:$AK,"Fora do Prazo") -> 0 | G27: =IFERROR(E27/SUM(E27:F27),"-") -> -
A28: =A27+1 -> 45684 | B28: =IF(C28="","",(TEXT(C28,"DD")&"/"&TEXT(C28,"MM")&"/"&TEXT(C28,"yy"))) -> 27/01/yy | C28: =C27+1 -> 45684 | D28: =COUNTIF(Os!$AI:$AI,$B28) -> 0 | E28: =COUNTIFS(Os!$AJ:$AJ,$B28,Os!$AK:$AK,"No Prazo",Os!$M:$M,"Concluído") -> 0 | F28: =COUNTIFS(Os!$AJ:$AJ,$B28,Os!$AK:$AK,"Fora do Prazo") -> 0 | G28: =IFERROR(E28/SUM(E28:F28),"-") -> -
A29: =A28+1 -> 45685 | B29: =IF(C29="","",(TEXT(C29,"DD")&"/"&TEXT(C29,"MM")&"/"&TEXT(C29,"yy"))) -> 28/01/yy | C29: =C28+1 -> 45685 | D29: =COUNTIF(Os!$AI:$AI,$B29) -> 0 | E29: =COUNTIFS(Os!$AJ:$AJ,$B29,Os!$AK:$AK,"No Prazo",Os!$M:$M,"Concluído") -> 0 | F29: =COUNTIFS(Os!$AJ:$AJ,$B29,Os!$AK:$AK,"Fora do Prazo") -> 0 | G29: =IFERROR(E29/SUM(E29:F29),"-") -> -
A30: =A29+1 -> 45686 | B30: =IF(C30="","",(TEXT(C30,"DD")&"/"&TEXT(C30,"MM")&"/"&TEXT(C30,"yy"))) -> 29/01/yy | C30: =C29+1 -> 45686 | D30: =COUNTIF(Os!$AI:$AI,$B30) -> 0 | E30: =COUNTIFS(Os!$AJ:$AJ,$B30,Os!$AK:$AK,"No Prazo",Os!$M:$M,"Concluído") -> 0 | F30: =COUNTIFS(Os!$AJ:$AJ,$B30,Os!$AK:$AK,"Fora do Prazo") -> 0 | G30: =IFERROR(E30/SUM(E30:F30),"-") -> -
A31: =A30+1 -> 45687 | B31: =IF(C31="","",(TEXT(C31,"DD")&"/"&TEXT(C31,"MM")&"/"&TEXT(C31,"yy"))) -> 30/01/yy | C31: =C30+1 -> 45687 | D31: =COUNTIF(Os!$AI:$AI,$B31) -> 0 | E31: =COUNTIFS(Os!$AJ:$AJ,$B31,Os!$AK:$AK,"No Prazo",Os!$M:$M,"Concluído") -> 0 | F31: =COUNTIFS(Os!$AJ:$AJ,$B31,Os!$AK:$AK,"Fora do Prazo") -> 0 | G31: =IFERROR(E31/SUM(E31:F31),"-") -> -
A32: =A31+1 -> 45688 | B32: =IF(C32="","",(TEXT(C32,"DD")&"/"&TEXT(C32,"MM")&"/"&TEXT(C32,"yy"))) -> 31/01/yy | C32: =C31+1 -> 45688 | D32: =COUNTIF(Os!$AI:$AI,$B32) -> 0 | E32: =COUNTIFS(Os!$AJ:$AJ,$B32,Os!$AK:$AK,"No Prazo",Os!$M:$M,"Concluído") -> 0 | F32: =COUNTIFS(Os!$AJ:$AJ,$B32,Os!$AK:$AK,"Fora do Prazo") -> 0 | G32: =IFERROR(E32/SUM(E32:F32),"-") -> -
E33: =IF(F33="","",$E$2)
E34: =IF(F34="","",$E$2)

Sheet Motivo
A1: IdMotivo | B1: CodMotivo | C1: Descricao | D1: Tipo
A2: MOT1 | B2: 0 | C2: INVENTÁRIO | D2: INVENTÁRIO
A3: MOT2 | B3: 10 | C3: ENTRADA DO CLIENTE | D3: ENTRADA
A4: MOT3 | B4: 11 | C4: ENTRADA DE O.S | D4: ENTRADA
A5: MOT4 | B5: 12 | C5: COMPRA DE MATERIAL PRÓPRIO | D5: ENTRADA
A6: MOT5 | B6: 20 | C6: BAIXA DE MATERIAL | D6: SAIDA
A7: MOT6 | B7: 21 | C7: DEVOLUÇÃO PARA CLIENTE | D7: SAIDA
A8: MOT7 | B8: 30 | C8: TRANSFERENCIA ENTRE ALMOXARIFADOS | D8: TRANSFERENCIA

Sheet TpMov
A1: IdTpMov | B1: TpMov | C1: Tipo
A2: ENTRADA | B2: ENTRADA | C2: tec
A3: SAIDA | B3: SAIDA | C3: tec
A4: INVENTÁRIO | B4: INVENTÁRIO
A5: TRANSFERENCIA | B5: TRANSFERENCIA

Sheet Din_Pareto
A1: #REF! | C1: Paret. | D1: cont | E1: cont2 | F1: x | G1: Perda | H1: Contagem | I1: Pareto
C2: =B2/SUM($B$2:$B$29) -> #DIV/0! | D2: 0.01 | E2: =B2+D2 -> 0.01 | G2: {=IF(A2="","Sem dados", INDEX(A:A,MATCH($H2,E:E,0)))} -> Sem dados | H2: =LARGE($E$2:$E$6,1) -> 0.05 | I2: =H2/SUM($H$2:$H$6) -> 0.33333333
C3: =B3/SUM($B$2:$B$29)+C2 -> #DIV/0! | D3: =D2+0.01 -> 0.02 | E3: =B3+D3 -> 0.02 | G3: =INDEX(A:A,MATCH($H3,E:E,0)) -> 0 | H3: =LARGE($E$2:$E$6,2) -> 0.04 | I3: =H3/SUM($H$2:$H$6)+I2 -> 0.6
C4: =B4/SUM($B$2:$B$29)+C3 -> #DIV/0! | D4: =D3+0.01 -> 0.03 | E4: =B4+D4 -> 0.03 | G4: =INDEX(A:A,MATCH($H4,E:E,0)) -> 0 | H4: =LARGE($E$2:$E$6,3) -> 0.03 | I4: =H4/SUM($H$2:$H$6)+I3 -> 0.8
C5: =B5/SUM($B$2:$B$29)+C4 -> #DIV/0! | D5: =D4+0.01 -> 0.04 | E5: =B5+D5 -> 0.04 | G5: =INDEX(A:A,MATCH($H5,E:E,0)) -> 0 | H5: =LARGE($E$2:$E$6,4) -> 0.02 | I5: =H5/SUM($H$2:$H$6)+I4 -> 0.93333333
C6: =B6/SUM($B$2:$B$29)+C5 -> #DIV/0! | D6: =D5+0.01 -> 0.05 | E6: =B6+D6 -> 0.05 | G6: =INDEX(A:A,MATCH($H6,E:E,0)) -> 0 | H6: =LARGE($E$2:$E$6,5) -> 0.01 | I6: =H6/SUM($H$2:$H$6)+I5 -> 1

Sheet Tab_Contrato
A1: Contrato | B1: Cliente
A3: Unifor
A4: MobWIre
A5: Tecnomulti

Sheet Tab_Obras
A1: Obra
A2: Obras Crato
A3: Obras Ceará
A4: Equipes Classe C
A5: Equipes Classe F
A6: Preventivas
A7: LD - PACOTI
A8: Obras Sergipe
A9: Equipes Classe F - (MA)
A10: Cab. Estruturado (Unifor)
A11: Equipes Reparadores
A12: B2B - RN
... A18: Equipes Disposição

Sheet Tab_Responsavel
A1: Responsavel | B1: Cliente
A2: Celso | B2: R2
A3: Marquinho | B3: R2
A4: Rógerio | B4: R2
A5: Clodomar | B5: R2
A6: Djair | B6: R2
A7: Batista | B7: R2
A8: Arlison | B8: R2
A9: Carlos Augusto | B9: R2
A10: Marcelo | B10: R2
A11: Adenilson | B11: UNIFOR
A12: Clebio | B12: R2
... A15: Adriano | B15: R2
A16: Oberdan
A17: Jonas
A18: Frank
A19: ANGELO FABRICIO | B19: R2
A20: Cleiton
A21: MARCILIO

Sheet Tab_Produtos
A1: Produto | B1: Cliente
A2: Cabeamento Estruturado
A3: Wi-Fi
A4: Equipe Disposição
A5: Camera PTZ
A6: Camera Fixa
A7: Adequação Enel
A8: Construção de Rede - LD
A9: Reparo - Classe F
A10: Reparo - Classe C
A11: Link de Dados
A12: Raiser
A13: Obra B2B
... A18: Vistoria de Poste
A19: Reparo - GPON | B19: VIVO
A20: Reparo - BBR | B20: VIVO
A21: Preventiva Postes
A22: Formatação de Sites
A25: Reparo - Disp - VIVO - Classe F | B25: VIVO
A26: Reparo - Disp - VIVO - Classe C | B26: VIVO
A27: Reparo - Disp - V.tal - Classe F | B27: V.tal
A28: Contrato - GPON | B28: R2 - VIVO
A29: Contrato B2B - GPON | B29: R2 - VIVO

Sheet Tab_Cidades
A1: Cidades
A2: Alta Floresta D´oeste - RO
A3: Ariquemes - RO
A4: Cabixi - RO
A5: Cacoal - RO
A6: Cerejeiras - RO
A7: Colorado do Oeste - RO
A8: Corumbiara - RO
A9: Costa Marques - RO
A10: Espigão D´oeste - RO
A11: Guajará-mirim - RO
A12: Jaru - RO
... A5578: b46e1afe

Sheet Tab_StatusOperacao
A1: Status_Operacao
A2: Lib. Execução
A3: Em Execução
A4: Aguard. Liberação
A5: Concluído
A6: Pend. Cliente
A7: Aguard. Material
A8: Cancelado
A9: Pend. Ativação
A10: Iniciar
A11: Declinado sem Acesso

Sheet Tab_StatusMedicao
A1: Status_Medicao
A2: Não Medido
A3: Em Medição
A4: Medição Concluída
A5: Medição Aceita
A6: NF Emitida
A7: Medição Enviada
A8: NF Recebida

Sheet Indicadores
A1: Status de Operação | B1: =COUNTA(Os!B:B)-1 -> 0 | D1: Status de Operação | E1: =SUM(Os!L:L) -> 2130253
A2: Concluído | B2: =COUNTIF(Os!M:M,A2) -> 377 | D2: Em Medição | E2: =SUMIF(Os!Q:Q,D2,Os!L:L) -> 0
A3: Realização Física | B3: =B2/B1 -> #DIV/0! | D3: Não Medido | E3: =SUMIF(Os!Q:Q,D3,Os!L:L) -> 465462.35
D4: (-) Realizado | E4: =E1-SUM(E2:E3) -> 1664790.7
D5: Realização Financeira | E5: =E4/E1 -> 0.78149903

Sheet TAB Indicadores
A1: Total Realizado | B1: Real Opera | C1: R$ em Medição | D1: R$ Não Medido | E1: Valor Serviço 2 | F1: Real Financeiro
A2: =IF(#REF!<>"",1,0) -> #REF! | B2: =IF(#REF!="Concluído",1,"") -> #REF! | C2: =IFERROR(SUMIF(#REF!,"Em Medição",#REF!),"") | D2: =IFERROR(SUMIF(#REF!,"Não Medido",#REF!),"") | E2: =IFERROR(#REF!,"") | F2: =E2-SUM(C2:D2) -> #VALUE!
A3: =IF(#REF!<>"",1,0) -> #REF! | B3: =IF(#REF!="Concluído",1,"") -> #REF! | C3: =IFERROR(SUMIF(#REF!,"Em Medição",#REF!),"") | D3: =IFERROR(SUMIF(#REF!,"Não Medido",#REF!),"") | E3: =IFERROR(#REF!,"") | F3: =E3-SUM(C3:D3) -> #VALUE!
A4: =IF(#REF!<>"",1,0) -> #REF! | B4: =IF(#REF!="Concluído",1,"") -> #REF! | C4: =IFERROR(SUMIF(#REF!,"Em Medição",#REF!),"") | D4: =IFERROR(SUMIF(#REF!,"Não Medido",#REF!),"") | E4: =IFERROR(#REF!,"") | F4: =E4-SUM(C4:D4) -> #VALUE!
A5: =IF(#REF!<>"",1,0) -> #REF! | B5: =IF(#REF!="Concluído",1,"") -> #REF! | C5: =IFERROR(SUMIF(#REF!,"Em Medição",#REF!),"") | D5: =IFERROR(SUMIF(#REF!,"Não Medido",#REF!),"") | E5: =IFERROR(#REF!,"") | F5: =E5-SUM(C5:D5) -> #VALUE!
A6: =IF(#REF!<>"",1,0) -> #REF! | B6: =IF(#REF!="Concluído",1,"") -> #REF! | C6: =IFERROR(SUMIF(#REF!,"Em Medição",#REF!),"") | D6: =IFERROR(SUMIF(#REF!,"Não Medido",#REF!),"") | E6: =IFERROR(#REF!,"") | F6: =E6-SUM(C6:D6) -> #VALUE!
A7: =IF(#REF!<>"",1,0) -> #REF! | B7: =IF(#REF!="Concluído",1,"") -> #REF! | C7: =IFERROR(SUMIF(#REF!,"Em Medição",#REF!),"") | D7: =IFERROR(SUMIF(#REF!,"Não Medido",#REF!),"") | E7: =IFERROR(#REF!,"") | F7: =E7-SUM(C7:D7) -> #VALUE!
A8: =IF(#REF!<>"",1,0) -> #REF! | B8: =IF(#REF!="Concluído",1,"") -> #REF! | C8: =IFERROR(SUMIF(#REF!,"Em Medição",#REF!),"") | D8: =IFERROR(SUMIF(#REF!,"Não Medido",#REF!),"") | E8: =IFERROR(#REF!,"") | F8: =E8-SUM(C8:D8) -> #VALUE!
A9: =IF(#REF!<>"",1,0) -> #REF! | B9: =IF(#REF!="Concluído",1,"") -> #REF! | C9: =IFERROR(SUMIF(#REF!,"Em Medição",#REF!),"") | D9: =IFERROR(SUMIF(#REF!,"Não Medido",#REF!),"") | E9: =IFERROR(#REF!,"") | F9: =E9-SUM(C9:D9) -> #VALUE!
A10: =IF(#REF!<>"",1,0) -> #REF! | B10: =IF(#REF!="Concluído",1,"") -> #REF! | C10: =IFERROR(SUMIF(#REF!,"Em Medição",#REF!),"") | D10: =IFERROR(SUMIF(#REF!,"Não Medido",#REF!),"") | E10: =IFERROR(#REF!,"") | F10: =E10-SUM(C10:D10) -> #VALUE!
A11: =IF(#REF!<>"",1,0) -> #REF! | B11: =IF(#REF!="Concluído",1,"") -> #REF! | C11: =IFERROR(SUMIF(#REF!,"Em Medição",#REF!),"") | D11: =IFERROR(SUMIF(#REF!,"Não Medido",#REF!),"") | E11: =IFERROR(#REF!,"") | F11: =E11-SUM(C11:D11) -> #VALUE!
A12: =IF(#REF!<>"",1,0) -> #REF! | B12: =IF(#REF!="Concluído",1,"") -> #REF! | C12: =IFERROR(SUMIF(#REF!,"Em Medição",#REF!),"") | D12: =IFERROR(SUMIF(#REF!,"Não Medido",#REF!),"") | E12: =IFERROR(#REF!,"") | F12: =E12-SUM(C12:D12) -> #VALUE!
A13: =IF(#REF!<>"",1,0) -> #REF! | B13: =IF(#REF!="Concluído",1,"") -> #REF! | C13: =IFERROR(SUMIF(#REF!,"Em Medição",#REF!),"") | D13: =IFERROR(SUMIF(#REF!,"Não Medido",#REF!),"") | E13: =IFERROR(#REF!,"") | F13: =E13-SUM(C13:D13) -> #VALUE!
... A3982: =IF(#REF!<>"",1,0) -> #REF! | B3982: =IF(#REF!="Concluído",1,"") -> #REF! | C3982: =IFERROR(SUMIF(#REF!,"Em Medição",#REF!),"") | D3982: =IFERROR(SUMIF(#REF!,"Não Medido",#REF!),"") | E3982: =IFERROR(#REF!,"") | F3982: =E3982-SUM(C3982:D3982) -> #VALUE!

Sheet Tabela dinâmica 1

Sheet Equipes
A1: IdEquipe | B1: CodEquipe | C1: NomeEquipe | D1: Prestadora | E1: Classificacao | F1: Unidade | G1: DescEquipe | H1: Centro
A2: 1 | B2: XON-CE | C2: ALMOXARIFADO INTERNO (CEARÁ) | D2: ALARES | E2: ALMOXARIFADO | F2: CE | G2: =CONCATENATE(B2," - ",C2) -> XON-CE - ALMOXARIFADO INTERNO (CEARÁ) | H2: ALMOXARIFADO
A3: 3 | B3: XON-PB | C3: ALMOXARIFADO INTERNO (PARAÍBA) | D3: X-ON | E3: ALMOXARIFADO | F3: PB | G3: =CONCATENATE(B3," - ",C3) -> XON-PB - ALMOXARIFADO INTERNO (PARAÍBA) | H3: ALMOXARIFADO
A4: 4 | B4: XON-RN | C4: ALMOXARIFADO INTERNO (RIO GRANDE DO NORTE) | D4: X-ON | E4: ALMOXARIFADO | F4: RN | G4: =CONCATENATE(B4," - ",C4) -> XON-RN - ALMOXARIFADO INTERNO (RIO GRANDE DO NORTE) | H4: ALMOXARIFADO
A5: 5 | B5: XRN-03 | C5: ELY/ ANDERSON (84986690564) | D5: ALARES | E5: IMPLANTAÇÃO | F5: RN | G5: =CONCATENATE(B5," - ",C5) -> XRN-03 - ELY/ ANDERSON (84986690564) | H5: LANÇAMENTO
A6: 6 | B6: XCE-01 | C6: BATISTA E JAIR / (85991669867) | D6: ALARES | E6: IMPLANTAÇÃO | F6: CE | G6: =CONCATENATE(B6," - ",C6) -> XCE-01 - BATISTA E JAIR / (85991669867) | H6: LANÇAMENTO
A7: 7 | B7: XRN-02 | C7: ALDENIR (85991743369) | D7: ALARES | E7: IMPLANTAÇÃO | F7: RN | G7: =CONCATENATE(B7," - ",C7) -> XRN-02 - ALDENIR (85991743369) | H7: LANÇAMENTO
A8: 11 | B8: XCE-02 | C8: FRANCISCO JOSE/ FERNANDO (85988636495) | D8: ALARES | E8: IMPLANTAÇÃO | F8: CE | G8: =CONCATENATE(B8," - ",C8) -> XCE-02 - FRANCISCO JOSE/ FERNANDO (85988636495) | H8: LANÇAMENTO
A9: 15 | B9: XCE-13 | C9: JEFESSON FREITAS/ ANDERSON (85981351805) | D9: ALARES | E9: IMPLANTAÇÃO | F9: CE | G9: =CONCATENATE(B9," - ",C9) -> XCE-13 - JEFESSON FREITAS/ ANDERSON (85981351805) | H9: FUSÃO
A10: 17 | B10: XCE-04 | C10: JOAO VICTOR | D10: ALARES | E10: IMPLANTAÇÃO | F10: CE | G10: =CONCATENATE(B10," - ",C10) -> XCE-04 - JOAO VICTOR | H10: FUSÃO
A11: 21 | B11: XCE-05 | C11: LEONARDO FERREIRA/ VALMIR (85985946718) | D11: ALARES | E11: IMPLANTAÇÃO | F11: CE | G11: =CONCATENATE(B11," - ",C11) -> XCE-05 - LEONARDO FERREIRA/ VALMIR (85985946718) | H11: FUSÃO
A12: 45 | B12: XCE-12 | C12: JOÃO PAULO/ LUCAS (85989820412) | D12: ALARES | E12: IMPLANTAÇÃO | F12: CE | G12: =CONCATENATE(B12," - ",C12) -> XCE-12 - JOÃO PAULO/ LUCAS (85989820412) | H12: FUSÃO
A13: 55 | B13: XPB-01 | C13: PABLO OLIVEIRA E AGNO SERGIO | D13: X-ON | E13: MANUTENÇÃO | F13: PB | G13: =CONCATENATE(B13," - ",C13) -> XPB-01 - PABLO OLIVEIRA E AGNO SERGIO | H13: FUSÃO
... A18: 61 | B18: XPB-04 | C18: WELLINGTON BRONZEADO E ISAAC | D18: X-ON | E18: MANUTENÇÃO | F18: PB | G18: =CONCATENATE(B18," - ",C18) -> XPB-04 - WELLINGTON BRONZEADO E ISAAC | H18: FUSÃO
A19: 05dea2e6 | B19: XRN-01 | C19: PAULO ROBERTO (84996063007) | D19: ALARES | E19: IMPLANTAÇÃO | F19: RN | G19: =CONCATENATE(B19," - ",C19) -> XRN-01 - PAULO ROBERTO (84996063007) | H19: FUSÃO
A20: 53ef62a7 | B20: XCE-08 | C20: DANIEL MELO | D20: ALARES | E20: IMPLANTAÇÃO | F20: CE | G20: =CONCATENATE(B20," - ",C20) -> XCE-08 - DANIEL MELO | H20: IMPLANTAÇÃO , FUSÃO
A21: 5aac2867 | B21: XCE-10 | C21: EVANILDO/ DELANO (85991198015) | D21: ALARES | E21: IMPLANTAÇÃO | F21: CE | G21: =CONCATENATE(B21," - ",C21) -> XCE-10 - EVANILDO/ DELANO (85991198015) | H21: FUSÃO
A22: 60db2b1b | B22: XCE-09 | C22: ALEF/ CAIKY (85998135803) | D22: ALARES | E22: IMPLANTAÇÃO | F22: CE | G22: =CONCATENATE(B22," - ",C22) -> XCE-09 - ALEF/ CAIKY (85998135803) | H22: FUSÃO
A23: 69e850a9 | B23: XCE-11 | C23: FRANCISCO/ WILL (85991442161) | D23: ALARES | E23: IMPLANTAÇÃO | F23: CE | G23: =CONCATENATE(B23," - ",C23) -> XCE-11 - FRANCISCO/ WILL (85991442161) | H23: FUSÃO
A24: 9ab51889 | B24: XCE-07 | C24: JOAQUIM GOMES/ ODAIL (85996525161) | D24: ALARES | E24: IMPLANTAÇÃO | F24: CE | G24: =CONCATENATE(B24," - ",C24) -> XCE-07 - JOAQUIM GOMES/ ODAIL (85996525161) | H24: FUSÃO
A25: a7a1ffee | B25: ALARES | C25: ALARES | D25: ALARES | E25: IMPLANTAÇÃO | F25: CE | G25: =CONCATENATE(B25," - ",C25) -> ALARES - ALARES | H25: IMPLANTAÇÃO
A26: d975757f | B26: XCE-03 | C26: FERNANDO/ MAURÍCIO (85982026260) | D26: ALARES | E26: IMPLANTAÇÃO | F26: CE | G26: =CONCATENATE(B26," - ",C26) -> XCE-03 - FERNANDO/ MAURÍCIO (85982026260) | H26: LANÇAMENTO
A27: 872208aa | B27: XRN-04 | C27: HÉLDER (84998410790) | D27: ALARES | E27: Implantação | F27: RN | G27: =CONCATENATE(B27," - ",C27) -> XRN-04 - HÉLDER (84998410790) | H27: IMPLANTAÇÃO
A28: 0611f994 | B28: XPRN-01 | C28: DEDA (84991662573) | D28: ALARES | E28: LANÇAMENTO | F28: RN | G28: =CONCATENATE(B28," - ",C28) -> XPRN-01 - DEDA (84991662573) | H28: IMPLANTAÇÃO
A29: 2cc0d5b5 | B29: XCE-14 | C29: YURY NEUTON (85996923320) | D29: ALARES | E29: IMPLANTAÇÃO | F29: CE | G29: =CONCATENATE(B29," - ",C29) -> XCE-14 - YURY NEUTON (85996923320) | H29: IMPLANTAÇÃO
A30: 65605b36 | B30: XCE-15 | C30: AMARO INSTALAÇÕES (85981396733) | D30: ALARES | E30: INPLANTAÇÃO | F30: CE | G30: =CONCATENATE(B30," - ",C30) -> XCE-15 - AMARO INSTALAÇÕES (85981396733) | H30: IMPLANTAÇÃO
A31: edd7d94a | B31: XPB-07 | C31: CARLOS EDUARDO (88997640024) | D31: ALARES | E31: INPLANTAÇÃO | F31: PB | G31: =CONCATENATE(B31," - ",C31) -> XPB-07 - CARLOS EDUARDO (88997640024)
A32: 5d3ad8f5 | B32: XCE-16 | C32: FERNANDO SOUZA (85996616671) | D32: ALARES | E32: IMPLANTAÇÃO | F32: CE | G32: =CONCATENATE(B32," - ",C32) -> XCE-16 - FERNANDO SOUZA (85996616671) | H32: IMPLANTAÇÃO

Sheet Giro
A1: F | B1: NUM | C1: Calendário | D1: Produção DIA | E1: Produção ACUMULADA | F1: GIRO | G1: =SUM(D3:D45) -> 0
B2: 1 | C2: 44942 | D2: =COUNTIFS(Os!I:I,$C2,Os!M:M,"Concluído") -> 0 | E2: =D2 -> 0 | F2: =E2/B2 -> 0
B3: 2 | C3: 44943 | D3: =COUNTIFS(Os!I:I,$C3,Os!M:M,"Concluído") -> 0 | E3: =D3+E2 -> 0 | F3: =E3/B3 -> 0
B4: 3 | C4: 44944 | D4: =COUNTIFS(Os!I:I,$C4,Os!M:M,"Concluído") -> 0 | E4: =D4+E3 -> 0 | F4: =E4/B4 -> 0
B5: 4 | C5: =C4+1 -> 44945 | D5: =COUNTIFS(Os!I:I,$C5,Os!M:M,"Concluído") -> 0 | E5: =D5+E4 -> 0 | F5: =E5/B5 -> 0
B6: 5 | C6: =C5+1 -> 44946 | D6: =COUNTIFS(Os!I:I,$C6,Os!M:M,"Concluído") -> 0 | E6: =D6+E5 -> 0 | F6: =E6/B6 -> 0
B7: 6 | C7: =C6+1 -> 44947 | D7: =COUNTIFS(Os!I:I,$C7,Os!M:M,"Concluído") -> 0 | E7: =D7+E6 -> 0 | F7: =E7/B7 -> 0
B8: 7 | C8: =C7+1 -> 44948 | D8: =COUNTIFS(Os!I:I,$C8,Os!M:M,"Concluído") -> 0 | E8: =D8+E7 -> 0 | F8: =E8/B8 -> 0
B9: 8 | C9: =C8+1 -> 44949 | D9: =COUNTIFS(Os!I:I,$C9,Os!M:M,"Concluído") -> 0 | E9: =D9+E8 -> 0 | F9: =E9/B9 -> 0
B10: 9 | C10: =C9+1 -> 44950 | D10: =COUNTIFS(Os!I:I,$C10,Os!M:M,"Concluído") -> 0 | E10: =D10+E9 -> 0 | F10: =E10/B10 -> 0
B11: 10 | C11: =C10+1 -> 44951 | D11: =COUNTIFS(Os!I:I,$C11,Os!M:M,"Concluído") -> 0 | E11: =D11+E10 -> 0 | F11: =E11/B11 -> 0
B12: 11 | C12: =C11+1 -> 44952 | D12: =COUNTIFS(Os!I:I,$C12,Os!M:M,"Concluído") -> 0 | E12: =D12+E11 -> 0 | F12: =E12/B12 -> 0
B13: 12 | C13: =C12+1 -> 44953 | D13: =COUNTIFS(Os!I:I,$C13,Os!M:M,"Concluído") -> 0 | E13: =D13+E12 -> 0 | F13: =E13/B13 -> 0
B14: 13 | C14: =C13+1 -> 44954 | D14: =COUNTIFS(Os!I:I,$C14,Os!M:M,"Concluído") -> 0 | E14: =D14+E13 -> 0 | F14: =E14/B14 -> 0
B15: 14 | C15: =C14+1 -> 44955 | D15: =COUNTIFS(Os!I:I,$C15,Os!M:M,"Concluído") -> 0 | E15: =D15+E14 -> 0 | F15: =E15/B15 -> 0
B16: 15 | C16: =C15+1 -> 44956 | D16: =COUNTIFS(Os!I:I,$C16,Os!M:M,"Concluído") -> 0 | E16: =D16+E15 -> 0 | F16: =E16/B16 -> 0
B17: 16 | C17: =C16+1 -> 44957 | D17: =COUNTIFS(Os!I:I,$C17,Os!M:M,"Concluído") -> 0 | E17: =D17+E16 -> 0 | F17: =E17/B17 -> 0
A18: x | B18: 1 | C18: =C17+1 -> 44958 | D18: =COUNTIFS(Os!I:I,$C18,Os!M:M,"Concluído") -> 0 | E18: =D18 -> 0 | F18: =E18/B18 -> 0
A19: x | B19: =1+B18 -> 2 | C19: =C18+1 -> 44959 | D19: =COUNTIFS(Os!I:I,$C19,Os!M:M,"Concluído") -> 0 | E19: =D19+E18 -> 0 | F19: =E19/B19 -> 0
A20: x | B20: =1+B19 -> 3 | C20: =C19+1 -> 44960 | D20: =COUNTIFS(Os!I:I,$C20,Os!M:M,"Concluído") -> 0 | E20: =D20+E19 -> 0 | F20: =E20/B20 -> 0
A21: x | B21: =1+B20 -> 4 | C21: =C20+1 -> 44961 | D21: =COUNTIFS(Os!I:I,$C21,Os!M:M,"Concluído") -> 0 | E21: =D21+E20 -> 0 | F21: =E21/B21 -> 0
A22: x | B22: =1+B21 -> 5 | C22: =C21+1 -> 44962 | D22: =COUNTIFS(Os!I:I,$C22,Os!M:M,"Concluído") -> 0 | E22: =D22+E21 -> 0 | F22: =E22/B22 -> 0
A23: x | B23: =1+B22 -> 6 | C23: =C22+1 -> 44963 | D23: =COUNTIFS(Os!I:I,$C23,Os!M:M,"Concluído") -> 0 | E23: =D23+E22 -> 0 | F23: =E23/B23 -> 0
A24: x | B24: =1+B23 -> 7 | C24: =C23+1 -> 44964 | D24: =COUNTIFS(Os!I:I,$C24,Os!M:M,"Concluído") -> 0 | E24: =D24+E23 -> 0 | F24: =E24/B24 -> 0
A25: x | B25: =1+B24 -> 8 | C25: =C24+1 -> 44965 | D25: =COUNTIFS(Os!I:I,$C25,Os!M:M,"Concluído") -> 0 | E25: =D25+E24 -> 0 | F25: =E25/B25 -> 0
A26: x | B26: =1+B25 -> 9 | C26: =C25+1 -> 44966 | D26: =COUNTIFS(Os!I:I,$C26,Os!M:M,"Concluído") -> 0 | E26: =D26+E25 -> 0 | F26: =E26/B26 -> 0
A27: x | B27: =1+B26 -> 10 | C27: =C26+1 -> 44967 | D27: =COUNTIFS(Os!I:I,$C27,Os!M:M,"Concluído") -> 0 | E27: =D27+E26 -> 0 | F27: =E27/B27 -> 0
A28: x | B28: =1+B27 -> 11 | C28: =C27+1 -> 44968 | D28: =COUNTIFS(Os!I:I,$C28,Os!M:M,"Concluído") -> 0 | E28: =D28+E27 -> 0 | F28: =E28/B28 -> 0
A29: x | B29: =1+B28 -> 12 | C29: =C28+1 -> 44969 | D29: =COUNTIFS(Os!I:I,$C29,Os!M:M,"Concluído") -> 0 | E29: =D29+E28 -> 0 | F29: =E29/B29 -> 0
A30: x | B30: =1+B29 -> 13 | C30: =C29+1 -> 44970 | D30: =COUNTIFS(Os!I:I,$C30,Os!M:M,"Concluído") -> 0 | E30: =D30+E29 -> 0 | F30: =E30/B30 -> 0
... A305: x | B305: =1+B304 -> 288 | C305: =C304+1 -> 45245 | D305: =COUNTIFS(Os!I:I,$C305,Os!M:M,"Concluído") -> 0 | E305: =D305+E304 -> 0 | F305: =E305/B305 -> 0

Sheet Movimentacao
A1: IdMovimentacao | B1: Protocolo | C1: DtEmissao | D1: TpMov | E1: Motivo | F1: DescMotivo | G1: Almoxarifado | H1: DescAlmoxarifado | I1: AlmoxDestino | J1: DescAlmoxDest | K1: Obs | L1: GatilhoImpresso | M1: Centro | N1: CentroDestino
A2: 195c30d1 | B2: 595b307c | C2: 45308 | D2: ENTRADA | E2: MOT2 | F2: ENTRADA DO CLIENTE | G2: 33 | H2: R2O-CE-R2T - VIVO OBRAS DE IMPLANTAÇÃO (CEARÁ) | J2: - | K2: DOC. 3360-2024 - RECEBIDO EM 15/01/2024 | L2: 45340.702
A3: f0d1b48a | B3: 595b307c | C3: 45308 | D3: ENTRADA | E3: MOT2 | F3: ENTRADA DO CLIENTE | G3: 33 | H3: R2O-CE-R2T - VIVO OBRAS DE IMPLANTAÇÃO (CEARÁ) | J3: - | K3: DOC. 358203 - RECEBIDO EM 15/01/24
A4: 623a1962 | C4: 45308 | D4: TRANSFERENCIA | E4: MOT7 | F4: TRANSFERENCIA ENTRE ALMOXARIFADOS | G4: 33 | H4: R2O-CE-R2T - VIVO OBRAS DE IMPLANTAÇÃO (CEARÁ) | I4: 24 | J4: PCE-05-MARCELO GAGO | K4: INICIO OBRAS ARMARIO I13
A5: fe452c3e | B5: 595b307c | C5: 45308 | D5: ENTRADA | E5: MOT2 | F5: ENTRADA DO CLIENTE | G5: 33 | H5: R2O-CE-R2T - VIVO OBRAS DE IMPLANTAÇÃO (CEARÁ) | J5: - | K5: DOC. 3795-2024 - RECEBIDO EM 16/01/2024
A6: 5b80511b | B6: 595b307c | C6: 45308 | D6: ENTRADA | E6: MOT2 | F6: ENTRADA DO CLIENTE | G6: 33 | H6: R2O-CE-R2T - VIVO OBRAS DE IMPLANTAÇÃO (CEARÁ) | J6: - | K6: DOC. 4002-2024 - RECEBIDO EM 17/01/2024
A7: ccce9f84 | C7: 45308 | D7: INVENTÁRIO | E7: MOT1 | F7: INVENTÁRIO | G7: 33 | H7: R2O-CE-R2T - VIVO OBRAS DE IMPLANTAÇÃO (CEARÁ) | J7: - | K7: AJUSTE INICIAL - OBRAS VIVO
A8: 09a822b8 | C8: 45308 | D8: TRANSFERENCIA | E8: MOT7 | F8: TRANSFERENCIA ENTRE ALMOXARIFADOS | G8: 33 | H8: R2O-CE-R2T - VIVO OBRAS DE IMPLANTAÇÃO (CEARÁ) | I8: 25 | J8: XCE-05-MARCELO SANTOS / NUW5526 - (859) | K8: ARMARIO I13 - BARRAMENTOS 266,267,268,269,267,277,279,280
A9: 8d50b890 | C9: 45308 | D9: TRANSFERENCIA | E9: MOT7 | F9: TRANSFERENCIA ENTRE ALMOXARIFADOS | G9: 33 | H9: R2O-CE-R2T - VIVO OBRAS DE IMPLANTAÇÃO (CEARÁ) | I9: 5 | J9: PCE-01-AMARO
A10: 536df24d | C10: 45309 | D10: TRANSFERENCIA | E10: MOT7 | F10: TRANSFERENCIA ENTRE ALMOXARIFADOS | G10: 33 | H10: R2O-CE-R2T - VIVO OBRAS DE IMPLANTAÇÃO (CEARÁ) | I10: 40 | J10: PCE-07-MARCELO PANTOJA | K10: SP169 A SP223
A11: 26aad57e | C11: 45309 | D11: TRANSFERENCIA | E11: MOT7 | F11: TRANSFERENCIA ENTRE ALMOXARIFADOS | G11: 33 | H11: R2O-CE-R2T - VIVO OBRAS DE IMPLANTAÇÃO (CEARÁ) | I11: 23 | J11: PCE-02-LUIS
A12: 4cd3fe3b | B12: 595b307c | C12: 45310 | D12: ENTRADA | E12: MOT2 | F12: ENTRADA DO CLIENTE | G12: 33 | H12: R2O-CE-R2T - VIVO OBRAS DE IMPLANTAÇÃO (CEARÁ) | J12: - | K12: DOC. 4567-2024 - MATERIAL RECEBIDO EM 18/01/2024
A13: 989b52f9 | B13: 595b307c | C13: 45310 | D13: ENTRADA | E13: MOT2 | F13: ENTRADA DO CLIENTE | G13: 33 | H13: R2O-CE-R2T - VIVO OBRAS DE IMPLANTAÇÃO (CEARÁ) | J13: - | K13: DOC. 4622-2024 - RECEBIDO EM 19/01/2024
A14: 1b9c6998 | C14: 45310 | D14: TRANSFERENCIA | E14: MOT7 | F14: TRANSFERENCIA ENTRE ALMOXARIFADOS | G14: 33 | H14: R2O-CE-R2T - VIVO OBRAS DE IMPLANTAÇÃO (CEARÁ) | I14: 24 | J14: PCE-05-MARCELO GAGO | L14: 45340.703
A15: 0c5e16bf | C15: 45310 | D15: TRANSFERENCIA | E15: MOT7 | F15: TRANSFERENCIA ENTRE ALMOXARIFADOS | G15: 33 | H15: R2O-CE-R2T - VIVO OBRAS DE IMPLANTAÇÃO (CEARÁ) | I15: 6 | J15: XCE-01-BATISTA E JAIR / PNP4152 - (85991669867) | K15: PRIMEIRO E SEGUNDO LANÇAMENTO
A16: 2272be74 | C16: 45310 | D16: TRANSFERENCIA | E16: MOT7 | F16: TRANSFERENCIA ENTRE ALMOXARIFADOS | G16: 6 | H16: XCE-01-BATISTA E JAIR / PNP4152 - (85991669867) | I16: 33 | J16: R2O-CE-R2T - VIVO OBRAS DE IMPLANTAÇÃO (CEARÁ) | K16: SOBRA DE OBRA
A17: 11db8f01 | C17: 45310 | D17: TRANSFERENCIA | E17: MOT7 | F17: TRANSFERENCIA ENTRE ALMOXARIFADOS | G17: 33 | H17: R2O-CE-R2T - VIVO OBRAS DE IMPLANTAÇÃO (CEARÁ) | I17: 0fbffe93 | J17: XVL-CE-ALMOXARIFADO VOLANTE CEARÁ (MARCOS FERREIRA) | K17: MATERIAL RECOLHIDO POR DAVID.
A18: 77768c6a | C18: 45310 | D18: TRANSFERENCIA | E18: MOT7 | F18: TRANSFERENCIA ENTRE ALMOXARIFADOS | G18: 24 | H18: PCE-05-MARCELO GAGO | I18: 33 | J18: R2O-CE-R2T - VIVO OBRAS DE IMPLANTAÇÃO (CEARÁ) | K18: DEVOLUÇÃO DE SOBRA DE OBRA | L18: 45341.73
A19: fb2ef88f | B19: 595b307c | C19: 45310 | D19: ENTRADA | E19: MOT2 | F19: ENTRADA DO CLIENTE | G19: 33 | H19: R2O-CE-R2T - VIVO OBRAS DE IMPLANTAÇÃO (CEARÁ) | J19: - | K19: DOC. 4948-2024 - RECEBIDO EM 19/01/2024
A20: 2d6bf234 | B20: 595b307c | C20: 45310 | D20: SAIDA | E20: MOT5 | F20: BAIXA DE MATERIAL | G20: 25 | H20: XCE-05-MARCELO SANTOS / NUW5526 - (859) | J20: - | K20: APONTAMENTO DE 17/01
A21: 5f64c953 | C21: 45313 | D21: TRANSFERENCIA | E21: MOT7 | F21: TRANSFERENCIA ENTRE ALMOXARIFADOS | G21: 33 | H21: R2O-CE-R2T - VIVO OBRAS DE IMPLANTAÇÃO (CEARÁ) | I21: 0fbffe93 | J21: XVL-CE-ALMOXARIFADO VOLANTE CEARÁ (MARCOS FERREIRA) | K21: RETIRADO POR BATISTA EM 20/01/24
A22: 5e86f1cc | C22: 45313 | D22: TRANSFERENCIA | E22: MOT7 | F22: TRANSFERENCIA ENTRE ALMOXARIFADOS | G22: 33 | H22: R2O-CE-R2T - VIVO OBRAS DE IMPLANTAÇÃO (CEARÁ) | I22: 6 | J22: XCE-01-BATISTA E JAIR / PNP4152 - (85991669867) | K22: RETIRADO EM 20/01/24
A23: cd092685 | C23: 45313 | D23: TRANSFERENCIA | E23: MOT7 | F23: TRANSFERENCIA ENTRE ALMOXARIFADOS | G23: 33 | H23: R2O-CE-R2T - VIVO OBRAS DE IMPLANTAÇÃO (CEARÁ) | I23: 5 | J23: PCE-01-AMARO | K23: RETIRADO NA SEXTA FEIRA 19/01
A24: f9ad1434 | C24: 45313 | D24: INVENTÁRIO | E24: MOT1 | F24: INVENTÁRIO | G24: 29 | H24: R2M-CE-R2T - VIVO MANUTENÇÃO (CEARÁ) | J24: - | K24: AJUSTE INICIAL
A25: c883e13d | B25: 595b307c | C25: 45313 | D25: ENTRADA | E25: MOT2 | F25: ENTRADA DO CLIENTE | G25: 33 | H25: R2O-CE-R2T - VIVO OBRAS DE IMPLANTAÇÃO (CEARÁ) | J25: - | K25: DOC. 5276-2024
A26: 080c3b51 | B26: 595b307c | C26: 45313 | D26: ENTRADA | E26: MOT2 | F26: ENTRADA DO CLIENTE | G26: 33 | H26: R2O-CE-R2T - VIVO OBRAS DE IMPLANTAÇÃO (CEARÁ) | J26: - | K26: DOC. 5188-2024
A27: aa2e5c88 | C27: 45313 | D27: TRANSFERENCIA | E27: MOT7 | F27: TRANSFERENCIA ENTRE ALMOXARIFADOS | G27: 33 | H27: R2O-CE-R2T - VIVO OBRAS DE IMPLANTAÇÃO (CEARÁ) | I27: 23 | J27: PCE-02-LUIS | K27: ENTREGUE POR DANIEL EM 20/01/24
A28: b5a0f21b | C28: 45313 | D28: TRANSFERENCIA | E28: MOT7 | F28: TRANSFERENCIA ENTRE ALMOXARIFADOS | G28: 33 | H28: R2O-CE-R2T - VIVO OBRAS DE IMPLANTAÇÃO (CEARÁ) | I28: 25 | J28: XCE-05-MARCELO SANTOS / NUW5526 - (859) | K28: ENTREGUE POR DANIEL EM 20/01
A29: a5dde159 | C29: 45313 | D29: INVENTÁRIO | E29: MOT1 | F29: INVENTÁRIO | G29: 1 | H29: XON-CE-ALMOXARIFADO INTERNO (CEARÁ) | J29: - | K29: AJUSTE INICIAL DE FERRAMENTAL/EPI
A30: 108af592 | C30: 45313 | D30: TRANSFERENCIA | E30: MOT7 | F30: TRANSFERENCIA ENTRE ALMOXARIFADOS | G30: 1 | H30: XON-CE-ALMOXARIFADO INTERNO (CEARÁ) | I30: 27 | J30: XCE-11-OLAVO / HVW8D52 - (85987392872) | K30: ENTREGUE POR JAMES EM 10/01/2024 - SMARTPHONE COM CARREGADOR E PELICULA E CAPA
A31: fd75ba93 | B31: 595b307c | C31: 45313 | D31: SAIDA | E31: MOT5 | F31: BAIXA DE MATERIAL | G31: 25 | H31: XCE-05-MARCELO SANTOS / NUW5526 - (859) | J31: - | K31: APONTAMENTO EM 18/01/24
A32: 65c73212 | B32: 595b307c | C32: 45313 | D32: SAIDA | E32: MOT5 | F32: BAIXA DE MATERIAL | G32: 25 | H32: XCE-05-MARCELO SANTOS / NUW5526 - (859) | J32: - | K32: REFERENTE AO DIA 19/01/24
A33: 9926a0e4 | B33: 595b307c | C33: 45313 | D33: SAIDA | E33: MOT5 | F33: BAIXA DE MATERIAL | G33: 6 | H33: XCE-01-BATISTA E JAIR / PNP4152 - (85991669867) | J33: - | K33: REFERENTE A APONTAMENTO DO DIA 19/01/24
A34: 7fa3459b | B34: 595b307c | C34: 45313 | D34: SAIDA | E34: MOT5 | F34: BAIXA DE MATERIAL | G34: 25 | H34: XCE-05-MARCELO SANTOS / NUW5526 - (859) | J34: - | K34: REFERENTE A APONTAMENTO DE 20/01/24
A35: 01ecedef | C35: 45314 | D35: TRANSFERENCIA | E35: MOT7 | F35: TRANSFERENCIA ENTRE ALMOXARIFADOS | G35: 33 | H35: R2O-CE-R2T - VIVO OBRAS DE IMPLANTAÇÃO (CEARÁ) | I35: 0fbffe93 | J35: XVL-CE-ALMOXARIFADO VOLANTE CEARÁ (MARCOS FERREIRA) | K35: RETIRADO POR BATISTA
A36: 64b3104b | C36: 45314 | D36: TRANSFERENCIA | E36: MOT7 | F36: TRANSFERENCIA ENTRE ALMOXARIFADOS | G36: 33 | H36: R2O-CE-R2T - VIVO OBRAS DE IMPLANTAÇÃO (CEARÁ) | I36: 27 | J36: XCE-11-OLAVO / HVW8D52 - (85987392872) | K36: RETIRADO EM 19/01/2024
A37: 88354109 | C37: 45314 | D37: TRANSFERENCIA | E37: MOT7 | F37: TRANSFERENCIA ENTRE ALMOXARIFADOS | G37: 33 | H37: R2O-CE-R2T - VIVO OBRAS DE IMPLANTAÇÃO (CEARÁ) | I37: 21 | J37: XCE-10-LEONARDO / PCF4G19 - (859) | K37: RETIRADO EM 19/01/2024
A38: f5d8e702 | C38: 45314 | D38: TRANSFERENCIA | E38: MOT7 | F38: TRANSFERENCIA ENTRE ALMOXARIFADOS | G38: 33 | H38: R2O-CE-R2T - VIVO OBRAS DE IMPLANTAÇÃO (CEARÁ) | I38: 27 | J38: XCE-11-OLAVO / HVW8D52 - (85987392872)
A39: e0466798 | B39: 595b307c | C39: 45314 | D39: SAIDA | E39: MOT5 | F39: BAIXA DE MATERIAL | G39: 6 | H39: XCE-01-BATISTA E JAIR / PNP4152 - (85991669867) | J39: - | K39: REFERENTE A 20/01/2024
A40: c91715e8 | B40: 595b307c | C40: 45314 | D40: SAIDA | E40: MOT5 | F40: BAIXA DE MATERIAL | G40: 25 | H40: XCE-05-MARCELO SANTOS / NUW5526 - (859) | J40: - | K40: REFERENTE A 22/01/2024
A41: e9934904 | B41: 595b307c | C41: 45314 | D41: SAIDA | E41: MOT5 | F41: BAIXA DE MATERIAL | G41: 5 | H41: PCE-01-AMARO | J41: - | K41: REFERENTE A 18/01 E 19/01
A42: d3c88df8 | B42: 595b307c | C42: 45314 | D42: SAIDA | E42: MOT5 | F42: BAIXA DE MATERIAL | G42: 5 | H42: PCE-01-AMARO | J42: - | K42: REFERENTE A 20/01
A43: 1a3fb0b0 | B43: 595b307c | C43: 45314 | D43: SAIDA | E43: MOT5 | F43: BAIXA DE MATERIAL | G43: 5 | H43: PCE-01-AMARO | J43: - | K43: REFERENTE A 22/01
A44: 973a6884 | B44: 595b307c | C44: 45314 | D44: SAIDA | E44: MOT5 | F44: BAIXA DE MATERIAL | G44: 23 | H44: PCE-02-LUIS | J44: - | K44: REFERENTE A 18/01
A45: 3af5c809 | B45: 595b307c | C45: 45314 | D45: SAIDA | E45: MOT5 | F45: BAIXA DE MATERIAL | G45: 23 | H45: PCE-02-LUIS | J45: - | K45: REFERENTE AO DIA 19/01/2024
A46: 62e3525b | B46: 595b307c | C46: 45314 | D46: SAIDA | E46: MOT5 | F46: BAIXA DE MATERIAL | G46: 23 | H46: PCE-02-LUIS | J46: - | K46: REFERENTE AO DIA 22/01/2024
A47: bc4bdd6a | B47: 595b307c | C47: 45314 | D47: SAIDA | E47: MOT5 | F47: BAIXA DE MATERIAL | G47: 25 | H47: XCE-05-MARCELO SANTOS / NUW5526 - (859) | J47: -
A48: ae430618 | B48: 595b307c | C48: 45314 | D48: SAIDA | E48: MOT5 | F48: BAIXA DE MATERIAL | G48: 6 | H48: XCE-01-BATISTA E JAIR / PNP4152 - (85991669867) | J48: -
A49: e2e15208 | C49: 45314 | D49: TRANSFERENCIA | E49: MOT7 | F49: TRANSFERENCIA ENTRE ALMOXARIFADOS | G49: 33 | H49: R2O-CE-R2T - VIVO OBRAS DE IMPLANTAÇÃO (CEARÁ) | I49: 25 | J49: XCE-05-MARCELO SANTOS / NUW5526 - (859)
A50: b7610c01 | C50: 45314 | D50: TRANSFERENCIA | E50: MOT7 | F50: TRANSFERENCIA ENTRE ALMOXARIFADOS | G50: 33 | H50: R2O-CE-R2T - VIVO OBRAS DE IMPLANTAÇÃO (CEARÁ) | I50: 39 | J50: XCE-06-YURY NEWTON / RIL5E31 - (85996244978)
A51: bdd3ff2c | C51: 45314 | D51: TRANSFERENCIA | E51: MOT7 | F51: TRANSFERENCIA ENTRE ALMOXARIFADOS | G51: 0fbffe93 | H51: XVL-CE-ALMOXARIFADO VOLANTE CEARÁ (MARCOS FERREIRA) | I51: 5 | J51: PCE-01-AMARO | K51: ENTREGUE EM CAMPO
A52: 3b35f0ab | C52: 45314 | D52: TRANSFERENCIA | E52: MOT7 | F52: TRANSFERENCIA ENTRE ALMOXARIFADOS | G52: 0fbffe93 | H52: XVL-CE-ALMOXARIFADO VOLANTE CEARÁ (MARCOS FERREIRA) | I52: 23 | J52: PCE-02-LUIS | K52: ENTREGUE EM CAMPO
A53: ce829383 | C53: 45314 | D53: TRANSFERENCIA | E53: MOT7 | F53: TRANSFERENCIA ENTRE ALMOXARIFADOS | G53: 0fbffe93 | H53: XVL-CE-ALMOXARIFADO VOLANTE CEARÁ (MARCOS FERREIRA) | I53: 40 | J53: PCE-07-MARCELO PANTOJA | K53: ENTREGUE EM CAMPO
A54: d43b45f3 | C54: 45314 | D54: TRANSFERENCIA | E54: MOT7 | F54: TRANSFERENCIA ENTRE ALMOXARIFADOS | G54: 0fbffe93 | H54: XVL-CE-ALMOXARIFADO VOLANTE CEARÁ (MARCOS FERREIRA) | I54: 33 | J54: R2O-CE-R2T - VIVO OBRAS DE IMPLANTAÇÃO (CEARÁ) | K54: DEVOLVIDO POR DAVID
A55: 9133397f | C55: 45314 | D55: SAIDA | E55: MOT5 | F55: BAIXA DE MATERIAL | G55: 24 | H55: PCE-05-MARCELO GAGO | J55: -
A56: e5bf88c2 | B56: 595b307c | C56: 45315 | D56: ENTRADA | E56: MOT2 | F56: ENTRADA DO CLIENTE | G56: 33 | H56: R2O-CE-R2T - VIVO OBRAS DE IMPLANTAÇÃO (CEARÁ) | J56: -
A57: 399744df | C57: 45315 | D57: TRANSFERENCIA | E57: MOT7 | F57: TRANSFERENCIA ENTRE ALMOXARIFADOS | G57: 33 | H57: R2O-CE-R2T - VIVO OBRAS DE IMPLANTAÇÃO (CEARÁ) | I57: 6 | J57: XCE-01-BATISTA E JAIR / PNP4152 - (85991669867)
A58: c1cb61dc | C58: 45315 | D58: TRANSFERENCIA | E58: MOT7 | F58: TRANSFERENCIA ENTRE ALMOXARIFADOS | G58: 33 | H58: R2O-CE-R2T - VIVO OBRAS DE IMPLANTAÇÃO (CEARÁ) | I58: 28 | J58: PCE-04-PAULO PC
A59: f3b94af3 | C59: 45315 | D59: TRANSFERENCIA | E59: MOT7 | F59: TRANSFERENCIA ENTRE ALMOXARIFADOS | G59: 33 | H59: R2O-CE-R2T - VIVO OBRAS DE IMPLANTAÇÃO (CEARÁ) | I59: 5 | J59: PCE-01-AMARO
A60: 3b86b671 | C60: 45315 | D60: TRANSFERENCIA | E60: MOT7 | F60: TRANSFERENCIA ENTRE ALMOXARIFADOS | G60: 33 | H60: R2O-CE-R2T - VIVO OBRAS DE IMPLANTAÇÃO (CEARÁ) | I60: 23 | J60: PCE-02-LUIS
A61: 55d351aa | C61: 45315 | D61: TRANSFERENCIA | E61: MOT7 | F61: TRANSFERENCIA ENTRE ALMOXARIFADOS | G61: 40 | H61: PCE-07-MARCELO PANTOJA | I61: 33 | J61: R2O-CE-R2T - VIVO OBRAS DE IMPLANTAÇÃO (CEARÁ) | K61: TROCA
A62: c2776df4 | C62: 45315 | D62: TRANSFERENCIA | E62: MOT7 | F62: TRANSFERENCIA ENTRE ALMOXARIFADOS | G62: 33 | H62: R2O-CE-R2T - VIVO OBRAS DE IMPLANTAÇÃO (CEARÁ) | I62: 40 | J62: PCE-07-MARCELO PANTOJA | K62: TROCA
A63: c3422185 | C63: 45315 | D63: TRANSFERENCIA | E63: MOT7 | F63: TRANSFERENCIA ENTRE ALMOXARIFADOS | G63: 33 | H63: R2O-CE-R2T - VIVO OBRAS DE IMPLANTAÇÃO (CEARÁ) | I63: 25 | J63: XCE-05-MARCELO SANTOS / NUW5526 - (859) | K63: TROCA
A64: 158f3575 | C64: 45315 | D64: TRANSFERENCIA | E64: MOT7 | F64: TRANSFERENCIA ENTRE ALMOXARIFADOS | G64: 25 | H64: XCE-05-MARCELO SANTOS / NUW5526 - (859) | I64: 33 | J64: R2O-CE-R2T - VIVO OBRAS DE IMPLANTAÇÃO (CEARÁ) | K64: TROCA
A65: da840bf3 | B65: 595b307c | C65: 45315 | D65: SAIDA | E65: MOT5 | F65: BAIXA DE MATERIAL | G65: 6 | H65: XCE-01-BATISTA E JAIR / PNP4152 - (85991669867) | J65: -
A66: bd9fdfb8 | B66: 595b307c | C66: 45315 | D66: SAIDA | E66: MOT5 | F66: BAIXA DE MATERIAL | G66: 27 | H66: XCE-11-OLAVO / HVW8D52 - (85987392872) | J66: - | K66: RETROATIVO
A67: 14d26fe0 | C67: 45315 | D67: TRANSFERENCIA | E67: MOT7 | F67: TRANSFERENCIA ENTRE ALMOXARIFADOS | G67: 0fbffe93 | H67: XVL-CE-ALMOXARIFADO VOLANTE CEARÁ (MARCOS FERREIRA) | I67: 27 | J67: XCE-11-OLAVO / HVW8D52 - (85987392872)
A68: 5fa9ed78 | B68: 595b307c | C68: 45315 | D68: SAIDA | E68: MOT5 | F68: BAIXA DE MATERIAL | G68: 21 | H68: XCE-10-LEONARDO / PCF4G19 - (859) | J68: -
A69: 5797fb2d | B69: 595b307c | C69: 45315 | D69: SAIDA | E69: MOT5 | F69: BAIXA DE MATERIAL | G69: 25 | H69: XCE-05-MARCELO SANTOS / NUW5526 - (859) | J69: - | K69: REFERENTE A 23/01/2024
A70: 286149f6 | C70: 45315 | D70: TRANSFERENCIA | E70: MOT7 | F70: TRANSFERENCIA ENTRE ALMOXARIFADOS | G70: 0fbffe93 | H70: XVL-CE-ALMOXARIFADO VOLANTE CEARÁ (MARCOS FERREIRA) | I70: 6 | J70: XCE-01-BATISTA E JAIR / PNP4152 - (85991669867)
A71: 32d0293f | B71: 595b307c | C71: 45315 | D71: SAIDA | E71: MOT5 | F71: BAIXA DE MATERIAL | G71: 6 | H71: XCE-01-BATISTA E JAIR / PNP4152 - (85991669867) | J71: -
A72: 4830b17f | B72: 595b307c | C72: 45315 | D72: SAIDA | E72: MOT5 | F72: BAIXA DE MATERIAL | G72: 25 | H72: XCE-05-MARCELO SANTOS / NUW5526 - (859) | J72: -
A73: 138bd882 | C73: 45316 | D73: TRANSFERENCIA | E73: MOT7 | F73: TRANSFERENCIA ENTRE ALMOXARIFADOS | G73: 33 | H73: R2O-CE-R2T - VIVO OBRAS DE IMPLANTAÇÃO (CEARÁ) | I73: 21 | J73: XCE-10-LEONARDO / PCF4G19 - (859)
A74: 57b85efd | B74: 595b307c | C74: 45316 | D74: SAIDA | E74: MOT5 | F74: BAIXA DE MATERIAL | G74: 5 | H74: PCE-01-AMARO | J74: - | K74: Referente a 23/01/2024
A75: c86d3093 | B75: 595b307c | C75: 45316 | D75: SAIDA | E75: MOT5 | F75: BAIXA DE MATERIAL | G75: 5 | H75: PCE-01-AMARO | J75: - | K75: Referente a 24/01/2024
A76: 8499673b | B76: 595b307c | C76: 45316 | D76: SAIDA | E76: MOT5 | F76: BAIXA DE MATERIAL | G76: 27 | H76: XCE-11-OLAVO / HVW8D52 - (85987392872) | J76: -
A77: c8b9f664 | B77: 595b307c | C77: 45316 | D77: SAIDA | E77: MOT5 | F77: BAIXA DE MATERIAL | G77: 6 | H77: XCE-01-BATISTA E JAIR / PNP4152 - (85991669867) | J77: -
A78: 6eed46f6 | C78: 45316 | D78: TRANSFERENCIA | E78: MOT7 | F78: TRANSFERENCIA ENTRE ALMOXARIFADOS | G78: 33 | H78: R2O-CE-R2T - VIVO OBRAS DE IMPLANTAÇÃO (CEARÁ) | I78: 5 | J78: PCE-01-AMARO | K78: Trâmite feito em campo por Marquinhos e Marcelo
A79: 27cf66d2 | C79: 45317 | D79: TRANSFERENCIA | E79: MOT7 | F79: TRANSFERENCIA ENTRE ALMOXARIFADOS | G79: 33 | H79: R2O-CE-R2T - VIVO OBRAS DE IMPLANTAÇÃO (CEARÁ) | I79: 6 | J79: XCE-01-BATISTA E JAIR / PNP4152 - (85991669867) | K79: RETIRADO POR FRANCISCO JOSÉ
A80: 3eea65c2 | C80: 45317 | D80: TRANSFERENCIA | E80: MOT7 | F80: TRANSFERENCIA ENTRE ALMOXARIFADOS | G80: 33 | H80: R2O-CE-R2T - VIVO OBRAS DE IMPLANTAÇÃO (CEARÁ) | I80: 28 | J80: PCE-04-PAULO PC
A81: ad303693 | C81: 45317 | D81: TRANSFERENCIA | E81: MOT7 | F81: TRANSFERENCIA ENTRE ALMOXARIFADOS | G81: 24 | H81: PCE-05-MARCELO GAGO | I81: 33 | J81: R2O-CE-R2T - VIVO OBRAS DE IMPLANTAÇÃO (CEARÁ) | K81: DEVOLVIDO EM 24/01/2024
A82: 3d4f8fbd | B82: 595b307c | C82: 45317 | D82: SAIDA | E82: MOT5 | F82: BAIXA DE MATERIAL | G82: 5 | H82: PCE-01-AMARO | J82: - | K82: REFERENTE A 25/01/2024
A83: edb98a09 | C83: 45317 | D83: TRANSFERENCIA | E83: MOT7 | F83: TRANSFERENCIA ENTRE ALMOXARIFADOS | G83: 33 | H83: R2O-CE-R2T - VIVO OBRAS DE IMPLANTAÇÃO (CEARÁ) | I83: 40 | J83: PCE-07-MARCELO PANTOJA
A84: 65ee00c7 | B84: 595b307c | C84: 45317 | D84: SAIDA | E84: MOT5 | F84: BAIXA DE MATERIAL | G84: 6 | H84: XCE-01-BATISTA E JAIR / PNP4152 - (85991669867) | J84: - | K84: 25/01/2024
A85: 882b102b | B85: 595b307c | C85: 45317 | D85: SAIDA | E85: MOT5 | F85: BAIXA DE MATERIAL | G85: 21 | H85: XCE-10-LEONARDO / PCF4G19 - (859) | J85: - | K85: 24/01/2024
A86: 129acd64 | B86: 595b307c | C86: 45317 | D86: SAIDA | E86: MOT5 | F86: BAIXA DE MATERIAL | G86: 27 | H86: XCE-11-OLAVO / HVW8D52 - (85987392872) | J86: - | K86: 24/01/2024
A87: cfbd5490 | B87: 595b307c | C87: 45317 | D87: SAIDA | E87: MOT5 | F87: BAIXA DE MATERIAL | G87: 6 | H87: XCE-01-BATISTA E JAIR / PNP4152 - (85991669867) | J87: - | K87: 24/01/2024
A88: 03663ca0 | B88: 595b307c | C88: 45317 | D88: SAIDA | E88: MOT5 | F88: BAIXA DE MATERIAL | G88: 25 | H88: XCE-05-MARCELO SANTOS / NUW5526 - (859) | J88: - | K88: 24/01/2024
A89: ae725555 | B89: 595b307c | C89: 45317 | D89: SAIDA | E89: MOT5 | F89: BAIXA DE MATERIAL | G89: 6 | H89: XCE-01-BATISTA E JAIR / PNP4152 - (85991669867) | J89: -
A90: 571fac78 | B90: 595b307c | C90: 45317 | D90: SAIDA | E90: MOT5 | F90: BAIXA DE MATERIAL | G90: 27 | H90: XCE-11-OLAVO / HVW8D52 - (85987392872) | J90: -
A91: 83b3bdec | B91: 595b307c | C91: 45317 | D91: SAIDA | E91: MOT5 | F91: BAIXA DE MATERIAL | G91: 25 | H91: XCE-05-MARCELO SANTOS / NUW5526 - (859) | J91: -
A92: b893da6a | C92: 45320 | D92: TRANSFERENCIA | E92: MOT7 | F92: TRANSFERENCIA ENTRE ALMOXARIFADOS | G92: 33 | H92: R2O-CE-R2T - VIVO OBRAS DE IMPLANTAÇÃO (CEARÁ) | I92: 22 | J92: XCE-09-LEVI E ALISSON / OSV9C43 - (85991749281) | K92: RETIRADO POR JEFFESON
A93: ddc6061e | C93: 45320 | D93: TRANSFERENCIA | E93: MOT7 | F93: TRANSFERENCIA ENTRE ALMOXARIFADOS | G93: 33 | H93: R2O-CE-R2T - VIVO OBRAS DE IMPLANTAÇÃO (CEARÁ) | I93: 15 | J93: XCE-13-JEFESSON FREITAS / HQE0062 - (859) | K93: RETIRADO NO SABADO 27/01/2024
A94: d20bdf7b | B94: 595b307c | C94: 45320 | D94: ENTRADA | E94: MOT2 | F94: ENTRADA DO CLIENTE | G94: 33 | H94: R2O-CE-R2T - VIVO OBRAS DE IMPLANTAÇÃO (CEARÁ) | J94: - | K94: DOC. 6311-2024
A95: ad4c04b1 | B95: 595b307c | C95: 45320 | D95: SAIDA | E95: MOT5 | F95: BAIXA DE MATERIAL | G95: 5 | H95: PCE-01-AMARO | J95: - | K95: REFERENTE AOS DIAS 26, 27 E 29/01/2024
A96: 34f8e7fc | C96: 45320 | D96: TRANSFERENCIA | E96: MOT7 | F96: TRANSFERENCIA ENTRE ALMOXARIFADOS | G96: 33 | H96: R2O-CE-R2T - VIVO OBRAS DE IMPLANTAÇÃO (CEARÁ) | I96: 5 | J96: PCE-01-AMARO
A97: 833763f9 | C97: 45321 | D97: TRANSFERENCIA | E97: MOT7 | F97: TRANSFERENCIA ENTRE ALMOXARIFADOS | G97: 33 | H97: R2O-CE-R2T - VIVO OBRAS DE IMPLANTAÇÃO (CEARÁ) | I97: 23 | J97: PCE-02-LUIS
A98: 2c7809b0 | B98: 595b307c | C98: 45321 | D98: SAIDA | E98: MOT5 | F98: BAIXA DE MATERIAL | G98: 23 | H98: PCE-02-LUIS | J98: - | K98: REFERENTE A 25/01/2024
A99: 5e76c557 | B99: 595b307c | C99: 45321 | D99: SAIDA | E99: MOT5 | F99: BAIXA DE MATERIAL | G99: 23 | H99: PCE-02-LUIS | J99: - | K99: REFERENTE A 26/01/2024
A100: 8763d036 | B100: 595b307c | C100: 45321 | D100: SAIDA | E100: MOT5 | F100: BAIXA DE MATERIAL | G100: 23 | H100: PCE-02-LUIS | J100: - | K100: REFERENTE A 27/01/2024
...

Sheet ItensMovimentacao
A1: IdItensMovimentacao | B1: Movimentacao | C1: Protocolo | D1: TpMov | E1: DtEmissao | F1: Material | G1: DescMaterial | H1: Qtd | I1: Almoxarifado | J1: DescAlmoxarifado | K1: Motivo | L1: DescMotivo | M1: Obs | N1: Registro | O1: Centro
A2: 6023964e | B2: 195c30d1 | C2: 595b307c | D2: ENTRADA | E2: 45308 | F2: MAT05 | G2: R2005 - ALÇA PREF P/ CFOA SM AS 80 DE 144 FO TS (0256-0245-7) | H2: 42 | I2: 33 | J2: R2O-CE-R2T - VIVO OBRAS DE IMPLANTAÇÃO (CEARÁ) | K2: MOT2 | L2: ENTRADA DO CLIENTE | M2: DOC. 3360-2024 - RECEBIDO EM 15/01/2024 | O2: IMPLANTAÇÃO
A3: b7a0c16a | B3: 195c30d1 | C3: 595b307c | D3: ENTRADA | E3: 45308 | F3: MAT22 | G3: R2022 - CONJUNTO EMENDA ÓPTICA MEC AER SUBT - 48 FO 4ENT (0456-0169-9) | H3: 81 | I3: 33 | J3: R2O-CE-R2T - VIVO OBRAS DE IMPLANTAÇÃO (CEARÁ) | K3: MOT2 | L3: ENTRADA DO CLIENTE | M3: DOC. 3360-2024 - RECEBIDO EM 15/01/2024 | O3: IMPLANTAÇÃO
A4: e7a529b9 | B4: 195c30d1 | C4: 595b307c | D4: ENTRADA | E4: 45308 | F4: MAT34 | G4: R2034 - DROP OPT PREC 2PTAS FIG8 UNI 150M PRET (0380-9264-4) | H4: 128 | I4: 33 | J4: R2O-CE-R2T - VIVO OBRAS DE IMPLANTAÇÃO (CEARÁ) | K4: MOT2 | L4: ENTRADA DO CLIENTE | M4: DOC. 3360-2024 - RECEBIDO EM 15/01/2024 | O4: IMPLANTAÇÃO
A5: 6cc83a53 | B5: 195c30d1 | C5: 595b307c | D5: ENTRADA | E5: 45308 | F5: MAT35 | G5: R2035 - DROP OPT PREC 2PTAS FIG8 UNI 200M PRET (0380-9265-5) | H5: 48 | I5: 33 | J5: R2O-CE-R2T - VIVO OBRAS DE IMPLANTAÇÃO (CEARÁ) | K5: MOT2 | L5: ENTRADA DO CLIENTE | M5: DOC. 3360-2024 - RECEBIDO EM 15/01/2024 | O5: IMPLANTAÇÃO
A6: 5eaf5e52 | B6: 195c30d1 | C6: 595b307c | D6: ENTRADA | E6: 45308 | F6: MAT36 | G6: R2036 - DROP OPT PREC 2PTAS FIG8 UNI 300M PRET (0380-9266-6) | H6: 17 | I6: 33 | J6: R2O-CE-R2T - VIVO OBRAS DE IMPLANTAÇÃO (CEARÁ) | K6: MOT2 | L6: ENTRADA DO CLIENTE | M6: DOC. 3360-2024 - RECEBIDO EM 15/01/2024 | O6: IMPLANTAÇÃO
A7: 19fa6f08 | B7: 195c30d1 | C7: 595b307c | D7: ENTRADA | E7: 45308 | F7: MAT37 | G7: R2037 - DROP OPT PREC 2PTAS FIG8 UNI 400M PRET (0380-9267-7) | H7: 6 | I7: 33 | J7: R2O-CE-R2T - VIVO OBRAS DE IMPLANTAÇÃO (CEARÁ) | K7: MOT2 | L7: ENTRADA DO CLIENTE | M7: DOC. 3360-2024 - RECEBIDO EM 15/01/2024 | O7: IMPLANTAÇÃO
A8: e143a647 | B8: 195c30d1 | C8: 595b307c | D8: ENTRADA | E8: 45308 | F8: MAT41 | G8: R2041 - FIO DE ESPINAR DIELETRICO - VIVO (0380-9203-3) | H8: 25 | I8: 33 | J8: R2O-CE-R2T - VIVO OBRAS DE IMPLANTAÇÃO (CEARÁ) | K8: MOT2 | L8: ENTRADA DO CLIENTE | M8: DOC. 3360-2024 - RECEBIDO EM 15/01/2024 | O8: IMPLANTAÇÃO
A9: 11fe7b1b | B9: 195c30d1 | C9: 595b307c | D9: ENTRADA | E9: 45308 | F9: cc64c0c4 | G9: R2064 - LAÇO PREF P/ CFOA SM AS80 144F 0456-0162-2 | H9: 21 | I9: 33 | J9: R2O-CE-R2T - VIVO OBRAS DE IMPLANTAÇÃO (CEARÁ) | K9: MOT2 | L9: ENTRADA DO CLIENTE | M9: DOC. 3360-2024 - RECEBIDO EM 15/01/2024 | O9: IMPLANTAÇÃO
A10: dc86b2b1 | B10: 195c30d1 | C10: 595b307c | D10: ENTRADA | E10: 45308 | F10: MAT45 | G10: R2045 - LAÇO PREF P/ CFOA SM AS 80 18 A 36 FO (0456-0160-0) | H10: 106 | I10: 33 | J10: R2O-CE-R2T - VIVO OBRAS DE IMPLANTAÇÃO (CEARÁ) | K10: MOT2 | L10: ENTRADA DO CLIENTE | M10: DOC. 3360-2024 - RECEBIDO EM 15/01/2024 | O10: IMPLANTAÇÃO
A11: b164a6e1 | B11: 195c30d1 | C11: 595b307c | D11: ENTRADA | E11: 45308 | F11: MAT50 | G11: R2050 - MINI-CEO TERMOC 16ENT AEREO E SUBT 144FO (0456-0170-0) | H11: 9 | I11: 33 | J11: R2O-CE-R2T - VIVO OBRAS DE IMPLANTAÇÃO (CEARÁ) | K11: MOT2 | L11: ENTRADA DO CLIENTE | M11: DOC. 3360-2024 - RECEBIDO EM 15/01/2024 | O11: IMPLANTAÇÃO
A12: 54eb590c | B12: 195c30d1 | C12: 595b307c | D12: ENTRADA | E12: 45308 | F12: MAT51 | G12: R2051 - SUP ANCORAGE CABO OPT AS E CORD DIELETR (SUPA - SCO) (0456-0157-7) | H12: 215 | I12: 33 | J12: R2O-CE-R2T - VIVO OBRAS DE IMPLANTAÇÃO (CEARÁ) | K12: MOT2 | L12: ENTRADA DO CLIENTE | M12: DOC. 3360-2024 - RECEBIDO EM 15/01/2024 | O12: IMPLANTAÇÃO
A13: f142036b | B13: 195c30d1 | C13: 595b307c | D13: ENTRADA | E13: 45308 | F13: MAT52 | G13: R2052 - SUP PASSAGEM CABO OPT AS E CORD DIELETR (SUPA - SCO) (0456-0158-8) | H13: 215 | I13: 33 | J13: R2O-CE-R2T - VIVO OBRAS DE IMPLANTAÇÃO (CEARÁ) | K13: MOT2 | L13: ENTRADA DO CLIENTE | M13: DOC. 3360-2024 - RECEBIDO EM 15/01/2024 | O13: IMPLANTAÇÃO
... A24: d5593df1 | B24: f0d1b48a | C24: 595b307c | D24: ENTRADA | E24: 45308 | F24: MAT04 | G24: R2004 - ALÇA PLASTICA 5MM C/ GANCHO METALICO (0380-9242-2) | H24: 800 | I24: 33 | J24: R2O-CE-R2T - VIVO OBRAS DE IMPLANTAÇÃO (CEARÁ) | K24: MOT2 | L24: ENTRADA DO CLIENTE | M24: DOC. 358203 - RECEBIDO EM 15/01/24 | O24: IMPLANTAÇÃO
A25: 3d83517e | B25: 623a1962 | D25: TRANSFERENCIA | E25: 45308 | F25: MAT05 | G25: R2005 - ALÇA PREF P/ CFOA SM AS 80 DE 144 FO TS (0256-0245-7) | H25: -20 | I25: 33 | J25: R2O-CE-R2T - VIVO OBRAS DE IMPLANTAÇÃO (CEARÁ) | K25: MOT7 | L25: TRANSFERENCIA ENTRE ALMOXARIFADOS | M25: INICIO OBRAS ARMARIO I13 | O25: IMPLANTAÇÃO
A26: 550bf2d2 | B26: 623a1962 | D26: TRANSFERENCIA | E26: 45308 | F26: MAT63 | G26: R2063 - PLAQUETA VIVO (MIL035) | H26: -100 | I26: 33 | J26: R2O-CE-R2T - VIVO OBRAS DE IMPLANTAÇÃO (CEARÁ) | K26: MOT7 | L26: TRANSFERENCIA ENTRE ALMOXARIFADOS | M26: INICIO OBRAS ARMARIO I13 | O26: IMPLANTAÇÃO
A27: e7bcb016 | B27: 623a1962 | D27: TRANSFERENCIA | E27: 45308 | F27: MAT56 | G27: R2056 - BRACADEIRA BAP4 R2 (FRG100) | H27: -20 | I27: 33 | J27: R2O-CE-R2T - VIVO OBRAS DE IMPLANTAÇÃO (CEARÁ) | K27: MOT7 | L27: TRANSFERENCIA ENTRE ALMOXARIFADOS | M27: INICIO OBRAS ARMARIO I13 | O27: IMPLANTAÇÃO
A28: cceca7b8 | B28: 623a1962 | D28: TRANSFERENCIA | E28: 45308 | F28: MAT51 | G28: R2051 - SUP ANCORAGE CABO OPT AS E CORD DIELETR (SUPA - SCO) (0456-0157-7) | H28: -50 | I28: 33 | J28: R2O-CE-R2T - VIVO OBRAS DE IMPLANTAÇÃO (CEARÁ) | K28: MOT7 | L28: TRANSFERENCIA ENTRE ALMOXARIFADOS | M28: INICIO OBRAS ARMARIO I13 | O28: IMPLANTAÇÃO
A29: 9af8d1e8 | B29: 623a1962 | D29: TRANSFERENCIA | E29: 45308 | F29: MAT21 | G29: R2021 - CONJ. SUP. CABOS OPT MEIO DE VAO (RAQUETE) (0460-0084-4) | H29: -2 | I29: 33 | J29: R2O-CE-R2T - VIVO OBRAS DE IMPLANTAÇÃO (CEARÁ) | K29: MOT7 | L29: TRANSFERENCIA ENTRE ALMOXARIFADOS | M29: INICIO OBRAS ARMARIO I13 | O29: IMPLANTAÇÃO
A31: b35447b4 | B31: fe452c3e | C31: 595b307c | D31: ENTRADA | E31: 45308 | F31: MAT12 | G31: R2012 - CABO FIBRA ÓPTICA CFOA SM AS 80 24 F - SAP 0452-0135-5 (0452-0120-3) | H31: 2842 | I31: 33 | J31: R2O-CE-R2T - VIVO OBRAS DE IMPLANTAÇÃO (CEARÁ) | K31: MOT2 | L31: ENTRADA DO CLIENTE | M31: DOC. 3795-2024 - RECEBIDO EM 16/01/2024 | O31: IMPLANTAÇÃO
A32: 5bd514f2 | B32: fe452c3e | C32: 595b307c | D32: ENTRADA | E32: 45308 | F32: MAT15 | G32: R2015 - CABO FIBRA OPTICA CFOA SM AS 80 72F TS (0452-0123-6) | H32: 1391 | I32: 33 | J32: R2O-CE-R2T - VIVO OBRAS DE IMPLANTAÇÃO (CEARÁ) | K32: MOT2 | L32: ENTRADA DO CLIENTE | M32: DOC. 3795-2024 - RECEBIDO EM 16/01/2024 | O32: IMPLANTAÇÃO
A33: cc2fbfbc | B33: fe452c3e | C33: 595b307c | D33: ENTRADA | E33: 45308 | F33: MAT14 | G33: R2014 - CABO FIBRA OPTICA CFOA SM AS 80 36F NR - SAP 0452-0121-4 (0452-0180-2) | H33: 1400 | I33: 33 | J33: R2O-CE-R2T - VIVO OBRAS DE IMPLANTAÇÃO (CEARÁ) | K33: MOT2 | L33: ENTRADA DO CLIENTE | M33: DOC. 3795-2024 - RECEBIDO EM 16/01/2024 | O33: IMPLANTAÇÃO
A34: 45d564c4 | B34: fe452c3e | C34: 595b307c | D34: ENTRADA | E34: 45308 | F34: MAT15 | G34: R2015 - CABO FIBRA OPTICA CFOA SM AS 80 72F TS (0452-0123-6) | H34: 2000 | I34: 33 | J34: R2O-CE-R2T - VIVO OBRAS DE IMPLANTAÇÃO (CEARÁ) | K34: MOT2 | L34: ENTRADA DO CLIENTE | M34: DOC. 3795-2024 - RECEBIDO EM 16/01/2024 | O34: IMPLANTAÇÃO
A35: ad7c6124 | B35: fe452c3e | C35: 595b307c | D35: ENTRADA | E35: 45308 | F35: MAT13 | G35: R2013 - CABO FIBRA ÓPTICA CFOA SM AS 80 144 F (0452-0124-7) | H35: 854 | I35: 33 | J35: R2O-CE-R2T - VIVO OBRAS DE IMPLANTAÇÃO (CEARÁ) | K35: MOT2 | L35: ENTRADA DO CLIENTE | M35: DOC. 3795-2024 - RECEBIDO EM 16/01/2024 | O35: IMPLANTAÇÃO
A36: 8456cc43 | B36: 623a1962 | D36: TRANSFERENCIA | E36: 45308 | F36: MAT13 | G36: R2013 - CABO FIBRA ÓPTICA CFOA SM AS 80 144 F (0452-0124-7) | H36: -854 | I36: 33 | J36: R2O-CE-R2T - VIVO OBRAS DE IMPLANTAÇÃO (CEARÁ) | K36: MOT7 | L36: TRANSFERENCIA ENTRE ALMOXARIFADOS | M36: INICIO OBRAS ARMARIO I13 | O36: IMPLANTAÇÃO
A37: e427cf77 | B37: 623a1962 | D37: TRANSFERENCIA | E37: 45308 | F37: MAT05 | G37: R2005 - ALÇA PREF P/ CFOA SM AS 80 DE 144 FO TS (0256-0245-7) | H37: 20 | I37: 24 | J37: PCE-05-MARCELO GAGO | K37: MOT7 | L37: TRANSFERENCIA ENTRE ALMOXARIFADOS | M37: INICIO OBRAS ARMARIO I13 | N37: x | O37: IMPLANTAÇÃO
A38: 968c13a3 | B38: 623a1962 | D38: TRANSFERENCIA | E38: 45308 | F38: MAT63 | G38: R2063 - PLAQUETA VIVO (MIL035) | H38: 100 | I38: 24 | J38: PCE-05-MARCELO GAGO | K38: MOT7 | L38: TRANSFERENCIA ENTRE ALMOXARIFADOS | M38: INICIO OBRAS ARMARIO I13 | N38: x | O38: IMPLANTAÇÃO
A39: 9621f2f9 | B39: 623a1962 | D39: TRANSFERENCIA | E39: 45308 | F39: MAT56 | G39: R2056 - BRACADEIRA BAP4 R2 (FRG100) | H39: 20 | I39: 24 | J39: PCE-05-MARCELO GAGO | K39: MOT7 | L39: TRANSFERENCIA ENTRE ALMOXARIFADOS | M39: INICIO OBRAS ARMARIO I13 | N39: x | O39: IMPLANTAÇÃO
A40: 8c7a08e8 | B40: 623a1962 | D40: TRANSFERENCIA | E40: 45308 | F40: MAT51 | G40: R2051 - SUP ANCORAGE CABO OPT AS E CORD DIELETR (SUPA - SCO) (0456-0157-7) | H40: 50 | I40: 24 | J40: PCE-05-MARCELO GAGO | K40: MOT7 | L40: TRANSFERENCIA ENTRE ALMOXARIFADOS | M40: INICIO OBRAS ARMARIO I13 | N40: x | O40: IMPLANTAÇÃO
A41: a7773495 | B41: 623a1962 | D41: TRANSFERENCIA | E41: 45308 | F41: MAT21 | G41: R2021 - CONJ. SUP. CABOS OPT MEIO DE VAO (RAQUETE) (0460-0084-4) | H41: 2 | I41: 24 | J41: PCE-05-MARCELO GAGO | K41: MOT7 | L41: TRANSFERENCIA ENTRE ALMOXARIFADOS | M41: INICIO OBRAS ARMARIO I13 | N41: x | O41: IMPLANTAÇÃO
A42: e23ce3ee | B42: 623a1962 | D42: TRANSFERENCIA | E42: 45308 | F42: MAT13 | G42: R2013 - CABO FIBRA ÓPTICA CFOA SM AS 80 144 F (0452-0124-7) | H42: 854 | I42: 24 | J42: PCE-05-MARCELO GAGO | K42: MOT7 | L42: TRANSFERENCIA ENTRE ALMOXARIFADOS | M42: INICIO OBRAS ARMARIO I13 | N42: x | O42: IMPLANTAÇÃO
A43: 9212ff83 | B43: 5b80511b | C43: 595b307c | D43: ENTRADA | E43: 45308 | F43: MAT03 | G43: R2003 - ALÇA ANCORAGEM P/CFOA SM AS - 80 DE 48 A 72 FO - VIVO (0256-0244-6) | H43: 32 | I43: 33 | J43: R2O-CE-R2T - VIVO OBRAS DE IMPLANTAÇÃO (CEARÁ) | K43: MOT2 | L43: ENTRADA DO CLIENTE | M43: DOC. 4002-2024 - RECEBIDO EM 17/01/2024 | O43: IMPLANTAÇÃO
A44: c1d6fcd9 | B44: 5b80511b | C44: 595b307c | D44: ENTRADA | E44: 45308 | F44: MAT07 | G44: R2007 - ALÇA PREF. P/ CORDOALHA DIELETRICA 6,4MM - VIVO (0380-9200-0) | H44: 523 | I44: 33 | J44: R2O-CE-R2T - VIVO OBRAS DE IMPLANTAÇÃO (CEARÁ) | K44: MOT2 | L44: ENTRADA DO CLIENTE | M44: DOC. 4002-2024 - RECEBIDO EM 17/01/2024 | O44: IMPLANTAÇÃO
A45: 885040aa | B45: 5b80511b | C45: 595b307c | D45: ENTRADA | E45: 45308 | F45: MAT10 | G45: R2010 - CABO DROP CIRCULAR 5 MM 12 FIBRAS (0452-1257-7) | H45: 15745 | I45: 33 | J45: R2O-CE-R2T - VIVO OBRAS DE IMPLANTAÇÃO (CEARÁ) | K45: MOT2 | L45: ENTRADA DO CLIENTE | M45: DOC. 4002-2024 - RECEBIDO EM 17/01/2024 | O45: IMPLANTAÇÃO
A46: 73fedd4a | B46: 5b80511b | C46: 595b307c | D46: ENTRADA | E46: 45308 | F46: MAT24 | G46: R2024 - CORDOALHA DIELETRICA 6,4mm - VIVO (0380-9201-1) | H46: 10090 | I46: 33 | J46: R2O-CE-R2T - VIVO OBRAS DE IMPLANTAÇÃO (CEARÁ) | K46: MOT2 | L46: ENTRADA DO CLIENTE | M46: DOC. 4002-2024 - RECEBIDO EM 17/01/2024 | O46: IMPLANTAÇÃO
A47: 1170ebda | B47: 5b80511b | C47: 595b307c | D47: ENTRADA | E47: 45308 | F47: MAT26 | G47: R2026 - CTOPS 1:2 1:8 PRE-C SELADA - 70/30 FC AZUL (0380-9212-2) | H47: 220 | I47: 33 | J47: R2O-CE-R2T - VIVO OBRAS DE IMPLANTAÇÃO (CEARÁ) | K47: MOT2 | L47: ENTRADA DO CLIENTE | M47: DOC. 4002-2024 - RECEBIDO EM 17/01/2024 | O47: IMPLANTAÇÃO
A48: 5b70a623 | B48: 5b80511b | C48: 595b307c | D48: ENTRADA | E48: 45308 | F48: MAT33 | G48: R2033 - DGO 144FO PARA REDE 1 :32 SC-APC PRECONEC (0486-0405-0) | H48: 1 | I48: 33 | J48: R2O-CE-R2T - VIVO OBRAS DE IMPLANTAÇÃO (CEARÁ) | K48: MOT2 | L48: ENTRADA DO CLIENTE | M48: DOC. 4002-2024 - RECEBIDO EM 17/01/2024 | O48: IMPLANTAÇÃO
A49: f84216a2 | B49: 5b80511b | C49: 595b307c | D49: ENTRADA | E49: 45308 | F49: MAT47 | G49: R2047 - LAÇO PREF P/ CFOA SM AS 80 48 A 72 FO (0456-0161-1) | H49: 42 | I49: 33 | J49: R2O-CE-R2T - VIVO OBRAS DE IMPLANTAÇÃO (CEARÁ) | K49: MOT2 | L49: ENTRADA DO CLIENTE | M49: DOC. 4002-2024 - RECEBIDO EM 17/01/2024 | O49: IMPLANTAÇÃO
A50: dd97b2f1 | B50: 5b80511b | C50: 595b307c | D50: ENTRADA | E50: 45308 | F50: MAT48 | G50: R2048 - LAÇO PREF. P/CORDOALHA DIELÉTRICA 6,4 - VIVO (0380-9204-4) | H50: 125 | I50: 33 | J50: R2O-CE-R2T - VIVO OBRAS DE IMPLANTAÇÃO (CEARÁ) | K50: MOT2 | L50: ENTRADA DO CLIENTE | M50: DOC. 4002-2024 - RECEBIDO EM 17/01/2024 | O50: IMPLANTAÇÃO
A51: 3697ef50 | B51: 5b80511b | C51: 595b307c | D51: ENTRADA | E51: 45308 | F51: MAT34 | G51: R2034 - DROP OPT PREC 2PTAS FIG8 UNI 150M PRET (0380-9264-4) | H51: 55 | I51: 33 | J51: R2O-CE-R2T - VIVO OBRAS DE IMPLANTAÇÃO (CEARÁ) | K51: MOT2 | L51: ENTRADA DO CLIENTE | M51: DOC. 4002-2024 - RECEBIDO EM 17/01/2024 | O51: IMPLANTAÇÃO
A52: a5bfe8c3 | B52: 5b80511b | C52: 595b307c | D52: ENTRADA | E52: 45308 | F52: MAT16 | G52: R2016 - CABO PC CFOA-SMDDR 144LSZH 120M (CABO TRANÇADO) (0452-1307-7) | H52: 2 | I52: 33 | J52: R2O-CE-R2T - VIVO OBRAS DE IMPLANTAÇÃO (CEARÁ) | K52: MOT2 | L52: ENTRADA DO CLIENTE | M52: DOC. 4002-2024 - RECEBIDO EM 17/01/2024 | O52: IMPLANTAÇÃO
A53: 625d1f38 | B53: 5b80511b | C53: 595b307c | D53: ENTRADA | E53: 45308 | F53: MAT09 | G53: R2009 - BASTIDOR 42U 19" 600MM (0258-0221-6) | H53: 1 | I53: 33 | J53: R2O-CE-R2T - VIVO OBRAS DE IMPLANTAÇÃO (CEARÁ) | K53: MOT2 | L53: ENTRADA DO CLIENTE | M53: DOC. 4002-2024 - RECEBIDO EM 17/01/2024 | O53: IMPLANTAÇÃO
A54: 1edab43a | B54: 5b80511b | C54: 595b307c | D54: ENTRADA | E54: 45308 | F54: MAT15 | G54: R2015 - CABO FIBRA OPTICA CFOA SM AS 80 72F TS (0452-0123-6) | H54: 862 | I54: 33 | J54: R2O-CE-R2T - VIVO OBRAS DE IMPLANTAÇÃO (CEARÁ) | K54: MOT2 | L54: ENTRADA DO CLIENTE | M54: DOC. 4002-2024 - RECEBIDO EM 17/01/2024 | O54: IMPLANTAÇÃO
A55: 9bc06df7 | B55: 5b80511b | C55: 595b307c | D55: ENTRADA | E55: 45308 | F55: 2294a707 | G55: R2065 - CTOPS 1:2 1:8 PRE-C SELADA - 60/40 FC VERMELHA | H55: 121 | I55: 33 | J55: R2O-CE-R2T - VIVO OBRAS DE IMPLANTAÇÃO (CEARÁ) | K55: MOT2 | L55: ENTRADA DO CLIENTE | M55: DOC. 4002-2024 - RECEBIDO EM 17/01/2024 | O55: IMPLANTAÇÃO
A56: 6688cfb4 | B56: ccce9f84 | D56: INVENTÁRIO | E56: 45308 | F56: MAT53 | G56: R2053 - SUPORTE DE ANCORAGEM (TIPO DM) COM ROLDANA R2 (0456-0167-7) | H56: 240 | I56: 33 | J56: R2O-CE-R2T - VIVO OBRAS DE IMPLANTAÇÃO (CEARÁ) | K56: MOT1 | L56: INVENTÁRIO | M56: AJUSTE INICIAL - OBRAS VIVO | O56: IMPLANTAÇÃO
A57: f5e70152 | B57: ccce9f84 | D57: INVENTÁRIO | E57: 45308 | F57: 0fd3bf3f | G57: R2066 - CTOPS 1:8 PRE-C SELADA VIOLETA | H57: 4 | I57: 33 | J57: R2O-CE-R2T - VIVO OBRAS DE IMPLANTAÇÃO (CEARÁ) | K57: MOT1 | L57: INVENTÁRIO | M57: AJUSTE INICIAL - OBRAS VIVO | O57: IMPLANTAÇÃO
A58: c613264b | B58: 09a822b8 | D58: TRANSFERENCIA | E58: 45308 | F58: 0fd3bf3f | G58: R2066 - CTOPS 1:8 PRE-C SELADA VIOLETA | H58: -2 | I58: 33 | J58: R2O-CE-R2T - VIVO OBRAS DE IMPLANTAÇÃO (CEARÁ) | K58: MOT7 | L58: TRANSFERENCIA ENTRE ALMOXARIFADOS | M58: ARMARIO I13 - BARRAMENTOS 266,267,268,269,267,277,279,280 | O58: IMPLANTAÇÃO
A59: 2058f9c6 | B59: 09a822b8 | D59: TRANSFERENCIA | E59: 45308 | F59: 0fd3bf3f | G59: R2066 - CTOPS 1:8 PRE-C SELADA VIOLETA | H59: 2 | I59: 25 | J59: XCE-05-MARCELO SANTOS / NUW5526 - (859) | K59: MOT7 | L59: TRANSFERENCIA ENTRE ALMOXARIFADOS | M59: ARMARIO I13 - BARRAMENTOS 266,267,268,269,267,277,279,280 | N59: x | O59: IMPLANTAÇÃO
A60: 3f522a0b | B60: 09a822b8 | D60: TRANSFERENCIA | E60: 45308 | F60: 2294a707 | G60: R2065 - CTOPS 1:2 1:8 PRE-C SELADA - 60/40 FC VERMELHA (0380-9211-1) | H60: -6 | I60: 33 | J60: R2O-CE-R2T - VIVO OBRAS DE IMPLANTAÇÃO (CEARÁ) | K60: MOT7 | L60: TRANSFERENCIA ENTRE ALMOXARIFADOS | M60: ARMARIO I13 - BARRAMENTOS 266,267,268,269,267,277,279,280 | O60: IMPLANTAÇÃO
A61: ba8bbe71 | B61: 09a822b8 | D61: TRANSFERENCIA | E61: 45308 | F61: 2294a707 | G61: R2065 - CTOPS 1:2 1:8 PRE-C SELADA - 60/40 FC VERMELHA (0380-9211-1) | H61: 6 | I61: 25 | J61: XCE-05-MARCELO SANTOS / NUW5526 - (859) | K61: MOT7 | L61: TRANSFERENCIA ENTRE ALMOXARIFADOS | M61: ARMARIO I13 - BARRAMENTOS 266,267,268,269,267,277,279,280 | N61: x | O61: IMPLANTAÇÃO
A62: 4e1550ac | B62: 09a822b8 | D62: TRANSFERENCIA | E62: 45308 | F62: MAT26 | G62: R2026 - CTOPS 1:2 1:8 PRE-C SELADA - 70/30 FC AZUL (0380-9212-2) | H62: -16 | I62: 33 | J62: R2O-CE-R2T - VIVO OBRAS DE IMPLANTAÇÃO (CEARÁ) | K62: MOT7 | L62: TRANSFERENCIA ENTRE ALMOXARIFADOS | M62: ARMARIO I13 - BARRAMENTOS 266,267,268,269,267,277,279,280 | O62: IMPLANTAÇÃO
A63: c209ce01 | B63: 09a822b8 | D63: TRANSFERENCIA | E63: 45308 | F63: MAT26 | G63: R2026 - CTOPS 1:2 1:8 PRE-C SELADA - 70/30 FC AZUL (0380-9212-2) | H63: 16 | I63: 25 | J63: XCE-05-MARCELO SANTOS / NUW5526 - (859) | K63: MOT7 | L63: TRANSFERENCIA ENTRE ALMOXARIFADOS | M63: ARMARIO I13 - BARRAMENTOS 266,267,268,269,267,277,279,280 | N63: x | O63: IMPLANTAÇÃO
A64: 1d5d9bad | B64: 09a822b8 | D64: TRANSFERENCIA | E64: 45308 | F64: MAT34 | G64: R2034 - DROP OPT PREC 2PTAS FIG8 UNI 150M PRET (0380-9264-4) | H64: -18 | I64: 33 | J64: R2O-CE-R2T - VIVO OBRAS DE IMPLANTAÇÃO (CEARÁ) | K64: MOT7 | L64: TRANSFERENCIA ENTRE ALMOXARIFADOS | M64: ARMARIO I13 - BARRAMENTOS 266,267,268,269,267,277,279,280 | O64: IMPLANTAÇÃO
A65: a6ad4129 | B65: 09a822b8 | D65: TRANSFERENCIA | E65: 45308 | F65: MAT34 | G65: R2034 - DROP OPT PREC 2PTAS FIG8 UNI 150M PRET (0380-9264-4) | H65: 18 | I65: 25 | J65: XCE-05-MARCELO SANTOS / NUW5526 - (859) | K65: MOT7 | L65: TRANSFERENCIA ENTRE ALMOXARIFADOS | M65: ARMARIO I13 - BARRAMENTOS 266,267,268,269,267,277,279,280 | N65: x | O65: IMPLANTAÇÃO
A66: f7a981a3 | B66: 09a822b8 | D66: TRANSFERENCIA | E66: 45308 | F66: MAT35 | G66: R2035 - DROP OPT PREC 2PTAS FIG8 UNI 200M PRET (0380-9265-5) | H66: -4 | I66: 33 | J66: R2O-CE-R2T - VIVO OBRAS DE IMPLANTAÇÃO (CEARÁ) | K66: MOT7 | L66: TRANSFERENCIA ENTRE ALMOXARIFADOS | M66: ARMARIO I13 - BARRAMENTOS 266,267,268,269,267,277,279,280 | O66: IMPLANTAÇÃO
A67: 79e972e9 | B67: 09a822b8 | D67: TRANSFERENCIA | E67: 45308 | F67: MAT35 | G67: R2035 - DROP OPT PREC 2PTAS FIG8 UNI 200M PRET (0380-9265-5) | H67: 4 | I67: 25 | J67: XCE-05-MARCELO SANTOS / NUW5526 - (859) | K67: MOT7 | L67: TRANSFERENCIA ENTRE ALMOXARIFADOS | M67: ARMARIO I13 - BARRAMENTOS 266,267,268,269,267,277,279,280 | N67: x | O67: IMPLANTAÇÃO
A68: 226638ae | B68: 09a822b8 | D68: TRANSFERENCIA | E68: 45308 | F68: MAT36 | G68: R2036 - DROP OPT PREC 2PTAS FIG8 UNI 300M PRET (0380-9266-6) | H68: -1 | I68: 33 | J68: R2O-CE-R2T - VIVO OBRAS DE IMPLANTAÇÃO (CEARÁ) | K68: MOT7 | L68: TRANSFERENCIA ENTRE ALMOXARIFADOS | M68: ARMARIO I13 - BARRAMENTOS 266,267,268,269,267,277,279,280 | O68: IMPLANTAÇÃO
A69: 54e02da2 | B69: 09a822b8 | D69: TRANSFERENCIA | E69: 45308 | F69: MAT36 | G69: R2036 - DROP OPT PREC 2PTAS FIG8 UNI 300M PRET (0380-9266-6) | H69: 1 | I69: 25 | J69: XCE-05-MARCELO SANTOS / NUW5526 - (859) | K69: MOT7 | L69: TRANSFERENCIA ENTRE ALMOXARIFADOS | M69: ARMARIO I13 - BARRAMENTOS 266,267,268,269,267,277,279,280 | N69: x | O69: IMPLANTAÇÃO
A70: d43891ed | B70: 09a822b8 | D70: TRANSFERENCIA | E70: 45308 | F70: MAT37 | G70: R2037 - DROP OPT PREC 2PTAS FIG8 UNI 400M PRET (0380-9267-7) | H70: -1 | I70: 33 | J70: R2O-CE-R2T - VIVO OBRAS DE IMPLANTAÇÃO (CEARÁ) | K70: MOT7 | L70: TRANSFERENCIA ENTRE ALMOXARIFADOS | M70: ARMARIO I13 - BARRAMENTOS 266,267,268,269,267,277,279,280 | O70: IMPLANTAÇÃO
A71: b7ad3a87 | B71: 09a822b8 | D71: TRANSFERENCIA | E71: 45308 | F71: MAT37 | G71: R2037 - DROP OPT PREC 2PTAS FIG8 UNI 400M PRET (0380-9267-7) | H71: 1 | I71: 25 | J71: XCE-05-MARCELO SANTOS / NUW5526 - (859) | K71: MOT7 | L71: TRANSFERENCIA ENTRE ALMOXARIFADOS | M71: ARMARIO I13 - BARRAMENTOS 266,267,268,269,267,277,279,280 | N71: x | O71: IMPLANTAÇÃO
A72: 26e6161f | B72: 09a822b8 | D72: TRANSFERENCIA | E72: 45308 | F72: MAT55 | G72: R2055 - SUPORTE UNIVERSAL PARA CAIXA BARRAMENTO (0460-0069-9) | H72: -24 | I72: 33 | J72: R2O-CE-R2T - VIVO OBRAS DE IMPLANTAÇÃO (CEARÁ) | K72: MOT7 | L72: TRANSFERENCIA ENTRE ALMOXARIFADOS | M72: ARMARIO I13 - BARRAMENTOS 266,267,268,269,267,277,279,280 | O72: IMPLANTAÇÃO
A73: fa4c0473 | B73: 09a822b8 | D73: TRANSFERENCIA | E73: 45308 | F73: MAT55 | G73: R2055 - SUPORTE UNIVERSAL PARA CAIXA BARRAMENTO (0460-0069-9) | H73: 24 | I73: 25 | J73: XCE-05-MARCELO SANTOS / NUW5526 - (859) | K73: MOT7 | L73: TRANSFERENCIA ENTRE ALMOXARIFADOS | M73: ARMARIO I13 - BARRAMENTOS 266,267,268,269,267,277,279,280 | N73: x | O73: IMPLANTAÇÃO
A74: 191d09e9 | B74: 09a822b8 | D74: TRANSFERENCIA | E74: 45308 | F74: MAT53 | G74: R2053 - SUPORTE DE ANCORAGEM (TIPO DM) COM ROLDANA R2 (0456-0167-7) | H74: -200 | I74: 33 | J74: R2O-CE-R2T - VIVO OBRAS DE IMPLANTAÇÃO (CEARÁ) | K74: MOT7 | L74: TRANSFERENCIA ENTRE ALMOXARIFADOS | M74: ARMARIO I13 - BARRAMENTOS 266,267,268,269,267,277,279,280 | O74: IMPLANTAÇÃO
A75: 2b17fc90 | B75: 09a822b8 | D75: TRANSFERENCIA | E75: 45308 | F75: MAT53 | G75: R2053 - SUPORTE DE ANCORAGEM (TIPO DM) COM ROLDANA R2 (0456-0167-7) | H75: 200 | I75: 25 | J75: XCE-05-MARCELO SANTOS / NUW5526 - (859) | K75: MOT7 | L75: TRANSFERENCIA ENTRE ALMOXARIFADOS | M75: ARMARIO I13 - BARRAMENTOS 266,267,268,269,267,277,279,280 | N75: x | O75: IMPLANTAÇÃO
A76: 4d613f20 | B76: 09a822b8 | D76: TRANSFERENCIA | E76: 45308 | F76: MAT32 | G76: R2032 - CUNHA PLASTICA P/ DROP OPTICO (VERDE) (AOP034) | H76: -200 | I76: 33 | J76: R2O-CE-R2T - VIVO OBRAS DE IMPLANTAÇÃO (CEARÁ) | K76: MOT7 | L76: TRANSFERENCIA ENTRE ALMOXARIFADOS | M76: ARMARIO I13 - BARRAMENTOS 266,267,268,269,267,277,279,280 | O76: IMPLANTAÇÃO
A77: 35daa632 | B77: 09a822b8 | D77: TRANSFERENCIA | E77: 45308 | F77: MAT32 | G77: R2032 - CUNHA PLASTICA P/ DROP OPTICO (VERDE) (AOP034) | H77: 200 | I77: 25 | J77: XCE-05-MARCELO SANTOS / NUW5526 - (859) | K77: MOT7 | L77: TRANSFERENCIA ENTRE ALMOXARIFADOS | M77: ARMARIO I13 - BARRAMENTOS 266,267,268,269,267,277,279,280 | N77: x | O77: IMPLANTAÇÃO
A78: 596ec88a | B78: 09a822b8 | D78: TRANSFERENCIA | E78: 45308 | F78: MAT63 | G78: R2063 - PLAQUETA VIVO (MIL035) | H78: -100 | I78: 33 | J78: R2O-CE-R2T - VIVO OBRAS DE IMPLANTAÇÃO (CEARÁ) | K78: MOT7 | L78: TRANSFERENCIA ENTRE ALMOXARIFADOS | M78: ARMARIO I13 - BARRAMENTOS 266,267,268,269,267,277,279,280 | O78: IMPLANTAÇÃO
A79: f108e309 | B79: 09a822b8 | D79: TRANSFERENCIA | E79: 45308 | F79: MAT63 | G79: R2063 - PLAQUETA VIVO (MIL035) | H79: 100 | I79: 25 | J79: XCE-05-MARCELO SANTOS / NUW5526 - (859) | K79: MOT7 | L79: TRANSFERENCIA ENTRE ALMOXARIFADOS | M79: ARMARIO I13 - BARRAMENTOS 266,267,268,269,267,277,279,280 | N79: x | O79: IMPLANTAÇÃO
A80: 99ad71cf | B80: 09a822b8 | D80: TRANSFERENCIA | E80: 45308 | F80: MAT61 | G80: R2061 - ADESIVO NUMERO VIVO (EMO019) | H80: -1 | I80: 33 | J80: R2O-CE-R2T - VIVO OBRAS DE IMPLANTAÇÃO (CEARÁ) | K80: MOT7 | L80: TRANSFERENCIA ENTRE ALMOXARIFADOS | M80: ARMARIO I13 - BARRAMENTOS 266,267,268,269,267,277,279,280 | O80: IMPLANTAÇÃO
A81: 979110a9 | B81: 09a822b8 | D81: TRANSFERENCIA | E81: 45308 | F81: MAT61 | G81: R2061 - ADESIVO NUMERO VIVO (EMO019) | H81: 1 | I81: 25 | J81: XCE-05-MARCELO SANTOS / NUW5526 - (859) | K81: MOT7 | L81: TRANSFERENCIA ENTRE ALMOXARIFADOS | M81: ARMARIO I13 - BARRAMENTOS 266,267,268,269,267,277,279,280 | N81: x | O81: IMPLANTAÇÃO
A82: ec7d31c5 | B82: 09a822b8 | D82: TRANSFERENCIA | E82: 45308 | F82: MAT62 | G82: R2062 - ADESIVO LETRA VIVO (EMO200) | H82: -1 | I82: 33 | J82: R2O-CE-R2T - VIVO OBRAS DE IMPLANTAÇÃO (CEARÁ) | K82: MOT7 | L82: TRANSFERENCIA ENTRE ALMOXARIFADOS | M82: ARMARIO I13 - BARRAMENTOS 266,267,268,269,267,277,279,280 | O82: IMPLANTAÇÃO
A83: b496b62b | B83: 09a822b8 | D83: TRANSFERENCIA | E83: 45308 | F83: MAT62 | G83: R2062 - ADESIVO LETRA VIVO (EMO200) | H83: 1 | I83: 25 | J83: XCE-05-MARCELO SANTOS / NUW5526 - (859) | K83: MOT7 | L83: TRANSFERENCIA ENTRE ALMOXARIFADOS | M83: ARMARIO I13 - BARRAMENTOS 266,267,268,269,267,277,279,280 | N83: x | O83: IMPLANTAÇÃO
A84: 16562ec0 | B84: 09a822b8 | D84: TRANSFERENCIA | E84: 45308 | F84: MAT24 | G84: R2024 - CORDOALHA DIELETRICA 6,4mm - VIVO (0380-9201-1) | H84: -500 | I84: 33 | J84: R2O-CE-R2T - VIVO OBRAS DE IMPLANTAÇÃO (CEARÁ) | K84: MOT7 | L84: TRANSFERENCIA ENTRE ALMOXARIFADOS | M84: ARMARIO I13 - BARRAMENTOS 266,267,268,269,267,277,279,280 | O84: IMPLANTAÇÃO
A85: dde67bd1 | B85: 09a822b8 | D85: TRANSFERENCIA | E85: 45308 | F85: MAT24 | G85: R2024 - CORDOALHA DIELETRICA 6,4mm - VIVO (0380-9201-1) | H85: 500 | I85: 25 | J85: XCE-05-MARCELO SANTOS / NUW5526 - (859) | K85: MOT7 | L85: TRANSFERENCIA ENTRE ALMOXARIFADOS | M85: ARMARIO I13 - BARRAMENTOS 266,267,268,269,267,277,279,280 | N85: x | O85: IMPLANTAÇÃO
A86: 81f55cb9 | B86: 09a822b8 | D86: TRANSFERENCIA | E86: 45308 | F86: MAT07 | G86: R2007 - ALÇA PREF. P/ CORDOALHA DIELETRICA 6,4MM - VIVO (0380-9200-0) | H86: -20 | I86: 33 | J86: R2O-CE-R2T - VIVO OBRAS DE IMPLANTAÇÃO (CEARÁ) | K86: MOT7 | L86: TRANSFERENCIA ENTRE ALMOXARIFADOS | M86: ARMARIO I13 - BARRAMENTOS 266,267,268,269,267,277,279,280 | O86: IMPLANTAÇÃO
A87: e747cc22 | B87: 09a822b8 | D87: TRANSFERENCIA | E87: 45308 | F87: MAT07 | G87: R2007 - ALÇA PREF. P/ CORDOALHA DIELETRICA 6,4MM - VIVO (0380-9200-0) | H87: 20 | I87: 25 | J87: XCE-05-MARCELO SANTOS / NUW5526 - (859) | K87: MOT7 | L87: TRANSFERENCIA ENTRE ALMOXARIFADOS | M87: ARMARIO I13 - BARRAMENTOS 266,267,268,269,267,277,279,280 | N87: x | O87: IMPLANTAÇÃO
A88: efcfb413 | B88: 09a822b8 | D88: TRANSFERENCIA | E88: 45308 | F88: MAT56 | G88: R2056 - BRACADEIRA BAP4 R2 (FRG100) | H88: -10 | I88: 33 | J88: R2O-CE-R2T - VIVO OBRAS DE IMPLANTAÇÃO (CEARÁ) | K88: MOT7 | L88: TRANSFERENCIA ENTRE ALMOXARIFADOS | M88: ARMARIO I13 - BARRAMENTOS 266,267,268,269,267,277,279,280 | O88: IMPLANTAÇÃO
A89: 23973720 | B89: 09a822b8 | D89: TRANSFERENCIA | E89: 45308 | F89: MAT56 | G89: R2056 - BRACADEIRA BAP4 R2 (FRG100) | H89: 10 | I89: 25 | J89: XCE-05-MARCELO SANTOS / NUW5526 - (859) | K89: MOT7 | L89: TRANSFERENCIA ENTRE ALMOXARIFADOS | M89: ARMARIO I13 - BARRAMENTOS 266,267,268,269,267,277,279,280 | N89: x | O89: IMPLANTAÇÃO
A90: 213e38db | B90: 09a822b8 | D90: TRANSFERENCIA | E90: 45308 | F90: MAT51 | G90: R2051 - SUP ANCORAGE CABO OPT AS E CORD DIELETR (SUPA - SCO) (0456-0157-7) | H90: -10 | I90: 33 | J90: R2O-CE-R2T - VIVO OBRAS DE IMPLANTAÇÃO (CEARÁ) | K90: MOT7 | L90: TRANSFERENCIA ENTRE ALMOXARIFADOS | M90: ARMARIO I13 - BARRAMENTOS 266,267,268,269,267,277,279,280 | O90: IMPLANTAÇÃO
A91: 2f4ea688 | B91: 09a822b8 | D91: TRANSFERENCIA | E91: 45308 | F91: MAT51 | G91: R2051 - SUP ANCORAGE CABO OPT AS E CORD DIELETR (SUPA - SCO) (0456-0157-7) | H91: 10 | I91: 25 | J91: XCE-05-MARCELO SANTOS / NUW5526 - (859) | K91: MOT7 | L91: TRANSFERENCIA ENTRE ALMOXARIFADOS | M91: ARMARIO I13 - BARRAMENTOS 266,267,268,269,267,277,279,280 | N91: x | O91: IMPLANTAÇÃO
A92: cbeed3ab | B92: ccce9f84 | D92: INVENTÁRIO | E92: 45308 | F92: MAT56 | G92: R2056 - BRACADEIRA BAP4 R2 (FRG100) | H92: 10 | I92: 33 | J92: R2O-CE-R2T - VIVO OBRAS DE IMPLANTAÇÃO (CEARÁ) | K92: MOT1 | L92: INVENTÁRIO | M92: AJUSTE INICIAL - OBRAS VIVO | O92: IMPLANTAÇÃO
A93: 086ea3a0 | B93: ccce9f84 | D93: INVENTÁRIO | E93: 45308 | F93: MAT51 | G93: R2051 - SUP ANCORAGE CABO OPT AS E CORD DIELETR (SUPA - SCO) (0456-0157-7) | H93: 75 | I93: 33 | J93: R2O-CE-R2T - VIVO OBRAS DE IMPLANTAÇÃO (CEARÁ) | K93: MOT1 | L93: INVENTÁRIO | M93: AJUSTE INICIAL - OBRAS VIVO | O93: IMPLANTAÇÃO
A94: 683d2ca8 | B94: 8d50b890 | D94: TRANSFERENCIA | E94: 45308 | F94: MAT34 | G94: R2034 - DROP OPT PREC 2PTAS FIG8 UNI 150M PRET (0380-9264-4) | H94: -69 | I94: 33 | J94: R2O-CE-R2T - VIVO OBRAS DE IMPLANTAÇÃO (CEARÁ) | K94: MOT7 | L94: TRANSFERENCIA ENTRE ALMOXARIFADOS | O94: IMPLANTAÇÃO
A95: 2ddf5d95 | B95: 8d50b890 | D95: TRANSFERENCIA | E95: 45308 | F95: MAT34 | G95: R2034 - DROP OPT PREC 2PTAS FIG8 UNI 150M PRET (0380-9264-4) | H95: 69 | I95: 5 | J95: PCE-01-AMARO | K95: MOT7 | L95: TRANSFERENCIA ENTRE ALMOXARIFADOS | N95: x | O95: IMPLANTAÇÃO
A96: fd6482b2 | B96: 8d50b890 | D96: TRANSFERENCIA | E96: 45308 | F96: MAT35 | G96: R2035 - DROP OPT PREC 2PTAS FIG8 UNI 200M PRET (0380-9265-5) | H96: -5 | I96: 33 | J96: R2O-CE-R2T - VIVO OBRAS DE IMPLANTAÇÃO (CEARÁ) | K96: MOT7 | L96: TRANSFERENCIA ENTRE ALMOXARIFADOS | O96: IMPLANTAÇÃO
A97: c540ab1c | B97: 8d50b890 | D97: TRANSFERENCIA | E97: 45308 | F97: MAT35 | G97: R2035 - DROP OPT PREC 2PTAS FIG8 UNI 200M PRET (0380-9265-5) | H97: 5 | I97: 5 | J97: PCE-01-AMARO | K97: MOT7 | L97: TRANSFERENCIA ENTRE ALMOXARIFADOS | N97: x | O97: IMPLANTAÇÃO
A98: f969272d | B98: 8d50b890 | D98: TRANSFERENCIA | E98: 45308 | F98: MAT36 | G98: R2036 - DROP OPT PREC 2PTAS FIG8 UNI 300M PRET (0380-9266-6) | H98: -1 | I98: 33 | J98: R2O-CE-R2T - VIVO OBRAS DE IMPLANTAÇÃO (CEARÁ) | K98: MOT7 | L98: TRANSFERENCIA ENTRE ALMOXARIFADOS | O98: IMPLANTAÇÃO
A99: 47d3f7f6 | B99: 8d50b890 | D99: TRANSFERENCIA | E99: 45308 | F99: MAT36 | G99: R2036 - DROP OPT PREC 2PTAS FIG8 UNI 300M PRET (0380-9266-6) | H99: 1 | I99: 5 | J99: PCE-01-AMARO | K99: MOT7 | L99: TRANSFERENCIA ENTRE ALMOXARIFADOS | N99: x | O99: IMPLANTAÇÃO
A100: e31101e5 | B100: 8d50b890 | D100: TRANSFERENCIA | E100: 45308 | F100: MAT26 | G100: R2026 - CTOPS 1:2 1:8 PRE-C SELADA - 70/30 FC AZUL (0380-9212-2) | H100: -44 | I100: 33 | J100: R2O-CE-R2T - VIVO OBRAS DE IMPLANTAÇÃO (CEARÁ) | K100: MOT7 | L100: TRANSFERENCIA ENTRE ALMOXARIFADOS | O100: IMPLANTAÇÃO
A101: 3689b941 | B101: 8d50b890 | D101: TRANSFERENCIA | E101: 45308 | F101: MAT26 | G101: R2026 - CTOPS 1:2 1:8 PRE-C SELADA - 70/30 FC AZUL (0380-9212-2) | H101: 44 | I101: 5 | J101: PCE-01-AMARO | K101: MOT7 | L101: TRANSFERENCIA ENTRE ALMOXARIFADOS | N101: x | O101: IMPLANTAÇÃO
A104: 5fb43c03 | B104: 8d50b890 | D104: TRANSFERENCIA | E104: 45308 | F104: MAT55 | G104: R2055 - SUPORTE UNIVERSAL PARA CAIXA BARRAMENTO (0460-0069-9) | H104: -65 | I104: 33 | J104: R2O-CE-R2T - VIVO OBRAS DE IMPLANTAÇÃO (CEARÁ) | K104: MOT7 | L104: TRANSFERENCIA ENTRE ALMOXARIFADOS | O104: IMPLANTAÇÃO
A105: 56bfc0d5 | B105: 8d50b890 | D105: TRANSFERENCIA | E105: 45308 | F105: MAT55 | G105: R2055 - SUPORTE UNIVERSAL PARA CAIXA BARRAMENTO (0460-0069-9) | H105: 65 | I105: 5 | J105: PCE-01-AMARO | K105: MOT7 | L105: TRANSFERENCIA ENTRE ALMOXARIFADOS | N105: x | O105: IMPLANTAÇÃO
A106: 03c08204 | B106: 8d50b890 | D106: TRANSFERENCIA | E106: 45308 | F106: MAT32 | G106: R2032 - CUNHA PLASTICA P/ DROP OPTICO (VERDE) (AOP034) | H106: -300 | I106: 33 | J106: R2O-CE-R2T - VIVO OBRAS DE IMPLANTAÇÃO (CEARÁ) | K106: MOT7 | L106: TRANSFERENCIA ENTRE ALMOXARIFADOS | O106: IMPLANTAÇÃO
A107: b95c2463 | B107: 8d50b890 | D107: TRANSFERENCIA | E107: 45308 | F107: MAT32 | G107: R2032 - CUNHA PLASTICA P/ DROP OPTICO (VERDE) (AOP034) | H107: 300 | I107: 5 | J107: PCE-01-AMARO | K107: MOT7 | L107: TRANSFERENCIA ENTRE ALMOXARIFADOS | N107: x | O107: IMPLANTAÇÃO
A108: 33207c2d | B108: 8d50b890 | D108: TRANSFERENCIA | E108: 45308 | F108: MAT07 | G108: R2007 - ALÇA PREF. P/ CORDOALHA DIELETRICA 6,4MM - VIVO (0380-9200-0) | H108: -20 | I108: 33 | J108: R2O-CE-R2T - VIVO OBRAS DE IMPLANTAÇÃO (CEARÁ) | K108: MOT7 | L108: TRANSFERENCIA ENTRE ALMOXARIFADOS | O108: IMPLANTAÇÃO
A109: 33447057 | B109: 8d50b890 | D109: TRANSFERENCIA | E109: 45308 | F109: MAT07 | G109: R2007 - ALÇA PREF. P/ CORDOALHA DIELETRICA 6,4MM - VIVO (0380-9200-0) | H109: 20 | I109: 5 | J109: PCE-01-AMARO | K109: MOT7 | L109: TRANSFERENCIA ENTRE ALMOXARIFADOS | N109: x | O109: IMPLANTAÇÃO
A110: 0f614c18 | B110: 8d50b890 | D110: TRANSFERENCIA | E110: 45308 | F110: MAT24 | G110: R2024 - CORDOALHA DIELETRICA 6,4mm - VIVO (0380-9201-1) | H110: -500 | I110: 33 | J110: R2O-CE-R2T - VIVO OBRAS DE IMPLANTAÇÃO (CEARÁ) | K110: MOT7 | L110: TRANSFERENCIA ENTRE ALMOXARIFADOS | O110: IMPLANTAÇÃO
A111: dde3c182 | B111: 8d50b890 | D111: TRANSFERENCIA | E111: 45308 | F111: MAT24 | G111: R2024 - CORDOALHA DIELETRICA 6,4mm - VIVO (0380-9201-1) | H111: 500 | I111: 5 | J111: PCE-01-AMARO | K111: MOT7 | L111: TRANSFERENCIA ENTRE ALMOXARIFADOS | N111: x | O111: IMPLANTAÇÃO
A112: d5749a14 | B112: 8d50b890 | D112: TRANSFERENCIA | E112: 45308 | F112: MAT63 | G112: R2063 - PLAQUETA VIVO (MIL035) | H112: -300 | I112: 33 | J112: R2O-CE-R2T - VIVO OBRAS DE IMPLANTAÇÃO (CEARÁ) | K112: MOT7 | L112: TRANSFERENCIA ENTRE ALMOXARIFADOS | O112: IMPLANTAÇÃO
A113: e5e7af57 | B113: 8d50b890 | D113: TRANSFERENCIA | E113: 45308 | F113: MAT63 | G113: R2063 - PLAQUETA VIVO (MIL035) | H113: 300 | I113: 5 | J113: PCE-01-AMARO | K113: MOT7 | L113: TRANSFERENCIA ENTRE ALMOXARIFADOS | N113: x | O113: IMPLANTAÇÃO
...

Sheet CadMaterial
A1: IdMaterial | B1: Material | C1: CodMaterial | D1: Descricao | E1: EAN | F1: Interno | G1: Um | H1: VlrUnt | I1: Fornecedor
A2: MAT01 | B2: =CONCATENATE(C2," - ",D2) -> R2001 - ALÇA 4,8MM PRÉ-FORMADA P/ CORDOALHA AÇO - VIVO (0256-0154-7) | C2: R2001 | D2: ALÇA 4,8MM PRÉ-FORMADA P/ CORDOALHA AÇO - VIVO (0256-0154-7) | F2: 0256-0154-7 | G2: UND | H2: 0 | I2: R2T
A3: MAT02 | B3: =CONCATENATE(C3," - ",D3) -> R2002 - ALÇA ANCORAGEM P/CFOA SM AS - 80 DE 18 A 36 FO - VIVO (0256-0243-5) | C3: R2002 | D3: ALÇA ANCORAGEM P/CFOA SM AS - 80 DE 18 A 36 FO - VIVO (0256-0243-5) | F3: 0256-0243-5 | G3: UND | H3: 0 | I3: R2T
A4: MAT03 | B4: =CONCATENATE(C4," - ",D4) -> R2003 - ALÇA ANCORAGEM P/CFOA SM AS - 80 DE 48 A 72 FO - VIVO (0256-0244-6) | C4: R2003 | D4: ALÇA ANCORAGEM P/CFOA SM AS - 80 DE 48 A 72 FO - VIVO (0256-0244-6) | F4: 0256-0244-6 | G4: UND | H4: 0 | I4: R2T
A5: MAT04 | B5: =CONCATENATE(C5," - ",D5) -> R2004 - ALÇA PLASTICA 5MM C/ GANCHO METALICO (0380-9242-2) | C5: R2004 | D5: ALÇA PLASTICA 5MM C/ GANCHO METALICO (0380-9242-2) | F5: 0380-9242-2 | G5: UND | H5: 0 | I5: R2T
A6: MAT05 | B6: =CONCATENATE(C6," - ",D6) -> R2005 - ALÇA PREF P/ CFOA SM AS 80 DE 144 FO TS (0256-0245-7) | C6: R2005 | D6: ALÇA PREF P/ CFOA SM AS 80 DE 144 FO TS (0256-0245-7) | F6: 0256-0245-7 | G6: UND | H6: 0 | I6: R2T
A7: MAT06 | B7: =CONCATENATE(C7," - ",D7) -> R2006 - ALÇA PREF PARA DROP CIRC 5MM ATÉ 24FO (0380-9295-0) | C7: R2006 | D7: ALÇA PREF PARA DROP CIRC 5MM ATÉ 24FO (0380-9295-0) | F7: 0380-9295-0 | G7: UND | H7: 0 | I7: R2T
A8: MAT07 | B8: =CONCATENATE(C8," - ",D8) -> R2007 - ALÇA PREF. P/ CORDOALHA DIELETRICA 6,4MM - VIVO (0380-9200-0) | C8: R2007 | D8: ALÇA PREF. P/ CORDOALHA DIELETRICA 6,4MM - VIVO (0380-9200-0) | F8: 0380-9200-0 | G8: UND | H8: 0 | I8: R2T
A9: MAT08 | B9: =CONCATENATE(C9," - ",D9) -> R2008 - ALÇA PREFORMADA PARA DROP FIG8 (0380-9296-0) | C9: R2008 | D9: ALÇA PREFORMADA PARA DROP FIG8 (0380-9296-0) | F9: 0380-9296-0 | G9: UND | H9: 0 | I9: R2T
A10: MAT09 | B10: =CONCATENATE(C10," - ",D10) -> R2009 - BASTIDOR 42U 19" 600MM (0258-0221-6) | C10: R2009 | D10: BASTIDOR 42U 19" 600MM (0258-0221-6) | F10: 0258-0221-6 | G10: UND | H10: 0 | I10: R2T
A11: MAT10 | B11: =CONCATENATE(C11," - ",D11) -> R2010 - CABO DROP CIRCULAR 5 MM 12 FIBRAS (0452-1257-7) | C11: R2010 | D11: CABO DROP CIRCULAR 5 MM 12 FIBRAS (0452-1257-7) | F11: 0452-1257-7 | G11: UND | H11: 0 | I11: R2T
A12: MAT11 | B12: =CONCATENATE(C12," - ",D12) -> R2011 - CABO DROP CIRCULAR DE 12 FIBRAS - 300M (0452-1262-2) | C12: R2011 | D12: CABO DROP CIRCULAR DE 12 FIBRAS - 300M (0452-1262-2) | F12: 0452-1262-2 | G12: UND | H12: 0 | I12: R2T
A13: MAT12 | B13: =CONCATENATE(C13," - ",D13) -> R2012 - CABO FIBRA ÓPTICA CFOA SM AS 80 24 F - SAP 0452-0135-5 (0452-0120-3) | C13: R2012 | D13: CABO FIBRA ÓPTICA CFOA SM AS 80 24 F - SAP 0452-0135-5 (0452-0120-3) | F13: 0452-0120-3 | G13: UND | H13: 0 | I13: R2T
... A480: 6d206cb5 | B480: =CONCATENATE(C480," - ",D480) -> VT132 - TAMPA RETANGULAR 63CMX39CM R1 (327788) | C480: VT132 | D480: TAMPA RETANGULAR 63CMX39CM R1 (327788) | F480: 327788 | G480: UND | H480: 0 | I480: R2T

Sheet Usuarios
A1: IdUsuario | B1: Email | C1: Nome | D1: Perfil
A2: 1 | B2: andrewsdigital86@gmail.com | C2: Lee Andrew | D2: adm
A3: 2 | B3: leeandrewls@gmail.com | C3: Andrew Tec | D3: tec
A4: 3 | B4: helio.sobreira@gmail.com | C4: Helio Germano | D4: adm
A5: 4 | B5: xonmedicao@gmail.com | C5: Fabricio | D5: adm

Sheet Menu
A1: IdMenu | B1: Nome | C1: Visao | D1: Imagem
A2: 1 | B2: Ordem de Serviço | C2: Os | D2: Menu_Images/1.Imagem.160059.png
A3: 780cf468 | B3: Usuários | C3: Usuarios | D3: Menu_Images/780cf468.Imagem.160445.png
A4: deb469a5 | B4: Equipes | C4: Equipes | D4: Menu_Images/deb469a5.Imagem.160607.png
A5: a96189b8 | B5: Movimentação de Material | C5: Movimentacao_visualizar | D5: Menu_Images/a96189b8.Imagem.161131.png
A6: 8eaecddd | B6: Consultas | C6: MenuConsultas | D6: Menu_Images/8eaecddd.Imagem.195432.png
A7: 38709cb4 | B7: Cadastros | C7: MenuCadastros | D7: Menu_Images/38709cb4.Imagem.195709.png

Sheet MenuCadastros
A1: IdMenu | B1: Nome | C1: Visao | D1: Imagem
A2: 1 | B2: Motivo | C2: Motivo
A3: 2 | B3: Tipo de Movimento | C3: TpMov
A4: 3 | B4: Equipes | C4: Equipes
A5: 4 | B5: Obras | C5: Obras
A6: 5 | B6: Responsavel | C6: Responsavel
A7: 6 | B7: Contrato | C7: Contrato
A8: 7 | B8: Produto | C8: Produtos
A9: 8 | B9: Status Operacao | C9: StatusOperacao
A10: 9 | B10: Status Medição | C10: StatusMedicao

Sheet MenuConsultas
A1: IdMenu | B1: Nome | C1: Visao | D1: Imagem
A2: 1 | B2: Consulta Por Centro/Equipe | C2: RelCentroEquipe
A3: 2 | B3: Consulta Por Material v2 | C3: Consulta Material
A4: 3 | B4: Consulta Por Material v1 | C4: VerEstoque

Sheet Parametros
A1: IdParametro | B1: CodMaterial | C1: Centro | D1: Equipe
A2: 1 | C2: PLANO DE AÇÃO | D2: 53
